Workbook

Sheet DATASHEET
B2: Variable name | D2: House building | E2: Nominal house price | F2: Nominal construction cost | G2: Transactions | H2: Private housing stock | I2: Interest rate | J2: House price (income) deflator | K2: Construction cost deflator
B3: Variable description | D3: Private enterprise starts, # homes | E3: Nominal house prices, £ | F3: Nominal construction cost, index | G3: Sales, # homes | H3: Owner-occupied + privated rented, # homes | I3: BOE official base rate, % | J3: Nominal disposable income / real disposable income, index | K3: GDP deflator, index
B4: Variable geography | D4: Great Britain | E4: United Kingdom | F4: Great Britain | G4: England & Wales | H4: Great Britain | I4: United Kingdom | J4: United Kingdom | K4: United Kingdom
B8: 1975 | C8: Q1 | D8: ='House building'!H8 -> 28800 | E8: ='Nominal house prices'!H8 -> 9179.4362 | F8: ='Nominal construction costs'!H8 -> 10.3 | G8: =Transactions!H8 -> 193500 | H8: ='Private housing stock'!Y8 -> 13573 | I8: ='Interest rate'!H8 -> 10.783333 | J8: ='House price (income) deflator'!H8 -> 13.222943 | K8: ='Construction cost deflator'!H8 -> 10.9778
C9: Q2 | D9: ='House building'!H9 -> 41600 | E9: ='Nominal house prices'!H9 -> 9423.1381 | F9: ='Nominal construction costs'!H9 -> 11.2 | G9: =Transactions!H9 -> 226500 | H9: ='Private housing stock'!Y9 -> 13587.284 | I9: ='Interest rate'!H9 -> 9.9615385 | J9: ='House price (income) deflator'!H9 -> 13.909269 | K9: ='Construction cost deflator'!H9 -> 11.7071
C10: Q3 | D10: ='House building'!H10 -> 41400 | E10: ='Nominal house prices'!H10 -> 9707.4569 | F10: ='Nominal construction costs'!H10 -> 11.7 | G10: =Transactions!H10 -> 236250 | H10: ='Private housing stock'!Y10 -> 13607.917 | I10: ='Interest rate'!H10 -> 10.706522 | J10: ='House price (income) deflator'!H10 -> 14.43728 | K10: ='Construction cost deflator'!H10 -> 12.2219
C11: Q4 | D11: ='House building'!H11 -> 37400 | E11: ='Nominal house prices'!H11 -> 9808.9993 | F11: ='Nominal construction costs'!H11 -> 11.5 | G11: =Transactions!H11 -> 224250 | H11: ='Private housing stock'!Y11 -> 13628.45 | I11: ='Interest rate'!H11 -> 11.730978 | J11: ='House price (income) deflator'!H11 -> 15.154198 | K11: ='Construction cost deflator'!H11 -> 12.7565
B12: 1976 | C12: Q1 | D12: ='House building'!H12 -> 37200 | E12: ='Nominal house prices'!H12 -> 10012.084 | F12: ='Nominal construction costs'!H12 -> 11.4 | G12: =Transactions!H12 -> 201750 | H12: ='Private housing stock'!Y12 -> 13647 | I12: ='Interest rate'!H12 -> 9.8681319 | J12: ='House price (income) deflator'!H12 -> 15.756414 | K12: ='Construction cost deflator'!H12 -> 13.1829
C13: Q2 | D13: ='House building'!H13 -> 46500 | E13: ='Nominal house prices'!H13 -> 10276.095 | F13: ='Nominal construction costs'!H13 -> 12.4 | G13: =Transactions!H13 -> 222750 | H13: ='Private housing stock'!Y13 -> 13672.025 | I13: ='Interest rate'!H13 -> 10.505495 | J13: ='House price (income) deflator'!H13 -> 16.154808 | K13: ='Construction cost deflator'!H13 -> 13.5525
C14: Q3 | D14: ='House building'!H14 -> 42800 | E14: ='Nominal house prices'!H14 -> 10519.796 | F14: ='Nominal construction costs'!H14 -> 12.8 | G14: =Transactions!H14 -> 237000 | H14: ='Private housing stock'!Y14 -> 13703.305 | I14: ='Interest rate'!H14 -> 11.793478 | J14: ='House price (income) deflator'!H14 -> 16.637217 | K14: ='Construction cost deflator'!H14 -> 13.8741
C15: Q4 | D15: ='House building'!H15 -> 28100 | E15: ='Nominal house prices'!H15 -> 10682.264 | F15: ='Nominal construction costs'!H15 -> 12.7 | G15: =Transactions!H15 -> 231000 | H15: ='Private housing stock'!Y15 -> 13732.097 | I15: ='Interest rate'!H15 -> 14.720109 | J15: ='House price (income) deflator'!H15 -> 17.573096 | K15: ='Construction cost deflator'!H15 -> 14.4219
B16: 1977 | C16: Q1 | D16: ='House building'!H16 -> 26200 | E16: ='Nominal house prices'!H16 -> 10763.498 | F16: ='Nominal construction costs'!H16 -> 12.3 | G16: =Transactions!H16 -> 196500 | H16: ='Private housing stock'!Y16 -> 13751 | I16: ='Interest rate'!H16 -> 12.325 | J16: ='House price (income) deflator'!H16 -> 18.243759 | K16: ='Construction cost deflator'!H16 -> 14.9647
C17: Q2 | D17: ='House building'!H17 -> 38100 | E17: ='Nominal house prices'!H17 -> 10925.966 | F17: ='Nominal construction costs'!H17 -> 13.5 | G17: =Transactions!H17 -> 225750 | H17: ='Private housing stock'!Y17 -> 13726.122 | I17: ='Interest rate'!H17 -> 8.4368132 | J17: ='House price (income) deflator'!H17 -> 18.934221 | K17: ='Construction cost deflator'!H17 -> 15.5529
C18: Q3 | D18: ='House building'!H18 -> 39100 | E18: ='Nominal house prices'!H18 -> 11250.902 | F18: ='Nominal construction costs'!H18 -> 14.1 | G18: =Transactions!H18 -> 249750 | H18: ='Private housing stock'!Y18 -> 13689.944 | I18: ='Interest rate'!H18 -> 7.2826087 | J18: ='House price (income) deflator'!H18 -> 19.311428 | K18: ='Construction cost deflator'!H18 -> 15.8767
C19: Q4 | D19: ='House building'!H19 -> 31400 | E19: ='Nominal house prices'!H19 -> 11596.146 | F19: ='Nominal construction costs'!H19 -> 14.1 | G19: =Transactions!H19 -> 257250 | H19: ='Private housing stock'!Y19 -> 13652.816 | I19: ='Interest rate'!H19 -> 5.875 | J19: ='House price (income) deflator'!H19 -> 19.647792 | K19: ='Construction cost deflator'!H19 -> 16.316
B20: 1978 | C20: Q1 | D20: ='House building'!H20 -> 30390 | E20: ='Nominal house prices'!H20 -> 11860.157 | F20: ='Nominal construction costs'!H20 -> 13.6 | G20: =Transactions!H20 -> 248250 | H20: ='Private housing stock'!Y20 -> 13623 | I20: ='Interest rate'!H20 -> 6.5444444 | J20: ='House price (income) deflator'!H20 -> 20.324324 | K20: ='Construction cost deflator'!H20 -> 16.9545
C21: Q2 | D21: ='House building'!H21 -> 46510 | E21: ='Nominal house prices'!H21 -> 12428.794 | F21: ='Nominal construction costs'!H21 -> 15.2 | G21: =Transactions!H21 -> 263250 | H21: ='Private housing stock'!Y21 -> 13650.432 | I21: ='Interest rate'!H21 -> 8.5027473 | J21: ='House price (income) deflator'!H21 -> 20.693377 | K21: ='Construction cost deflator'!H21 -> 17.4266
C22: Q3 | D22: ='House building'!H22 -> 41310 | E22: ='Nominal house prices'!H22 -> 13302.059 | F22: ='Nominal construction costs'!H22 -> 16.3 | G22: =Transactions!H22 -> 261750 | H22: ='Private housing stock'!Y22 -> 13692.416 | I22: ='Interest rate'!H22 -> 10 | J22: ='House price (income) deflator'!H22 -> 21.073563 | K22: ='Construction cost deflator'!H22 -> 17.6786
C23: Q4 | D23: ='House building'!H23 -> 39100 | E23: ='Nominal house prices'!H23 -> 14236.25 | F23: ='Nominal construction costs'!H23 -> 16.6 | G23: =Transactions!H23 -> 250500 | H23: ='Private housing stock'!Y23 -> 13729.705 | I23: ='Interest rate'!H23 -> 11.440217 | J23: ='House price (income) deflator'!H23 -> 21.77632 | K23: ='Construction cost deflator'!H23 -> 18.1534
B24: 1979 | C24: Q1 | D24: ='House building'!H24 -> 23320 | E24: ='Nominal house prices'!H24 -> 14987.664 | F24: ='Nominal construction costs'!H24 -> 16.2 | G24: =Transactions!H24 -> 229500 | H24: ='Private housing stock'!Y24 -> 13765 | I24: ='Interest rate'!H24 -> 13.022222 | J24: ='House price (income) deflator'!H24 -> 22.495944 | K24: ='Construction cost deflator'!H24 -> 18.8287
C25: Q2 | D25: ='House building'!H25 -> 40050 | E25: ='Nominal house prices'!H25 -> 16145.247 | F25: ='Nominal construction costs'!H25 -> 18.2 | G25: =Transactions!H25 -> 235500 | H25: ='Private housing stock'!Y25 -> 13787.671 | I25: ='Interest rate'!H25 -> 12.43956 | J25: ='House price (income) deflator'!H25 -> 22.975937 | K25: ='Construction cost deflator'!H25 -> 19.2827
C26: Q3 | D26: ='House building'!H26 -> 41250 | E26: ='Nominal house prices'!H26 -> 17384.065 | F26: ='Nominal construction costs'!H26 -> 20.1 | G26: =Transactions!H26 -> 258750 | H26: ='Private housing stock'!Y26 -> 13826.605 | I26: ='Interest rate'!H26 -> 14 | J26: ='House price (income) deflator'!H26 -> 24.540922 | K26: ='Construction cost deflator'!H26 -> 20.7477
C27: Q4 | D27: ='House building'!H27 -> 39390 | E27: ='Nominal house prices'!H27 -> 18541.649 | F27: ='Nominal construction costs'!H27 -> 20.6 | G27: =Transactions!H27 -> 255750 | H27: ='Private housing stock'!Y27 -> 13866.707 | I27: ='Interest rate'!H27 -> 15.532609 | J27: ='House price (income) deflator'!H27 -> 25.612205 | K27: ='Construction cost deflator'!H27 -> 21.6294
B28: 1980 | C28: Q1 | D28: ='House building'!H28 -> 24530 | E28: ='Nominal house prices'!H28 -> 19272.754 | F28: ='Nominal construction costs'!H28 -> 20.1 | G28: =Transactions!H28 -> 234000 | H28: ='Private housing stock'!Y28 -> 13905 | I28: ='Interest rate'!H28 -> 17 | J28: ='House price (income) deflator'!H28 -> 26.727327 | K28: ='Construction cost deflator'!H28 -> 22.724
C29: Q2 | D29: ='House building'!H29 -> 29440 | E29: ='Nominal house prices'!H29 -> 20044.477 | F29: ='Nominal construction costs'!H29 -> 23 | G29: =Transactions!H29 -> 246000 | H29: ='Private housing stock'!Y29 -> 13935.785 | I29: ='Interest rate'!H29 -> 17 | J29: ='House price (income) deflator'!H29 -> 27.671739 | K29: ='Construction cost deflator'!H29 -> 23.7775
C30: Q3 | D30: ='House building'!H30 -> 23370 | E30: ='Nominal house prices'!H30 -> 20856.816 | F30: ='Nominal construction costs'!H30 -> 24.5 | G30: =Transactions!H30 -> 231000 | H30: ='Private housing stock'!Y30 -> 13972.731 | I30: ='Interest rate'!H30 -> 16.021739 | J30: ='House price (income) deflator'!H30 -> 28.323628 | K30: ='Construction cost deflator'!H30 -> 24.6711
C31: Q4 | D31: ='House building'!H31 -> 20670 | E31: ='Nominal house prices'!H31 -> 20897.433 | F31: ='Nominal construction costs'!H31 -> 24.5 | G31: =Transactions!H31 -> 239250 | H31: ='Private housing stock'!Y31 -> 14002.06 | I31: ='Interest rate'!H31 -> 15.195652 | J31: ='House price (income) deflator'!H31 -> 29.568832 | K31: ='Construction cost deflator'!H31 -> 25.7582
B32: 1981 | C32: Q1 | D32: ='House building'!H32 -> 26290 | E32: ='Nominal house prices'!H32 -> 20938.05 | F32: ='Nominal construction costs'!H32 -> 23.1 | G32: =Transactions!H32 -> 216000 | H32: ='Private housing stock'!Y32 -> 14028 | I32: ='Interest rate'!H32 -> 13.533333 | J32: ='House price (income) deflator'!H32 -> 30.442952 | K32: ='Construction cost deflator'!H32 -> 26.4908
C33: Q2 | D33: ='House building'!H33 -> 32240 | E33: ='Nominal house prices'!H33 -> 21506.688 | F33: ='Nominal construction costs'!H33 -> 25.3 | G33: =Transactions!H33 -> 246000 | H33: ='Private housing stock'!Y33 -> 14072.757 | I33: ='Interest rate'!H33 -> 12 | J33: ='House price (income) deflator'!H33 -> 31.260893 | K33: ='Construction cost deflator'!H33 -> 26.9733
C34: Q3 | D34: ='House building'!H34 -> 32080 | E34: ='Nominal house prices'!H34 -> 21851.932 | F34: ='Nominal construction costs'!H34 -> 25.5 | G34: =Transactions!H34 -> 263250 | H34: ='Private housing stock'!Y34 -> 14127.643 | I34: ='Interest rate'!H34 -> 12.505326 | J34: ='House price (income) deflator'!H34 -> 31.966598 | K34: ='Construction cost deflator'!H34 -> 27.4242
C35: Q4 | D35: ='House building'!H35 -> 24520 | E35: ='Nominal house prices'!H35 -> 21425.454 | F35: ='Nominal construction costs'!H35 -> 24.5 | G35: =Transactions!H35 -> 288000 | H35: ='Private housing stock'!Y35 -> 14182.257 | I35: ='Interest rate'!H35 -> 14.599022 | J35: ='House price (income) deflator'!H35 -> 33.059927 | K35: ='Construction cost deflator'!H35 -> 28.2612
B36: 1982 | C36: Q1 | D36: ='House building'!H36 -> 31770 | E36: ='Nominal house prices'!H36 -> 20897.433 | F36: ='Nominal construction costs'!H36 -> 23.2 | G36: =Transactions!H36 -> 240000 | H36: ='Private housing stock'!Y36 -> 14224 | I36: ='Interest rate'!H36 -> 13.795 | J36: ='House price (income) deflator'!H36 -> 33.999461 | K36: ='Construction cost deflator'!H36 -> 28.956
C37: Q2 | D37: ='House building'!H37 -> 38120 | E37: ='Nominal house prices'!H37 -> 21811.315 | F37: ='Nominal construction costs'!H37 -> 25.2 | G37: =Transactions!H37 -> 276000 | H37: ='Private housing stock'!Y37 -> 14299.778 | I37: ='Interest rate'!H37 -> 13.021978 | J37: ='House price (income) deflator'!H37 -> 34.443782 | K37: ='Construction cost deflator'!H37 -> 29.2297
C38: Q3 | D38: ='House building'!H38 -> 38000 | E38: ='Nominal house prices'!H38 -> 22359.644 | F38: ='Nominal construction costs'!H38 -> 25.3 | G38: =Transactions!H38 -> 318000 | H38: ='Private housing stock'!Y38 -> 14390.702 | I38: ='Interest rate'!H38 -> 11.364239 | J38: ='House price (income) deflator'!H38 -> 34.840135 | K38: ='Construction cost deflator'!H38 -> 29.6918
C39: Q4 | D39: ='House building'!H39 -> 32140 | E39: ='Nominal house prices'!H39 -> 22684.58 | F39: ='Nominal construction costs'!H39 -> 24.8 | G39: =Transactions!H39 -> 321750 | H39: ='Private housing stock'!Y39 -> 14481.34 | I39: ='Interest rate'!H39 -> 9.701413 | J39: ='House price (income) deflator'!H39 -> 35.671708 | K39: ='Construction cost deflator'!H39 -> 30.3211
B40: 1983 | C40: Q1 | D40: ='House building'!H40 -> 39890 | E40: ='Nominal house prices'!H40 -> 23354.76 | F40: ='Nominal construction costs'!H40 -> 25.6 | G40: =Transactions!H40 -> 302250 | H40: ='Private housing stock'!Y40 -> 14558 | I40: ='Interest rate'!H40 -> 10.794667 | J40: ='House price (income) deflator'!H40 -> 36.393889 | K40: ='Construction cost deflator'!H40 -> 30.8562
C41: Q2 | D41: ='House building'!H41 -> 47850 | E41: ='Nominal house prices'!H41 -> 24167.1 | F41: ='Nominal construction costs'!H41 -> 26.2 | G41: =Transactions!H41 -> 308250 | H41: ='Private housing stock'!Y41 -> 14629.413 | I41: ='Interest rate'!H41 -> 10.032527 | J41: ='House price (income) deflator'!H41 -> 36.432132 | K41: ='Construction cost deflator'!H41 -> 30.9348
C42: Q3 | D42: ='House building'!H42 -> 43730 | E42: ='Nominal house prices'!H42 -> 25182.524 | F42: ='Nominal construction costs'!H42 -> 26.9 | G42: =Transactions!H42 -> 323250 | H42: ='Private housing stock'!Y42 -> 14715.077 | I42: ='Interest rate'!H42 -> 9.5586957 | J42: ='House price (income) deflator'!H42 -> 37.314785 | K42: ='Construction cost deflator'!H42 -> 31.3756
C43: Q4 | D43: ='House building'!H43 -> 37780 | E43: ='Nominal house prices'!H43 -> 25385.609 | F43: ='Nominal construction costs'!H43 -> 27.3 | G43: =Transactions!H43 -> 318000 | H43: ='Private housing stock'!Y43 -> 14793.364 | I43: ='Interest rate'!H43 -> 9.0708696 | J43: ='House price (income) deflator'!H43 -> 37.618284 | K43: ='Construction cost deflator'!H43 -> 31.945
B44: 1984 | C44: Q1 | D44: ='House building'!H44 -> 37090 | E44: ='Nominal house prices'!H44 -> 25588.694 | F44: ='Nominal construction costs'!H44 -> 27.8 | G44: =Transactions!H44 -> 318000 | H44: ='Private housing stock'!Y44 -> 14861 | I44: ='Interest rate'!H44 -> 8.9418681 | J44: ='House price (income) deflator'!H44 -> 38.155344 | K44: ='Construction cost deflator'!H44 -> 32.0195
C45: Q2 | D45: ='House building'!H45 -> 43670 | E45: ='Nominal house prices'!H45 -> 26401.033 | F45: ='Nominal construction costs'!H45 -> 28.3 | G45: =Transactions!H45 -> 320250 | H45: ='Private housing stock'!Y45 -> 14928.112 | I45: ='Interest rate'!H45 -> 8.8417582 | J45: ='House price (income) deflator'!H45 -> 38.725851 | K45: ='Construction cost deflator'!H45 -> 33.008
C46: Q3 | D46: ='House building'!H46 -> 40180 | E46: ='Nominal house prices'!H46 -> 27416.458 | F46: ='Nominal construction costs'!H46 -> 28.8 | G46: =Transactions!H46 -> 342000 | H46: ='Private housing stock'!Y46 -> 15007.129 | I46: ='Interest rate'!H46 -> 10.892935 | J46: ='House price (income) deflator'!H46 -> 39.527526 | K46: ='Construction cost deflator'!H46 -> 33.2646
C47: Q4 | D47: ='House building'!H47 -> 32700 | E47: ='Nominal house prices'!H47 -> 27822.627 | F47: ='Nominal construction costs'!H47 -> 29.1 | G47: =Transactions!H47 -> 339000 | H47: ='Private housing stock'!Y47 -> 15079.832 | I47: ='Interest rate'!H47 -> 9.9673913 | J47: ='House price (income) deflator'!H47 -> 39.998885 | K47: ='Construction cost deflator'!H47 -> 33.7681
B48: 1985 | C48: Q1 | D48: ='House building'!H48 -> 33640 | E48: ='Nominal house prices'!H48 -> 27822.627 | F48: ='Nominal construction costs'!H48 -> 29.5 | G48: =Transactions!H48 -> 303000 | H48: ='Private housing stock'!Y48 -> 15139 | I48: ='Interest rate'!H48 -> 12.847333 | J48: ='House price (income) deflator'!H48 -> 40.285473 | K48: ='Construction cost deflator'!H48 -> 33.8297
C49: Q2 | D49: ='House building'!H49 -> 45460 | E49: ='Nominal house prices'!H49 -> 28838.052 | F49: ='Nominal construction costs'!H49 -> 29.9 | G49: =Transactions!H49 -> 325500 | H49: ='Private housing stock'!Y49 -> 15193.672 | I49: ='Interest rate'!H49 -> 12.478901 | J49: ='House price (income) deflator'!H49 -> 40.113339 | K49: ='Construction cost deflator'!H49 -> 34.7102
C50: Q3 | D50: ='House building'!H50 -> 44650 | E50: ='Nominal house prices'!H50 -> 29447.306 | F50: ='Nominal construction costs'!H50 -> 30.4 | G50: =Transactions!H50 -> 346500 | H50: ='Private housing stock'!Y50 -> 15267.555 | I50: ='Interest rate'!H50 -> 11.570217 | J50: ='House price (income) deflator'!H50 -> 41.5419 | K50: ='Construction cost deflator'!H50 -> 35.2137
C51: Q4 | D51: ='House building'!H51 -> 38690 | E51: ='Nominal house prices'!H51 -> 30462.731 | F51: ='Nominal construction costs'!H51 -> 31 | G51: =Transactions!H51 -> 331500 | H51: ='Private housing stock'!Y51 -> 15340.12 | I51: ='Interest rate'!H51 -> 11.38 | J51: ='House price (income) deflator'!H51 -> 41.961901 | K51: ='Construction cost deflator'!H51 -> 35.9104
B52: 1986 | C52: Q1 | D52: ='House building'!H52 -> 35890 | E52: ='Nominal house prices'!H52 -> 31071.985 | F52: ='Nominal construction costs'!H52 -> 31.9 | G52: =Transactions!H52 -> 292500 | H52: ='Private housing stock'!Y52 -> 15403 | I52: ='Interest rate'!H52 -> 12.08 | J52: ='House price (income) deflator'!H52 -> 42.30237 | K52: ='Construction cost deflator'!H52 -> 35.9949
C53: Q2 | D53: ='House building'!H53 -> 50150 | E53: ='Nominal house prices'!H53 -> 32493.58 | F53: ='Nominal construction costs'!H53 -> 32.4 | G53: =Transactions!H53 -> 313500 | H53: ='Private housing stock'!Y53 -> 15458.567 | I53: ='Interest rate'!H53 -> 10.314066 | J53: ='House price (income) deflator'!H53 -> 42.400727 | K53: ='Construction cost deflator'!H53 -> 36.4128
C54: Q3 | D54: ='House building'!H54 -> 49990 | E54: ='Nominal house prices'!H54 -> 33915.174 | F54: ='Nominal construction costs'!H54 -> 33.2 | G54: =Transactions!H54 -> 374250 | H54: ='Private housing stock'!Y54 -> 15536.213 | I54: ='Interest rate'!H54 -> 9.88 | J54: ='House price (income) deflator'!H54 -> 43.174733 | K54: ='Construction cost deflator'!H54 -> 36.8573
C55: Q4 | D55: ='House building'!H55 -> 39650 | E55: ='Nominal house prices'!H55 -> 34930.598 | F55: ='Nominal construction costs'!H55 -> 33.7 | G55: =Transactions!H55 -> 370500 | H55: ='Private housing stock'!Y55 -> 15613.611 | I55: ='Interest rate'!H55 -> 10.727826 | J55: ='House price (income) deflator'!H55 -> 44.080199 | K55: ='Construction cost deflator'!H55 -> 37.4189
B56: 1987 | C56: Q1 | D56: ='House building'!H56 -> 44270 | E56: ='Nominal house prices'!H56 -> 35946.022 | F56: ='Nominal construction costs'!H56 -> 34.6 | G56: =Transactions!H56 -> 321750 | H56: ='Private housing stock'!Y56 -> 15675 | I56: ='Interest rate'!H56 -> 10.674444 | J56: ='House price (income) deflator'!H56 -> 44.711083 | K56: ='Construction cost deflator'!H56 -> 37.8694
C57: Q2 | D57: ='House building'!H57 -> 51080 | E57: ='Nominal house prices'!H57 -> 37570.701 | F57: ='Nominal construction costs'!H57 -> 35.4 | G57: =Transactions!H57 -> 329250 | H57: ='Private housing stock'!Y57 -> 15774.055 | I57: ='Interest rate'!H57 -> 9.2316484 | J57: ='House price (income) deflator'!H57 -> 44.858318 | K57: ='Construction cost deflator'!H57 -> 38.5077
C58: Q3 | D58: ='House building'!H58 -> 53200 | E58: ='Nominal house prices'!H58 -> 39398.465 | F58: ='Nominal construction costs'!H58 -> 36.4 | G58: =Transactions!H58 -> 400500 | H58: ='Private housing stock'!Y58 -> 15888.349 | I58: ='Interest rate'!H58 -> 9.4886957 | J58: ='House price (income) deflator'!H58 -> 45.432282 | K58: ='Construction cost deflator'!H58 -> 39.1525
C59: Q4 | D59: ='House building'!H59 -> 44520 | E59: ='Nominal house prices'!H59 -> 41731.767 | F59: ='Nominal construction costs'!H59 -> 37.5 | G59: =Transactions!H59 -> 401250 | H59: ='Private housing stock'!Y59 -> 16007.385 | I59: ='Interest rate'!H59 -> 9.0267391 | J59: ='House price (income) deflator'!H59 -> 45.487922 | K59: ='Construction cost deflator'!H59 -> 39.5653
B60: 1988 | C60: Q1 | D60: ='House building'!H60 -> 51200 | E60: ='Nominal house prices'!H60 -> 43482.75 | F60: ='Nominal construction costs'!H60 -> 38.6 | G60: =Transactions!H60 -> 365250 | H60: ='Private housing stock'!Y60 -> 16107 | I60: ='Interest rate'!H60 -> 8.6272527 | J60: ='House price (income) deflator'!H60 -> 46.486187 | K60: ='Construction cost deflator'!H60 -> 39.955
C61: Q2 | D61: ='House building'!H61 -> 61290 | E61: ='Nominal house prices'!H61 -> 46109.225 | F61: ='Nominal construction costs'!H61 -> 40.1 | G61: =Transactions!H61 -> 388500 | H61: ='Private housing stock'!Y61 -> 16199.025 | I61: ='Interest rate'!H61 -> 7.9789011 | J61: ='House price (income) deflator'!H61 -> 47.584957 | K61: ='Construction cost deflator'!H61 -> 40.7764
C62: Q3 | D62: ='House building'!H62 -> 55970 | E62: ='Nominal house prices'!H62 -> 52237.667 | F62: ='Nominal construction costs'!H62 -> 42.1 | G62: =Transactions!H62 -> 462000 | H62: ='Private housing stock'!Y62 -> 16309.185 | I62: ='Interest rate'!H62 -> 10.901739 | J62: ='House price (income) deflator'!H62 -> 47.887036 | K62: ='Construction cost deflator'!H62 -> 41.6271
C63: Q4 | D63: ='House building'!H63 -> 50750 | E63: ='Nominal house prices'!H63 -> 55447.802 | F63: ='Nominal construction costs'!H63 -> 43.8 | G63: =Transactions!H63 -> 395250 | H63: ='Private housing stock'!Y63 -> 16409.784 | I63: ='Interest rate'!H63 -> 12.282174 | J63: ='House price (income) deflator'!H63 -> 48.23332 | K63: ='Construction cost deflator'!H63 -> 42.6328
B64: 1989 | C64: Q1 | D64: ='House building'!H64 -> 46690 | E64: ='Nominal house prices'!H64 -> 56615.125 | F64: ='Nominal construction costs'!H64 -> 45.5 | G64: =Transactions!H64 -> 305250 | H64: ='Private housing stock'!Y64 -> 16501 | I64: ='Interest rate'!H64 -> 12.88 | J64: ='House price (income) deflator'!H64 -> 49.014842 | K64: ='Construction cost deflator'!H64 -> 43.3473
C65: Q2 | D65: ='House building'!H65 -> 50010 | E65: ='Nominal house prices'!H65 -> 58657.938 | F65: ='Nominal construction costs'!H65 -> 47.1 | G65: =Transactions!H65 -> 303750 | H65: ='Private housing stock'!Y65 -> 16611.228 | I65: ='Interest rate'!H65 -> 13.233736 | J65: ='House price (income) deflator'!H65 -> 50.25704 | K65: ='Construction cost deflator'!H65 -> 43.9994
C66: Q3 | D66: ='House building'!H66 -> 40280 | E66: ='Nominal house prices'!H66 -> 60700.752 | F66: ='Nominal construction costs'!H66 -> 48.4 | G66: =Transactions!H66 -> 292500 | H66: ='Private housing stock'!Y66 -> 16729.295 | I66: ='Interest rate'!H66 -> 13.759565 | J66: ='House price (income) deflator'!H66 -> 50.682282 | K66: ='Construction cost deflator'!H66 -> 45.2101
C67: Q4 | D67: ='House building'!H67 -> 32450 | E67: ='Nominal house prices'!H67 -> 59533.43 | F67: ='Nominal construction costs'!H67 -> 49.7 | G67: =Transactions!H67 -> 283500 | H67: ='Private housing stock'!Y67 -> 16824.39 | I67: ='Interest rate'!H67 -> 14.818587 | J67: ='House price (income) deflator'!H67 -> 51.771362 | K67: ='Construction cost deflator'!H67 -> 46.1388
B68: 1990 | C68: Q1 | D68: ='House building'!H68 -> 35980 | E68: ='Nominal house prices'!H68 -> 58249.725 | F68: ='Nominal construction costs'!H68 -> 50.9 | G68: =Transactions!H68 -> 258000 | H68: ='Private housing stock'!Y68 -> 16901 | I68: ='Interest rate'!H68 -> 14.88 | J68: ='House price (income) deflator'!H68 -> 53.120241 | K68: ='Construction cost deflator'!H68 -> 46.9188
C69: Q2 | D69: ='House building'!H69 -> 37390 | E69: ='Nominal house prices'!H69 -> 57726.001 | F69: ='Nominal construction costs'!H69 -> 51.8 | G69: =Transactions!H69 -> 270000 | H69: ='Private housing stock'!Y69 -> 16985.273 | I69: ='Interest rate'!H69 -> 14.88 | J69: ='House price (income) deflator'!H69 -> 53.578868 | K69: ='Construction cost deflator'!H69 -> 47.8913
C70: Q3 | D70: ='House building'!H70 -> 34350 | E70: ='Nominal house prices'!H70 -> 58773.449 | F70: ='Nominal construction costs'!H70 -> 52.5 | G70: =Transactions!H70 -> 261750 | H70: ='Private housing stock'!Y70 -> 17072.848 | I70: ='Interest rate'!H70 -> 14.88 | J70: ='House price (income) deflator'!H70 -> 54.560454 | K70: ='Construction cost deflator'!H70 -> 49.3666
C71: Q4 | D71: ='House building'!H71 -> 29330 | E71: ='Nominal house prices'!H71 -> 57900.576 | F71: ='Nominal construction costs'!H71 -> 52.9 | G71: =Transactions!H71 -> 258750 | H71: ='Private housing stock'!Y71 -> 17153.303 | I71: ='Interest rate'!H71 -> 13.956087 | J71: ='House price (income) deflator'!H71 -> 55.599264 | K71: ='Construction cost deflator'!H71 -> 49.6666
B72: 1991 | C72: Q1 | D72: ='House building'!H72 -> 32010 | E72: ='Nominal house prices'!H72 -> 57085.894 | F72: ='Nominal construction costs'!H72 -> 53 | G72: =Transactions!H72 -> 235500 | H72: ='Private housing stock'!Y72 -> 17222 | I72: ='Interest rate'!H72 -> 13.38 | J72: ='House price (income) deflator'!H72 -> 56.912753 | K72: ='Construction cost deflator'!H72 -> 50.8122
C73: Q2 | D73: ='House building'!H73 -> 38350 | E73: ='Nominal house prices'!H73 -> 56853.128 | F73: ='Nominal construction costs'!H73 -> 52.5 | G73: =Transactions!H73 -> 243000 | H73: ='Private housing stock'!Y73 -> 17145 | I73: ='Interest rate'!H73 -> 11.731648 | J73: ='House price (income) deflator'!H73 -> 58.059921 | K73: ='Construction cost deflator'!H73 -> 51.5787
C74: Q3 | D74: ='House building'!H74 -> 36510 | E74: ='Nominal house prices'!H74 -> 57958.767 | F74: ='Nominal construction costs'!H74 -> 52.4 | G74: =Transactions!H74 -> 264750 | H74: ='Private housing stock'!Y74 -> 17223.603 | I74: ='Interest rate'!H74 -> 10.793043 | J74: ='House price (income) deflator'!H74 -> 59.588418 | K74: ='Construction cost deflator'!H74 -> 52.2071
C75: Q4 | D75: ='House building'!H75 -> 29740 | E75: ='Nominal house prices'!H75 -> 57435.043 | F75: ='Nominal construction costs'!H75 -> 52.1 | G75: =Transactions!H75 -> 236250 | H75: ='Private housing stock'!Y75 -> 17298.435 | I75: ='Interest rate'!H75 -> 10.38 | J75: ='House price (income) deflator'!H75 -> 59.65012 | K75: ='Construction cost deflator'!H75 -> 52.8926
B76: 1992 | C76: Q1 | D76: ='House building'!H76 -> 32040 | E76: ='Nominal house prices'!H76 -> 56503.979 | F76: ='Nominal construction costs'!H76 -> 51.6 | G76: =Transactions!H76 -> 177000 | H76: ='Private housing stock'!Y76 -> 17359.391 | I76: ='Interest rate'!H76 -> 10.38 | J76: ='House price (income) deflator'!H76 -> 60.505087 | K76: ='Construction cost deflator'!H76 -> 53.4255
C77: Q2 | D77: ='House building'!H77 -> 34800 | E77: ='Nominal house prices'!H77 -> 55165.574 | F77: ='Nominal construction costs'!H77 -> 51.1 | G77: =Transactions!H77 -> 198750 | H77: ='Private housing stock'!Y77 -> 17425 | I77: ='Interest rate'!H77 -> 10.066813 | J77: ='House price (income) deflator'!H77 -> 60.681739 | K77: ='Construction cost deflator'!H77 -> 53.718
C78: Q3 | D78: ='House building'!H78 -> 29770 | E78: ='Nominal house prices'!H78 -> 55328.304 | F78: ='Nominal construction costs'!H78 -> 50.7 | G78: =Transactions!H78 -> 275250 | H78: ='Private housing stock'!Y78 -> 17488.136 | I78: ='Interest rate'!H78 -> 9.7821739 | J78: ='House price (income) deflator'!H78 -> 61.595083 | K78: ='Construction cost deflator'!H78 -> 53.5477
C79: Q4 | D79: ='House building'!H79 -> 23550 | E79: ='Nominal house prices'!H79 -> 53212.81 | F79: ='Nominal construction costs'!H79 -> 50.2 | G79: =Transactions!H79 -> 201000 | H79: ='Private housing stock'!Y79 -> 17542.146 | I79: ='Interest rate'!H79 -> 7.5104348 | J79: ='House price (income) deflator'!H79 -> 61.781869 | K79: ='Construction cost deflator'!H79 -> 54.1034
B80: 1993 | C80: Q1 | D80: ='House building'!H80 -> 34910 | E80: ='Nominal house prices'!H80 -> 53484.027 | F80: ='Nominal construction costs'!H80 -> 48.7 | G80: =Transactions!H80 -> 179250 | H80: ='Private housing stock'!Y80 -> 17584.872 | I80: ='Interest rate'!H80 -> 6.1577778 | J80: ='House price (income) deflator'!H80 -> 62.037245 | K80: ='Construction cost deflator'!H80 -> 55.1164
C81: Q2 | D81: ='House building'!H81 -> 38690 | E81: ='Nominal house prices'!H81 -> 53917.975 | F81: ='Nominal construction costs'!H81 -> 50.1 | G81: =Transactions!H81 -> 209250 | H81: ='Private housing stock'!Y81 -> 17643 | I81: ='Interest rate'!H81 -> 5.88 | J81: ='House price (income) deflator'!H81 -> 68.235081 | K81: ='Construction cost deflator'!H81 -> 54.9872
C82: Q3 | D82: ='House building'!H82 -> 36000 | E82: ='Nominal house prices'!H82 -> 55057.087 | F82: ='Nominal construction costs'!H82 -> 50.2 | G82: =Transactions!H82 -> 260250 | H82: ='Private housing stock'!Y82 -> 17707.799 | I82: ='Interest rate'!H82 -> 5.88 | J82: ='House price (income) deflator'!H82 -> 59.63607 | K82: ='Construction cost deflator'!H82 -> 55.5651
C83: Q4 | D83: ='House building'!H83 -> 31310 | E83: ='Nominal house prices'!H83 -> 54026.461 | F83: ='Nominal construction costs'!H83 -> 51.5 | G83: =Transactions!H83 -> 248250 | H83: ='Private housing stock'!Y83 -> 17768.093 | I83: ='Interest rate'!H83 -> 5.6680435 | J83: ='House price (income) deflator'!H83 -> 64.176358 | K83: ='Construction cost deflator'!H83 -> 55.9242
B84: 1994 | C84: Q1 | D84: ='House building'!H84 -> 39280 | E84: ='Nominal house prices'!H84 -> 54623.139 | F84: ='Nominal construction costs'!H84 -> 52.3 | G84: =Transactions!H84 -> 224250 | H84: ='Private housing stock'!Y84 -> 17820.532 | I84: ='Interest rate'!H84 -> 5.2355556 | J84: ='House price (income) deflator'!H84 -> 63.883512 | K84: ='Construction cost deflator'!H84 -> 56.2623
C85: Q2 | D85: ='House building'!H85 -> 44380 | E85: ='Nominal house prices'!H85 -> 55382.547 | F85: ='Nominal construction costs'!H85 -> 53.7 | G85: =Transactions!H85 -> 234000 | H85: ='Private housing stock'!Y85 -> 17879 | I85: ='Interest rate'!H85 -> 5.13 | J85: ='House price (income) deflator'!H85 -> 63.61477 | K85: ='Construction cost deflator'!H85 -> 56.1132
C86: Q3 | D86: ='House building'!H86 -> 41020 | E86: ='Nominal house prices'!H86 -> 56304.686 | F86: ='Nominal construction costs'!H86 -> 54.5 | G86: =Transactions!H86 -> 258750 | H86: ='Private housing stock'!Y86 -> 17947.406 | I86: ='Interest rate'!H86 -> 5.2332609 | J86: ='House price (income) deflator'!H86 -> 65.866475 | K86: ='Construction cost deflator'!H86 -> 56.1499
C87: Q4 | D87: ='House building'!H87 -> 34270 | E87: ='Nominal house prices'!H87 -> 55924.982 | F87: ='Nominal construction costs'!H87 -> 54.6 | G87: =Transactions!H87 -> 239250 | H87: ='Private housing stock'!Y87 -> 18010.633 | I87: ='Interest rate'!H87 -> 5.7658696 | J87: ='House price (income) deflator'!H87 -> 64.126518 | K87: ='Construction cost deflator'!H87 -> 57.0215
B88: 1995 | C88: Q1 | D88: ='House building'!H88 -> 35470 | E88: ='Nominal house prices'!H88 -> 55436.791 | F88: ='Nominal construction costs'!H88 -> 53.9 | G88: =Transactions!H88 -> 213000 | H88: ='Private housing stock'!Y88 -> 18063.455 | I88: ='Interest rate'!H88 -> 6.4522222 | J88: ='House price (income) deflator'!H88 -> 65.461673 | K88: ='Construction cost deflator'!H88 -> 57.205
C89: Q2 | D89: ='House building'!H89 -> 39370 | E89: ='Nominal house prices'!H89 -> 56033.468 | F89: ='Nominal construction costs'!H89 -> 54 | G89: =Transactions!H89 -> 210000 | H89: ='Private housing stock'!Y89 -> 18124 | I89: ='Interest rate'!H89 -> 6.63 | J89: ='House price (income) deflator'!H89 -> 66.403449 | K89: ='Construction cost deflator'!H89 -> 57.764
C90: Q3 | D90: ='House building'!H90 -> 33890 | E90: ='Nominal house prices'!H90 -> 56521.659 | F90: ='Nominal construction costs'!H90 -> 53.9 | G90: =Transactions!H90 -> 223500 | H90: ='Private housing stock'!Y90 -> 18188.584 | I90: ='Interest rate'!H90 -> 6.63 | J90: ='House price (income) deflator'!H90 -> 66.591072 | K90: ='Construction cost deflator'!H90 -> 58.2673
C91: Q4 | D91: ='House building'!H91 -> 25990 | E91: ='Nominal house prices'!H91 -> 55762.251 | F91: ='Nominal construction costs'!H91 -> 54 | G91: =Transactions!H91 -> 204000 | H91: ='Private housing stock'!Y91 -> 18244.179 | I91: ='Interest rate'!H91 -> 6.5783696 | J91: ='House price (income) deflator'!H91 -> 67.670446 | K91: ='Construction cost deflator'!H91 -> 58.8322
B92: 1996 | C92: Q1 | D92: ='House building'!H92 -> 33280 | E92: ='Nominal house prices'!H92 -> 56575.903 | F92: ='Nominal construction costs'!H92 -> 54 | G92: =Transactions!H92 -> 185027 | H92: ='Private housing stock'!Y92 -> 18286.814 | I92: ='Interest rate'!H92 -> 6.1265934 | J92: ='House price (income) deflator'!H92 -> 68.369734 | K92: ='Construction cost deflator'!H92 -> 59.609
C93: Q2 | D93: ='House building'!H93 -> 37720 | E93: ='Nominal house prices'!H93 -> 56630.146 | F93: ='Nominal construction costs'!H93 -> 55.2 | G93: =Transactions!H93 -> 238478 | H93: ='Private housing stock'!Y93 -> 18345 | I93: ='Interest rate'!H93 -> 5.8713187 | J93: ='House price (income) deflator'!H93 -> 69.315572 | K93: ='Construction cost deflator'!H93 -> 60.7563
C94: Q3 | D94: ='House building'!H94 -> 39160 | E94: ='Nominal house prices'!H94 -> 58854.127 | F94: ='Nominal construction costs'!H94 -> 56.1 | G94: =Transactions!H94 -> 279743 | H94: ='Private housing stock'!Y94 -> 18404.803 | I94: ='Interest rate'!H94 -> 5.69 | J94: ='House price (income) deflator'!H94 -> 70.186868 | K94: ='Construction cost deflator'!H94 -> 61.2501
C95: Q4 | D95: ='House building'!H95 -> 35540 | E95: ='Nominal house prices'!H95 -> 59884.752 | F95: ='Nominal construction costs'!H95 -> 57.2 | G95: =Transactions!H95 -> 290748 | H95: ='Private housing stock'!Y95 -> 18466.889 | I95: ='Interest rate'!H95 -> 5.8611957 | J95: ='House price (income) deflator'!H95 -> 69.830287 | K95: ='Construction cost deflator'!H95 -> 61.6322
B96: 1997 | C96: Q1 | D96: ='House building'!H96 -> 42510 | E96: ='Nominal house prices'!H96 -> 60698.404 | F96: ='Nominal construction costs'!H96 -> 57.1 | G96: =Transactions!H96 -> 228736 | H96: ='Private housing stock'!Y96 -> 18523.236 | I96: ='Interest rate'!H96 -> 5.94 | J96: ='House price (income) deflator'!H96 -> 70.223149 | K96: ='Construction cost deflator'!H96 -> 60.5473
C97: Q2 | D97: ='House building'!H97 -> 42510 | E97: ='Nominal house prices'!H97 -> 61946.003 | F97: ='Nominal construction costs'!H97 -> 58.4 | G97: =Transactions!H97 -> 289049 | H97: ='Private housing stock'!Y97 -> 18576 | I97: ='Interest rate'!H97 -> 6.1994505 | J97: ='House price (income) deflator'!H97 -> 70.933906 | K97: ='Construction cost deflator'!H97 -> 60.5804
C98: Q3 | D98: ='House building'!H98 -> 41520 | E98: ='Nominal house prices'!H98 -> 65092.122 | F98: ='Nominal construction costs'!H98 -> 59.4 | G98: =Transactions!H98 -> 316937 | H98: ='Private housing stock'!Y98 -> 18641.709 | I98: ='Interest rate'!H98 -> 6.875 | J98: ='House price (income) deflator'!H98 -> 71.281799 | K98: ='Construction cost deflator'!H98 -> 61.8046
C99: Q4 | D99: ='House building'!H99 -> 36490 | E99: ='Nominal house prices'!H99 -> 64603.931 | F99: ='Nominal construction costs'!H99 -> 60.2 | G99: =Transactions!H99 -> 289365 | H99: ='Private housing stock'!Y99 -> 18705.888 | I99: ='Interest rate'!H99 -> 7.1521739 | J99: ='House price (income) deflator'!H99 -> 70.984157 | K99: ='Construction cost deflator'!H99 -> 60.705
B100: 1998 | C100: Q1 | D100: ='House building'!H100 -> 41870 | E100: ='Nominal house prices'!H100 -> 66231.234 | F100: ='Nominal construction costs'!H100 -> 61.7 | G100: =Transactions!H100 -> 218153 | H100: ='Private housing stock'!Y100 -> 18762.291 | I100: ='Interest rate'!H100 -> 7.25 | J100: ='House price (income) deflator'!H100 -> 71.368127 | K100: ='Construction cost deflator'!H100 -> 61.2826
C101: Q2 | D101: ='House building'!H101 -> 40580 | E101: ='Nominal house prices'!H101 -> 69757.058 | F101: ='Nominal construction costs'!H101 -> 62.1 | G101: =Transactions!H101 -> 279969 | H101: ='Private housing stock'!Y101 -> 18828 | I101: ='Interest rate'!H101 -> 7.3241758 | J101: ='House price (income) deflator'!H101 -> 71.727903 | K101: ='Construction cost deflator'!H101 -> 61.5423
C102: Q3 | D102: ='House building'!H102 -> 40620 | E102: ='Nominal house prices'!H102 -> 72794.69 | F102: ='Nominal construction costs'!H102 -> 62.7 | G102: =Transactions!H102 -> 302169 | H102: ='Private housing stock'!Y102 -> 18888.173 | I102: ='Interest rate'!H102 -> 7.5 | J102: ='House price (income) deflator'!H102 -> 72.095249 | K102: ='Construction cost deflator'!H102 -> 62.1222
C103: Q4 | D103: ='House building'!H103 -> 32040 | E103: ='Nominal house prices'!H103 -> 72469.229 | F103: ='Nominal construction costs'!H103 -> 64.7 | G103: =Transactions!H103 -> 277514 | H103: ='Private housing stock'!Y103 -> 18948.405 | I103: ='Interest rate'!H103 -> 6.8396739 | J103: ='House price (income) deflator'!H103 -> 72.340111 | K103: ='Construction cost deflator'!H103 -> 62.4648
B104: 1999 | C104: Q1 | D104: ='House building'!H104 -> 40410 | E104: ='Nominal house prices'!H104 -> 72903.177 | F104: ='Nominal construction costs'!H104 -> 66.9 | G104: =Transactions!H104 -> 223665 | H104: ='Private housing stock'!Y104 -> 18995.914 | I104: ='Interest rate'!H104 -> 5.7055556 | J104: ='House price (income) deflator'!H104 -> 72.789155 | K104: ='Construction cost deflator'!H104 -> 62.5587
...

Sheet House building
D3: Cat 1 | E3: Cat 2 | F3: Cat 3 | G3: Cat4 | H3: Updated | I3: Previous | J3: Difference
B4: Notes 1 | D4: [Geoff Meen] | E4: House building, UK: Permanent dwellings started & completed by country [ONS] | F4: House building, UK: Permanent dwellings started & completed by country [ONS] | G4: House building, UK: Permanent dwellings started & completed by country [ONS] | H4: Sum cats 1-4
B5: Notes 2 | E5: Private enterprise starts GB | F5: Private enterprise starts GB | G5: Private enterprise starts GB
B6: Link | D6: N/A | E6: https://www.ons.gov.uk/peoplepopulationandcommunity/housing/datasets/ukhousebuildingpermanentdwellingsstartedandcompleted | F6: https://www.ons.gov.uk/peoplepopulationandcommunity/housing/datasets/ukhousebuildingpermanentdwellingsstartedandcompleted | G6: https://www.ons.gov.uk/peoplepopulationandcommunity/housing/datasets/ukhousebuildingpermanentdwellingsstartedandcompleted
B7: Table | D7: N/A | E7: 1b | F7: 1c | G7: 1d
B8: 1975 | C8: Q1 | D8: 28800 | H8: =SUM(D8:G8) -> 28800 | I8: 28800 | J8: =H8-I8 -> 0
C9: Q2 | D9: 41600 | H9: =SUM(D9:G9) -> 41600 | I9: 41600 | J9: =H9-I9 -> 0
C10: Q3 | D10: 41400 | H10: =SUM(D10:G10) -> 41400 | I10: 41400 | J10: =H10-I10 -> 0
C11: Q4 | D11: 37400 | H11: =SUM(D11:G11) -> 37400 | I11: 37400 | J11: =H11-I11 -> 0
B12: 1976 | C12: Q1 | D12: 37200 | H12: =SUM(D12:G12) -> 37200 | I12: 37200 | J12: =H12-I12 -> 0
C13: Q2 | D13: 46500 | H13: =SUM(D13:G13) -> 46500 | I13: 46500 | J13: =H13-I13 -> 0
C14: Q3 | D14: 42800 | H14: =SUM(D14:G14) -> 42800 | I14: 42800 | J14: =H14-I14 -> 0
C15: Q4 | D15: 28100 | H15: =SUM(D15:G15) -> 28100 | I15: 28100 | J15: =H15-I15 -> 0
B16: 1977 | C16: Q1 | D16: 26200 | H16: =SUM(D16:G16) -> 26200 | I16: 26200 | J16: =H16-I16 -> 0
C17: Q2 | D17: 38100 | H17: =SUM(D17:G17) -> 38100 | I17: 38100 | J17: =H17-I17 -> 0
C18: Q3 | D18: 39100 | H18: =SUM(D18:G18) -> 39100 | I18: 39100 | J18: =H18-I18 -> 0
C19: Q4 | D19: 31400 | H19: =SUM(D19:G19) -> 31400 | I19: 31400 | J19: =H19-I19 -> 0
B20: 1978 | C20: Q1 | E20: 25880 | F20: 1490 | G20: 3020 | H20: =SUM(D20:G20) -> 30390 | I20: 30390 | J20: =H20-I20 -> 0
C21: Q2 | E21: 39760 | F21: 2110 | G21: 4640 | H21: =SUM(D21:G21) -> 46510 | I21: 46510 | J21: =H21-I21 -> 0
C22: Q3 | E22: 34490 | F22: 1780 | G22: 5040 | H22: =SUM(D22:G22) -> 41310 | I22: 41310 | J22: =H22-I22 -> 0
C23: Q4 | E23: 33450 | F23: 1790 | G23: 3860 | H23: =SUM(D23:G23) -> 39100 | I23: 39100 | J23: =H23-I23 -> 0
B24: 1979 | C24: Q1 | E24: 19060 | F24: 1460 | G24: 2800 | H24: =SUM(D24:G24) -> 23320 | I24: 23320 | J24: =H24-I24 -> 0
C25: Q2 | E25: 33300 | F25: 2100 | G25: 4650 | H25: =SUM(D25:G25) -> 40050 | I25: 40050 | J25: =H25-I25 -> 0
C26: Q3 | E26: 34260 | F26: 2550 | G26: 4440 | H26: =SUM(D26:G26) -> 41250 | I26: 41250 | J26: =H26-I26 -> 0
C27: Q4 | E27: 34510 | F27: 1470 | G27: 3410 | H27: =SUM(D27:G27) -> 39390 | I27: 39390 | J27: =H27-I27 -> 0
B28: 1980 | C28: Q1 | E28: 20470 | F28: 1300 | G28: 2760 | H28: =SUM(D28:G28) -> 24530 | I28: 24540 | J28: =H28-I28 -> -10
C29: Q2 | E29: 25210 | F29: 1480 | G29: 2750 | H29: =SUM(D29:G29) -> 29440 | I29: 29450 | J29: =H29-I29 -> -10
C30: Q3 | E30: 20120 | F30: 1030 | G30: 2220 | H30: =SUM(D30:G30) -> 23370 | I30: 23390 | J30: =H30-I30 -> -20
C31: Q4 | E31: 17500 | F31: 1220 | G31: 1950 | H31: =SUM(D31:G31) -> 20670 | I31: 20630 | J31: =H31-I31 -> 40
B32: 1981 | C32: Q1 | E32: 22790 | F32: 830 | G32: 2670 | H32: =SUM(D32:G32) -> 26290 | I32: 26290 | J32: =H32-I32 -> 0
C33: Q2 | E33: 27720 | F33: 1330 | G33: 3190 | H33: =SUM(D33:G33) -> 32240 | I33: 32280 | J33: =H33-I33 -> -40
C34: Q3 | E34: 27830 | F34: 1340 | G34: 2910 | H34: =SUM(D34:G34) -> 32080 | I34: 32040 | J34: =H34-I34 -> 40
C35: Q4 | E35: 21270 | F35: 990 | G35: 2260 | H35: =SUM(D35:G35) -> 24520 | I35: 24510 | J35: =H35-I35 -> 10
B36: 1982 | C36: Q1 | E36: 27730 | F36: 980 | G36: 3060 | H36: =SUM(D36:G36) -> 31770 | I36: 31730 | J36: =H36-I36 -> 40
C37: Q2 | E37: 33340 | F37: 1420 | G37: 3360 | H37: =SUM(D37:G37) -> 38120 | I37: 38050 | J37: =H37-I37 -> 70
C38: Q3 | E38: 33340 | F38: 1650 | G38: 3010 | H38: =SUM(D38:G38) -> 38000 | I38: 38010 | J38: =H38-I38 -> -10
C39: Q4 | E39: 28050 | F39: 1390 | G39: 2700 | H39: =SUM(D39:G39) -> 32140 | I39: 32260 | J39: =H39-I39 -> -120
B40: 1983 | C40: Q1 | E40: 34450 | F40: 1720 | G40: 3720 | H40: =SUM(D40:G40) -> 39890 | I40: 39920 | J40: =H40-I40 -> -30
C41: Q2 | E41: 41890 | F41: 1730 | G41: 4230 | H41: =SUM(D41:G41) -> 47850 | I41: 47810 | J41: =H41-I41 -> 40
C42: Q3 | E42: 38600 | F42: 1450 | G42: 3680 | H42: =SUM(D42:G42) -> 43730 | I42: 43830 | J42: =H42-I42 -> -100
C43: Q4 | E43: 32900 | F43: 1320 | G43: 3560 | H43: =SUM(D43:G43) -> 37780 | I43: 37830 | J43: =H43-I43 -> -50
B44: 1984 | C44: Q1 | E44: 31910 | F44: 1280 | G44: 3900 | H44: =SUM(D44:G44) -> 37090 | I44: 37100 | J44: =H44-I44 -> -10
C45: Q2 | E45: 37980 | F45: 1620 | G45: 4070 | H45: =SUM(D45:G45) -> 43670 | I45: 43710 | J45: =H45-I45 -> -40
C46: Q3 | E46: 34830 | F46: 1380 | G46: 3970 | H46: =SUM(D46:G46) -> 40180 | I46: 40270 | J46: =H46-I46 -> -90
C47: Q4 | E47: 28690 | F47: 1330 | G47: 2680 | H47: =SUM(D47:G47) -> 32700 | I47: 32640 | J47: =H47-I47 -> 60
B48: 1985 | C48: Q1 | E48: 28470 | F48: 1710 | G48: 3460 | H48: =SUM(D48:G48) -> 33640 | I48: 33420 | J48: =H48-I48 -> 220
C49: Q2 | E49: 39720 | F49: 2180 | G49: 3560 | H49: =SUM(D49:G49) -> 45460 | I49: 45470 | J49: =H49-I49 -> -10
C50: Q3 | E50: 39110 | F50: 1600 | G50: 3940 | H50: =SUM(D50:G50) -> 44650 | I50: 44670 | J50: =H50-I50 -> -20
C51: Q4 | E51: 33810 | F51: 1740 | G51: 3140 | H51: =SUM(D51:G51) -> 38690 | I51: 38740 | J51: =H51-I51 -> -50
B52: 1986 | C52: Q1 | E52: 30860 | F52: 1440 | G52: 3590 | H52: =SUM(D52:G52) -> 35890 | I52: 35980 | J52: =H52-I52 -> -90
C53: Q2 | E53: 44470 | F53: 2110 | G53: 3570 | H53: =SUM(D53:G53) -> 50150 | I53: 50180 | J53: =H53-I53 -> -30
C54: Q3 | E54: 43910 | F54: 2160 | G54: 3920 | H54: =SUM(D54:G54) -> 49990 | I54: 50070 | J54: =H54-I54 -> -80
C55: Q4 | E55: 34750 | F55: 1480 | G55: 3420 | H55: =SUM(D55:G55) -> 39650 | I55: 39620 | J55: =H55-I55 -> 30
B56: 1987 | C56: Q1 | E56: 39030 | F56: 1890 | G56: 3350 | H56: =SUM(D56:G56) -> 44270 | I56: 44320 | J56: =H56-I56 -> -50
C57: Q2 | E57: 44760 | F57: 2470 | G57: 3850 | H57: =SUM(D57:G57) -> 51080 | I57: 51110 | J57: =H57-I57 -> -30
C58: Q3 | E58: 47370 | F58: 2630 | G58: 3200 | H58: =SUM(D58:G58) -> 53200 | I58: 53160 | J58: =H58-I58 -> 40
C59: Q4 | E59: 40040 | F59: 1820 | G59: 2660 | H59: =SUM(D59:G59) -> 44520 | I59: 44540 | J59: =H59-I59 -> -20
B60: 1988 | C60: Q1 | E60: 45040 | F60: 2390 | G60: 3770 | H60: =SUM(D60:G60) -> 51200 | I60: 51260 | J60: =H60-I60 -> -60
C61: Q2 | E61: 54280 | F61: 2980 | G61: 4030 | H61: =SUM(D61:G61) -> 61290 | I61: 61310 | J61: =H61-I61 -> -20
C62: Q3 | E62: 49640 | F62: 2720 | G62: 3610 | H62: =SUM(D62:G62) -> 55970 | I62: 56010 | J62: =H62-I62 -> -40
C63: Q4 | E63: 44520 | F63: 2640 | G63: 3590 | H63: =SUM(D63:G63) -> 50750 | I63: 50790 | J63: =H63-I63 -> -40
B64: 1989 | C64: Q1 | E64: 40220 | F64: 2170 | G64: 4300 | H64: =SUM(D64:G64) -> 46690 | I64: 46690 | J64: =H64-I64 -> 0
C65: Q2 | E65: 41780 | F65: 3110 | G65: 5120 | H65: =SUM(D65:G65) -> 50010 | I65: 50090 | J65: =H65-I65 -> -80
C66: Q3 | E66: 33390 | F66: 2670 | G66: 4220 | H66: =SUM(D66:G66) -> 40280 | I66: 40310 | J66: =H66-I66 -> -30
C67: Q4 | E67: 26070 | F67: 2010 | G67: 4370 | H67: =SUM(D67:G67) -> 32450 | I67: 32750 | J67: =H67-I67 -> -300
B68: 1990 | C68: Q1 | E68: 29470 | F68: 1970 | G68: 4540 | H68: =SUM(D68:G68) -> 35980 | I68: 35980 | J68: =H68-I68 -> 0
C69: Q2 | E69: 30440 | F69: 2140 | G69: 4810 | H69: =SUM(D69:G69) -> 37390 | I69: 37390 | J69: =H69-I69 -> 0
C70: Q3 | E70: 28310 | F70: 1960 | G70: 4080 | H70: =SUM(D70:G70) -> 34350 | I70: 34350 | J70: =H70-I70 -> 0
C71: Q4 | E71: 24510 | F71: 1610 | G71: 3210 | H71: =SUM(D71:G71) -> 29330 | I71: 29330 | J71: =H71-I71 -> 0
B72: 1991 | C72: Q1 | E72: 25700 | F72: 1560 | G72: 4750 | H72: =SUM(D72:G72) -> 32010 | I72: 32010 | J72: =H72-I72 -> 0
C73: Q2 | E73: 32500 | F73: 1960 | G73: 3890 | H73: =SUM(D73:G73) -> 38350 | I73: 38350 | J73: =H73-I73 -> 0
C74: Q3 | E74: 31460 | F74: 1850 | G74: 3200 | H74: =SUM(D74:G74) -> 36510 | I74: 36510 | J74: =H74-I74 -> 0
C75: Q4 | E75: 24650 | F75: 1340 | G75: 3750 | H75: =SUM(D75:G75) -> 29740 | I75: 29740 | J75: =H75-I75 -> 0
B76: 1992 | C76: Q1 | E76: 26940 | F76: 1550 | G76: 3550 | H76: =SUM(D76:G76) -> 32040 | I76: 32040 | J76: =H76-I76 -> 0
C77: Q2 | E77: 28910 | F77: 1640 | G77: 4250 | H77: =SUM(D77:G77) -> 34800 | I77: 34800 | J77: =H77-I77 -> 0
C78: Q3 | E78: 24510 | F78: 1420 | G78: 3840 | H78: =SUM(D78:G78) -> 29770 | I78: 29770 | J78: =H78-I78 -> 0
C79: Q4 | E79: 19230 | F79: 1400 | G79: 2920 | H79: =SUM(D79:G79) -> 23550 | I79: 23550 | J79: =H79-I79 -> 0
B80: 1993 | C80: Q1 | E80: 29110 | F80: 1860 | G80: 3940 | H80: =SUM(D80:G80) -> 34910 | I80: 34910 | J80: =H80-I80 -> 0
C81: Q2 | E81: 31560 | F81: 2020 | G81: 5110 | H81: =SUM(D81:G81) -> 38690 | I81: 38690 | J81: =H81-I81 -> 0
C82: Q3 | E82: 30130 | F82: 1860 | G82: 4010 | H82: =SUM(D82:G82) -> 36000 | I82: 36000 | J82: =H82-I82 -> 0
C83: Q4 | E83: 25660 | F83: 1560 | G83: 4090 | H83: =SUM(D83:G83) -> 31310 | I83: 31310 | J83: =H83-I83 -> 0
B84: 1994 | C84: Q1 | E84: 32590 | F84: 1860 | G84: 4830 | H84: =SUM(D84:G84) -> 39280 | I84: 39280 | J84: =H84-I84 -> 0
C85: Q2 | E85: 36980 | F85: 1890 | G85: 5510 | H85: =SUM(D85:G85) -> 44380 | I85: 44380 | J85: =H85-I85 -> 0
C86: Q3 | E86: 33470 | F86: 1810 | G86: 5740 | H86: =SUM(D86:G86) -> 41020 | I86: 41020 | J86: =H86-I86 -> 0
C87: Q4 | E87: 28360 | F87: 1750 | G87: 4160 | H87: =SUM(D87:G87) -> 34270 | I87: 34270 | J87: =H87-I87 -> 0
B88: 1995 | C88: Q1 | E88: 29220 | F88: 1700 | G88: 4550 | H88: =SUM(D88:G88) -> 35470 | I88: 35470 | J88: =H88-I88 -> 0
C89: Q2 | E89: 33040 | F89: 1990 | G89: 4340 | H89: =SUM(D89:G89) -> 39370 | I89: 39370 | J89: =H89-I89 -> 0
C90: Q3 | E90: 27280 | F90: 1570 | G90: 5040 | H90: =SUM(D90:G90) -> 33890 | I90: 33890 | J90: =H90-I90 -> 0
C91: Q4 | E91: 20870 | F91: 1510 | G91: 3610 | H91: =SUM(D91:G91) -> 25990 | I91: 25990 | J91: =H91-I91 -> 0
B92: 1996 | C92: Q1 | E92: 26960 | F92: 1380 | G92: 4940 | H92: =SUM(D92:G92) -> 33280 | I92: 33280 | J92: =H92-I92 -> 0
C93: Q2 | E93: 31590 | F93: 1780 | G93: 4350 | H93: =SUM(D93:G93) -> 37720 | I93: 37720 | J93: =H93-I93 -> 0
C94: Q3 | E94: 33100 | F94: 1950 | G94: 4110 | H94: =SUM(D94:G94) -> 39160 | I94: 39160 | J94: =H94-I94 -> 0
C95: Q4 | E95: 29940 | F95: 1590 | G95: 4010 | H95: =SUM(D95:G95) -> 35540 | I95: 35540 | J95: =H95-I95 -> 0
B96: 1997 | C96: Q1 | E96: 35320 | F96: 1740 | G96: 5450 | H96: =SUM(D96:G96) -> 42510 | I96: 42510 | J96: =H96-I96 -> 0
C97: Q2 | E97: 35360 | F97: 2280 | G97: 4870 | H97: =SUM(D97:G97) -> 42510 | I97: 42510 | J97: =H97-I97 -> 0
C98: Q3 | E98: 34340 | F98: 1920 | G98: 5260 | H98: =SUM(D98:G98) -> 41520 | I98: 41520 | J98: =H98-I98 -> 0
C99: Q4 | E99: 31060 | F99: 1560 | G99: 3870 | H99: =SUM(D99:G99) -> 36490 | I99: 36490 | J99: =H99-I99 -> 0
B100: 1998 | C100: Q1 | E100: 35530 | F100: 1800 | G100: 4540 | H100: =SUM(D100:G100) -> 41870 | I100: 41870 | J100: =H100-I100 -> 0
C101: Q2 | E101: 34770 | F101: 2030 | G101: 3780 | H101: =SUM(D101:G101) -> 40580 | I101: 40580 | J101: =H101-I101 -> 0
C102: Q3 | E102: 34240 | F102: 2050 | G102: 4330 | H102: =SUM(D102:G102) -> 40620 | I102: 40620 | J102: =H102-I102 -> 0
...

Sheet Nominal house prices
D3: Cat 1 | E3: Cat 2 | F3: Cat 3 | G3: Cat4 | H3: Updated | I3: Previous | J3: Difference | L3: Raw data download processing..
B4: Notes 1 | D4: House Price Index [ONS, Land Registry] | H4: Cat 1
B5: Notes 2 | D5: Nominal house prices, UK
B6: Link | D6: UK House Price Index: data downloads September 2022 - GOV.UK (www.gov.uk)
B7: Table | D7: Average price, extract UK data
B8: 1975 | C8: Q1 | D8: 9179.4362 | H8: =SUM(D8:G8) -> 9179.4362 | I8: 9179.4362 | J8: =H8-I8 -> 0 | L8: 1975 | M8: January | N8: 9179.4362
C9: Q2 | D9: 9423.1381 | H9: =SUM(D9:G9) -> 9423.1381 | I9: 9423.1381 | J9: =H9-I9 -> 0 | L9: 1975 | M9: February | N9: 9179.4362
C10: Q3 | D10: 9707.4569 | H10: =SUM(D10:G10) -> 9707.4569 | I10: 9707.4569 | J10: =H10-I10 -> 0 | L10: 1975 | M10: March | N10: 9179.4362 | O10: =AVERAGE(N8:N10) -> 9179.4362
C11: Q4 | D11: 9808.9993 | H11: =SUM(D11:G11) -> 9808.9993 | I11: 9808.9993 | J11: =H11-I11 -> 0 | L11: 1975 | M11: April | N11: 9423.1381 | O11: =AVERAGE(N9:N11) -> 9260.6702
B12: 1976 | C12: Q1 | D12: 10012.084 | H12: =SUM(D12:G12) -> 10012.084 | I12: 10012.084 | J12: =H12-I12 -> 0 | L12: 1975 | M12: May | N12: 9423.1381 | O12: =AVERAGE(N10:N12) -> 9341.9041
C13: Q2 | D13: 10276.095 | H13: =SUM(D13:G13) -> 10276.095 | I13: 10276.095 | J13: =H13-I13 -> 0 | L13: 1975 | M13: June | N13: 9423.1381 | O13: =AVERAGE(N11:N13) -> 9423.1381
C14: Q3 | D14: 10519.796 | H14: =SUM(D14:G14) -> 10519.796 | I14: 10519.796 | J14: =H14-I14 -> 0 | L14: 1975 | M14: July | N14: 9707.4569 | O14: =AVERAGE(N12:N14) -> 9517.911
C15: Q4 | D15: 10682.264 | H15: =SUM(D15:G15) -> 10682.264 | I15: 10682.264 | J15: =H15-I15 -> 0 | L15: 1975 | M15: August | N15: 9707.4569 | O15: =AVERAGE(N13:N15) -> 9612.684
B16: 1977 | C16: Q1 | D16: 10763.498 | H16: =SUM(D16:G16) -> 10763.498 | I16: 10763.498 | J16: =H16-I16 -> 0 | L16: 1975 | M16: September | N16: 9707.4569 | O16: =AVERAGE(N14:N16) -> 9707.4569
C17: Q2 | D17: 10925.966 | H17: =SUM(D17:G17) -> 10925.966 | I17: 10925.966 | J17: =H17-I17 -> 0 | L17: 1975 | M17: October | N17: 9808.9993 | O17: =AVERAGE(N15:N17) -> 9741.3044
C18: Q3 | D18: 11250.902 | H18: =SUM(D18:G18) -> 11250.902 | I18: 11250.902 | J18: =H18-I18 -> 0 | L18: 1975 | M18: November | N18: 9808.9993 | O18: =AVERAGE(N16:N18) -> 9775.1519
C19: Q4 | D19: 11596.146 | H19: =SUM(D19:G19) -> 11596.146 | I19: 11596.146 | J19: =H19-I19 -> 0 | L19: 1975 | M19: December | N19: 9808.9993 | O19: =AVERAGE(N17:N19) -> 9808.9993
B20: 1978 | C20: Q1 | D20: 11860.157 | H20: =SUM(D20:G20) -> 11860.157 | I20: 11860.157 | J20: =H20-I20 -> 0 | L20: 1976 | M20: January | N20: 10012.084 | O20: =AVERAGE(N18:N20) -> 9876.6943
C21: Q2 | D21: 12428.794 | H21: =SUM(D21:G21) -> 12428.794 | I21: 12428.794 | J21: =H21-I21 -> 0 | L21: 1976 | M21: February | N21: 10012.084 | O21: =AVERAGE(N19:N21) -> 9944.3892
C22: Q3 | D22: 13302.059 | H22: =SUM(D22:G22) -> 13302.059 | I22: 13302.059 | J22: =H22-I22 -> 0 | L22: 1976 | M22: March | N22: 10012.084 | O22: =AVERAGE(N20:N22) -> 10012.084
C23: Q4 | D23: 14236.25 | H23: =SUM(D23:G23) -> 14236.25 | I23: 14236.25 | J23: =H23-I23 -> 0 | L23: 1976 | M23: April | N23: 10276.095 | O23: =AVERAGE(N21:N23) -> 10100.088
B24: 1979 | C24: Q1 | D24: 14987.664 | H24: =SUM(D24:G24) -> 14987.664 | I24: 14987.664 | J24: =H24-I24 -> 0 | L24: 1976 | M24: May | N24: 10276.095 | O24: =AVERAGE(N22:N24) -> 10188.091
C25: Q2 | D25: 16145.247 | H25: =SUM(D25:G25) -> 16145.247 | I25: 16145.247 | J25: =H25-I25 -> 0 | L25: 1976 | M25: June | N25: 10276.095 | O25: =AVERAGE(N23:N25) -> 10276.095
C26: Q3 | D26: 17384.065 | H26: =SUM(D26:G26) -> 17384.065 | I26: 17384.065 | J26: =H26-I26 -> 0 | L26: 1976 | M26: July | N26: 10519.796 | O26: =AVERAGE(N24:N26) -> 10357.328
C27: Q4 | D27: 18541.649 | H27: =SUM(D27:G27) -> 18541.649 | I27: 18541.649 | J27: =H27-I27 -> 0 | L27: 1976 | M27: August | N27: 10519.796 | O27: =AVERAGE(N25:N27) -> 10438.562
B28: 1980 | C28: Q1 | D28: 19272.754 | H28: =SUM(D28:G28) -> 19272.754 | I28: 19272.754 | J28: =H28-I28 -> 0 | L28: 1976 | M28: September | N28: 10519.796 | O28: =AVERAGE(N26:N28) -> 10519.796
C29: Q2 | D29: 20044.477 | H29: =SUM(D29:G29) -> 20044.477 | I29: 20044.477 | J29: =H29-I29 -> 0 | L29: 1976 | M29: October | N29: 10682.264 | O29: =AVERAGE(N27:N29) -> 10573.952
C30: Q3 | D30: 20856.816 | H30: =SUM(D30:G30) -> 20856.816 | I30: 20856.816 | J30: =H30-I30 -> 0 | L30: 1976 | M30: November | N30: 10682.264 | O30: =AVERAGE(N28:N30) -> 10628.108
C31: Q4 | D31: 20897.433 | H31: =SUM(D31:G31) -> 20897.433 | I31: 20897.433 | J31: =H31-I31 -> 0 | L31: 1976 | M31: December | N31: 10682.264 | O31: =AVERAGE(N29:N31) -> 10682.264
B32: 1981 | C32: Q1 | D32: 20938.05 | H32: =SUM(D32:G32) -> 20938.05 | I32: 20938.05 | J32: =H32-I32 -> 0 | L32: 1977 | M32: January | N32: 10763.498 | O32: =AVERAGE(N30:N32) -> 10709.342
C33: Q2 | D33: 21506.688 | H33: =SUM(D33:G33) -> 21506.688 | I33: 21506.688 | J33: =H33-I33 -> 0 | L33: 1977 | M33: February | N33: 10763.498 | O33: =AVERAGE(N31:N33) -> 10736.42
C34: Q3 | D34: 21851.932 | H34: =SUM(D34:G34) -> 21851.932 | I34: 21851.932 | J34: =H34-I34 -> 0 | L34: 1977 | M34: March | N34: 10763.498 | O34: =AVERAGE(N32:N34) -> 10763.498
C35: Q4 | D35: 21425.454 | H35: =SUM(D35:G35) -> 21425.454 | I35: 21425.454 | J35: =H35-I35 -> 0 | L35: 1977 | M35: April | N35: 10925.966 | O35: =AVERAGE(N33:N35) -> 10817.654
B36: 1982 | C36: Q1 | D36: 20897.433 | H36: =SUM(D36:G36) -> 20897.433 | I36: 20897.433 | J36: =H36-I36 -> 0 | L36: 1977 | M36: May | N36: 10925.966 | O36: =AVERAGE(N34:N36) -> 10871.81
C37: Q2 | D37: 21811.315 | H37: =SUM(D37:G37) -> 21811.315 | I37: 21811.315 | J37: =H37-I37 -> 0 | L37: 1977 | M37: June | N37: 10925.966 | O37: =AVERAGE(N35:N37) -> 10925.966
C38: Q3 | D38: 22359.644 | H38: =SUM(D38:G38) -> 22359.644 | I38: 22359.644 | J38: =H38-I38 -> 0 | L38: 1977 | M38: July | N38: 11250.902 | O38: =AVERAGE(N36:N38) -> 11034.278
C39: Q4 | D39: 22684.58 | H39: =SUM(D39:G39) -> 22684.58 | I39: 22684.58 | J39: =H39-I39 -> 0 | L39: 1977 | M39: August | N39: 11250.902 | O39: =AVERAGE(N37:N39) -> 11142.59
B40: 1983 | C40: Q1 | D40: 23354.76 | H40: =SUM(D40:G40) -> 23354.76 | I40: 23354.76 | J40: =H40-I40 -> 0 | L40: 1977 | M40: September | N40: 11250.902 | O40: =AVERAGE(N38:N40) -> 11250.902
C41: Q2 | D41: 24167.1 | H41: =SUM(D41:G41) -> 24167.1 | I41: 24167.1 | J41: =H41-I41 -> 0 | L41: 1977 | M41: October | N41: 11596.146 | O41: =AVERAGE(N39:N41) -> 11365.983
C42: Q3 | D42: 25182.524 | H42: =SUM(D42:G42) -> 25182.524 | I42: 25182.524 | J42: =H42-I42 -> 0 | L42: 1977 | M42: November | N42: 11596.146 | O42: =AVERAGE(N40:N42) -> 11481.065
C43: Q4 | D43: 25385.609 | H43: =SUM(D43:G43) -> 25385.609 | I43: 25385.609 | J43: =H43-I43 -> 0 | L43: 1977 | M43: December | N43: 11596.146 | O43: =AVERAGE(N41:N43) -> 11596.146
B44: 1984 | C44: Q1 | D44: 25588.694 | H44: =SUM(D44:G44) -> 25588.694 | I44: 25588.694 | J44: =H44-I44 -> 0 | L44: 1978 | M44: January | N44: 11860.157 | O44: =AVERAGE(N42:N44) -> 11684.15
C45: Q2 | D45: 26401.033 | H45: =SUM(D45:G45) -> 26401.033 | I45: 26401.033 | J45: =H45-I45 -> 0 | L45: 1978 | M45: February | N45: 11860.157 | O45: =AVERAGE(N43:N45) -> 11772.153
C46: Q3 | D46: 27416.458 | H46: =SUM(D46:G46) -> 27416.458 | I46: 27416.458 | J46: =H46-I46 -> 0 | L46: 1978 | M46: March | N46: 11860.157 | O46: =AVERAGE(N44:N46) -> 11860.157
C47: Q4 | D47: 27822.627 | H47: =SUM(D47:G47) -> 27822.627 | I47: 27822.627 | J47: =H47-I47 -> 0 | L47: 1978 | M47: April | N47: 12428.794 | O47: =AVERAGE(N45:N47) -> 12049.702
B48: 1985 | C48: Q1 | D48: 27822.627 | H48: =SUM(D48:G48) -> 27822.627 | I48: 27822.627 | J48: =H48-I48 -> 0 | L48: 1978 | M48: May | N48: 12428.794 | O48: =AVERAGE(N46:N48) -> 12239.248
C49: Q2 | D49: 28838.052 | H49: =SUM(D49:G49) -> 28838.052 | I49: 28838.052 | J49: =H49-I49 -> 0 | L49: 1978 | M49: June | N49: 12428.794 | O49: =AVERAGE(N47:N49) -> 12428.794
C50: Q3 | D50: 29447.306 | H50: =SUM(D50:G50) -> 29447.306 | I50: 29447.306 | J50: =H50-I50 -> 0 | L50: 1978 | M50: July | N50: 13302.059 | O50: =AVERAGE(N48:N50) -> 12719.882
C51: Q4 | D51: 30462.731 | H51: =SUM(D51:G51) -> 30462.731 | I51: 30462.731 | J51: =H51-I51 -> 0 | L51: 1978 | M51: August | N51: 13302.059 | O51: =AVERAGE(N49:N51) -> 13010.971
B52: 1986 | C52: Q1 | D52: 31071.985 | H52: =SUM(D52:G52) -> 31071.985 | I52: 31071.985 | J52: =H52-I52 -> 0 | L52: 1978 | M52: September | N52: 13302.059 | O52: =AVERAGE(N50:N52) -> 13302.059
C53: Q2 | D53: 32493.58 | H53: =SUM(D53:G53) -> 32493.58 | I53: 32493.58 | J53: =H53-I53 -> 0 | L53: 1978 | M53: October | N53: 14236.25 | O53: =AVERAGE(N51:N53) -> 13613.456
C54: Q3 | D54: 33915.174 | H54: =SUM(D54:G54) -> 33915.174 | I54: 33915.174 | J54: =H54-I54 -> 0 | L54: 1978 | M54: November | N54: 14236.25 | O54: =AVERAGE(N52:N54) -> 13924.853
C55: Q4 | D55: 34930.598 | H55: =SUM(D55:G55) -> 34930.598 | I55: 34930.598 | J55: =H55-I55 -> 0 | L55: 1978 | M55: December | N55: 14236.25 | O55: =AVERAGE(N53:N55) -> 14236.25
B56: 1987 | C56: Q1 | D56: 35946.022 | H56: =SUM(D56:G56) -> 35946.022 | I56: 35946.022 | J56: =H56-I56 -> 0 | L56: 1979 | M56: January | N56: 14987.664 | O56: =AVERAGE(N54:N56) -> 14486.721
C57: Q2 | D57: 37570.701 | H57: =SUM(D57:G57) -> 37570.701 | I57: 37570.701 | J57: =H57-I57 -> 0 | L57: 1979 | M57: February | N57: 14987.664 | O57: =AVERAGE(N55:N57) -> 14737.192
C58: Q3 | D58: 39398.465 | H58: =SUM(D58:G58) -> 39398.465 | I58: 39398.465 | J58: =H58-I58 -> 0 | L58: 1979 | M58: March | N58: 14987.664 | O58: =AVERAGE(N56:N58) -> 14987.664
C59: Q4 | D59: 41731.767 | H59: =SUM(D59:G59) -> 41731.767 | I59: 41731.767 | J59: =H59-I59 -> 0 | L59: 1979 | M59: April | N59: 16145.247 | O59: =AVERAGE(N57:N59) -> 15373.525
B60: 1988 | C60: Q1 | D60: 43482.75 | H60: =SUM(D60:G60) -> 43482.75 | I60: 43482.75 | J60: =H60-I60 -> 0 | L60: 1979 | M60: May | N60: 16145.247 | O60: =AVERAGE(N58:N60) -> 15759.386
C61: Q2 | D61: 46109.225 | H61: =SUM(D61:G61) -> 46109.225 | I61: 46109.225 | J61: =H61-I61 -> 0 | L61: 1979 | M61: June | N61: 16145.247 | O61: =AVERAGE(N59:N61) -> 16145.247
C62: Q3 | D62: 52237.667 | H62: =SUM(D62:G62) -> 52237.667 | I62: 52237.667 | J62: =H62-I62 -> 0 | L62: 1979 | M62: July | N62: 17384.065 | O62: =AVERAGE(N60:N62) -> 16558.187
C63: Q4 | D63: 55447.802 | H63: =SUM(D63:G63) -> 55447.802 | I63: 55447.802 | J63: =H63-I63 -> 0 | L63: 1979 | M63: August | N63: 17384.065 | O63: =AVERAGE(N61:N63) -> 16971.126
B64: 1989 | C64: Q1 | D64: 56615.125 | H64: =SUM(D64:G64) -> 56615.125 | I64: 56615.125 | J64: =H64-I64 -> 0 | L64: 1979 | M64: September | N64: 17384.065 | O64: =AVERAGE(N62:N64) -> 17384.065
C65: Q2 | D65: 58657.938 | H65: =SUM(D65:G65) -> 58657.938 | I65: 58657.938 | J65: =H65-I65 -> 0 | L65: 1979 | M65: October | N65: 18541.649 | O65: =AVERAGE(N63:N65) -> 17769.926
C66: Q3 | D66: 60700.752 | H66: =SUM(D66:G66) -> 60700.752 | I66: 60700.752 | J66: =H66-I66 -> 0 | L66: 1979 | M66: November | N66: 18541.649 | O66: =AVERAGE(N64:N66) -> 18155.788
C67: Q4 | D67: 59533.43 | H67: =SUM(D67:G67) -> 59533.43 | I67: 59533.43 | J67: =H67-I67 -> 0 | L67: 1979 | M67: December | N67: 18541.649 | O67: =AVERAGE(N65:N67) -> 18541.649
B68: 1990 | C68: Q1 | D68: 58249.725 | H68: =SUM(D68:G68) -> 58249.725 | I68: 58249.725 | J68: =H68-I68 -> 0 | L68: 1980 | M68: January | N68: 19272.754 | O68: =AVERAGE(N66:N68) -> 18785.351
C69: Q2 | D69: 57726.001 | H69: =SUM(D69:G69) -> 57726.001 | I69: 57726.001 | J69: =H69-I69 -> 0 | L69: 1980 | M69: February | N69: 19272.754 | O69: =AVERAGE(N67:N69) -> 19029.053
C70: Q3 | D70: 58773.449 | H70: =SUM(D70:G70) -> 58773.449 | I70: 58773.449 | J70: =H70-I70 -> 0 | L70: 1980 | M70: March | N70: 19272.754 | O70: =AVERAGE(N68:N70) -> 19272.754
C71: Q4 | D71: 57900.576 | H71: =SUM(D71:G71) -> 57900.576 | I71: 57900.576 | J71: =H71-I71 -> 0 | L71: 1980 | M71: April | N71: 20044.477 | O71: =AVERAGE(N69:N71) -> 19529.995
B72: 1991 | C72: Q1 | D72: 57085.894 | H72: =SUM(D72:G72) -> 57085.894 | I72: 57085.894 | J72: =H72-I72 -> 0 | L72: 1980 | M72: May | N72: 20044.477 | O72: =AVERAGE(N70:N72) -> 19787.236
C73: Q2 | D73: 56853.128 | H73: =SUM(D73:G73) -> 56853.128 | I73: 56853.128 | J73: =H73-I73 -> 0 | L73: 1980 | M73: June | N73: 20044.477 | O73: =AVERAGE(N71:N73) -> 20044.477
C74: Q3 | D74: 57958.767 | H74: =SUM(D74:G74) -> 57958.767 | I74: 57958.767 | J74: =H74-I74 -> 0 | L74: 1980 | M74: July | N74: 20856.816 | O74: =AVERAGE(N72:N74) -> 20315.257
C75: Q4 | D75: 57435.043 | H75: =SUM(D75:G75) -> 57435.043 | I75: 57435.043 | J75: =H75-I75 -> 0 | L75: 1980 | M75: August | N75: 20856.816 | O75: =AVERAGE(N73:N75) -> 20586.037
B76: 1992 | C76: Q1 | D76: 56503.979 | H76: =SUM(D76:G76) -> 56503.979 | I76: 56503.979 | J76: =H76-I76 -> 0 | L76: 1980 | M76: September | N76: 20856.816 | O76: =AVERAGE(N74:N76) -> 20856.816
C77: Q2 | D77: 55165.574 | H77: =SUM(D77:G77) -> 55165.574 | I77: 55165.574 | J77: =H77-I77 -> 0 | L77: 1980 | M77: October | N77: 20897.433 | O77: =AVERAGE(N75:N77) -> 20870.355
C78: Q3 | D78: 55328.304 | H78: =SUM(D78:G78) -> 55328.304 | I78: 55328.304 | J78: =H78-I78 -> 0 | L78: 1980 | M78: November | N78: 20897.433 | O78: =AVERAGE(N76:N78) -> 20883.894
C79: Q4 | D79: 53212.81 | H79: =SUM(D79:G79) -> 53212.81 | I79: 53212.81 | J79: =H79-I79 -> 0 | L79: 1980 | M79: December | N79: 20897.433 | O79: =AVERAGE(N77:N79) -> 20897.433
B80: 1993 | C80: Q1 | D80: 53484.027 | H80: =SUM(D80:G80) -> 53484.027 | I80: 53484.027 | J80: =H80-I80 -> 0 | L80: 1981 | M80: January | N80: 20938.05 | O80: =AVERAGE(N78:N80) -> 20910.972
C81: Q2 | D81: 53917.975 | H81: =SUM(D81:G81) -> 53917.975 | I81: 53917.975 | J81: =H81-I81 -> 0 | L81: 1981 | M81: February | N81: 20938.05 | O81: =AVERAGE(N79:N81) -> 20924.511
C82: Q3 | D82: 55057.087 | H82: =SUM(D82:G82) -> 55057.087 | I82: 55057.087 | J82: =H82-I82 -> 0 | L82: 1981 | M82: March | N82: 20938.05 | O82: =AVERAGE(N80:N82) -> 20938.05
C83: Q4 | D83: 54026.461 | H83: =SUM(D83:G83) -> 54026.461 | I83: 54026.461 | J83: =H83-I83 -> 0 | L83: 1981 | M83: April | N83: 21506.688 | O83: =AVERAGE(N81:N83) -> 21127.596
B84: 1994 | C84: Q1 | D84: 54623.139 | H84: =SUM(D84:G84) -> 54623.139 | I84: 54623.139 | J84: =H84-I84 -> 0 | L84: 1981 | M84: May | N84: 21506.688 | O84: =AVERAGE(N82:N84) -> 21317.142
C85: Q2 | D85: 55382.547 | H85: =SUM(D85:G85) -> 55382.547 | I85: 55382.547 | J85: =H85-I85 -> 0 | L85: 1981 | M85: June | N85: 21506.688 | O85: =AVERAGE(N83:N85) -> 21506.688
C86: Q3 | D86: 56304.686 | H86: =SUM(D86:G86) -> 56304.686 | I86: 56304.686 | J86: =H86-I86 -> 0 | L86: 1981 | M86: July | N86: 21851.932 | O86: =AVERAGE(N84:N86) -> 21621.769
C87: Q4 | D87: 55924.982 | H87: =SUM(D87:G87) -> 55924.982 | I87: 55924.982 | J87: =H87-I87 -> 0 | L87: 1981 | M87: August | N87: 21851.932 | O87: =AVERAGE(N85:N87) -> 21736.851
B88: 1995 | C88: Q1 | D88: 55436.791 | H88: =SUM(D88:G88) -> 55436.791 | I88: 55436.791 | J88: =H88-I88 -> 0 | L88: 1981 | M88: September | N88: 21851.932 | O88: =AVERAGE(N86:N88) -> 21851.932
C89: Q2 | D89: 56033.468 | H89: =SUM(D89:G89) -> 56033.468 | I89: 56033.468 | J89: =H89-I89 -> 0 | L89: 1981 | M89: October | N89: 21425.454 | O89: =AVERAGE(N87:N89) -> 21709.773
C90: Q3 | D90: 56521.659 | H90: =SUM(D90:G90) -> 56521.659 | I90: 56521.659 | J90: =H90-I90 -> 0 | L90: 1981 | M90: November | N90: 21425.454 | O90: =AVERAGE(N88:N90) -> 21567.613
C91: Q4 | D91: 55762.251 | H91: =SUM(D91:G91) -> 55762.251 | I91: 55762.251 | J91: =H91-I91 -> 0 | L91: 1981 | M91: December | N91: 21425.454 | O91: =AVERAGE(N89:N91) -> 21425.454
B92: 1996 | C92: Q1 | D92: 56575.903 | H92: =SUM(D92:G92) -> 56575.903 | I92: 56575.903 | J92: =H92-I92 -> 0 | L92: 1982 | M92: January | N92: 20897.433 | O92: =AVERAGE(N90:N92) -> 21249.447
C93: Q2 | D93: 56630.146 | H93: =SUM(D93:G93) -> 56630.146 | I93: 56630.146 | J93: =H93-I93 -> 0 | L93: 1982 | M93: February | N93: 20897.433 | O93: =AVERAGE(N91:N93) -> 21073.44
C94: Q3 | D94: 58854.127 | H94: =SUM(D94:G94) -> 58854.127 | I94: 58854.127 | J94: =H94-I94 -> 0 | L94: 1982 | M94: March | N94: 20897.433 | O94: =AVERAGE(N92:N94) -> 20897.433
C95: Q4 | D95: 59884.752 | H95: =SUM(D95:G95) -> 59884.752 | I95: 59884.752 | J95: =H95-I95 -> 0 | L95: 1982 | M95: April | N95: 21811.315 | O95: =AVERAGE(N93:N95) -> 21202.061
B96: 1997 | C96: Q1 | D96: 60698.404 | H96: =SUM(D96:G96) -> 60698.404 | I96: 60698.404 | J96: =H96-I96 -> 0 | L96: 1982 | M96: May | N96: 21811.315 | O96: =AVERAGE(N94:N96) -> 21506.688
C97: Q2 | D97: 61946.003 | H97: =SUM(D97:G97) -> 61946.003 | I97: 61946.003 | J97: =H97-I97 -> 0 | L97: 1982 | M97: June | N97: 21811.315 | O97: =AVERAGE(N95:N97) -> 21811.315
C98: Q3 | D98: 65092.122 | H98: =SUM(D98:G98) -> 65092.122 | I98: 65092.122 | J98: =H98-I98 -> 0 | L98: 1982 | M98: July | N98: 22359.644 | O98: =AVERAGE(N96:N98) -> 21994.092
C99: Q4 | D99: 64603.931 | H99: =SUM(D99:G99) -> 64603.931 | I99: 64603.931 | J99: =H99-I99 -> 0 | L99: 1982 | M99: August | N99: 22359.644 | O99: =AVERAGE(N97:N99) -> 22176.868
B100: 1998 | C100: Q1 | D100: 66231.234 | H100: =SUM(D100:G100) -> 66231.234 | I100: 66231.234 | J100: =H100-I100 -> 0 | L100: 1982 | M100: September | N100: 22359.644 | O100: =AVERAGE(N98:N100) -> 22359.644
C101: Q2 | D101: 69757.058 | H101: =SUM(D101:G101) -> 69757.058 | I101: 69757.058 | J101: =H101-I101 -> 0 | L101: 1982 | M101: October | N101: 22684.58 | O101: =AVERAGE(N99:N101) -> 22467.956
C102: Q3 | D102: 72794.69 | H102: =SUM(D102:G102) -> 72794.69 | I102: 72794.69 | J102: =H102-I102 -> 0 | L102: 1982 | M102: November | N102: 22684.58 | O102: =AVERAGE(N100:N102) -> 22576.268
...

Sheet Nominal construction costs
D3: Cat 1 | E3: Cat 2 | F3: Cat 3 | G3: Cat4 | H3: Updated | I3: Previous | J3: Difference | L3: Raw data download processing..
B4: Notes 1 | D4: BIS Quarterly construction price and cost indices: July to September 2014 [BIS] | E4: Construction output price indices [ONS] | H4: See formula in cells; cat 2 series rebased to match cat 1 series
B5: Notes 2 | D5: Output price index for new construction, private housing, GB | E5: New work output prices, housing, GB
B6: Link | D6: BIS quarterly construction price and cost indices: July to September 2014 - GOV.UK (www.gov.uk) | E6: Construction output price indices - Office for National Statistics
B7: Table | D7: Table 1 tab | E7: New work tab
B8: 1975 | C8: Q1 | D8: 10.3 | H8: =IF(D8>0,D8,D$164*E8/100) -> 10.3 | I8: 10.3 | J8: =H8-I8 -> 0 | L8: 2014 | M8: January | N8: 100.6
C9: Q2 | D9: 11.2 | H9: =IF(D9>0,D9,D$164*E9/100) -> 11.2 | I9: 11.2 | J9: =H9-I9 -> 0 | L9: 2014 | M9: February | N9: 99.9
C10: Q3 | D10: 11.7 | H10: =IF(D10>0,D10,D$164*E10/100) -> 11.7 | I10: 11.7 | J10: =H10-I10 -> 0 | L10: 2014 | M10: March | N10: 99.4 | O10: =AVERAGE(N8:N10) -> 99.966667
C11: Q4 | D11: 11.5 | H11: =IF(D11>0,D11,D$164*E11/100) -> 11.5 | I11: 11.5 | J11: =H11-I11 -> 0 | L11: 2014 | M11: April | N11: 98.8 | O11: =AVERAGE(N9:N11) -> 99.366667
B12: 1976 | C12: Q1 | D12: 11.4 | H12: =IF(D12>0,D12,D$164*E12/100) -> 11.4 | I12: 11.4 | J12: =H12-I12 -> 0 | L12: 2014 | M12: May | N12: 98.5 | O12: =AVERAGE(N10:N12) -> 98.9
C13: Q2 | D13: 12.4 | H13: =IF(D13>0,D13,D$164*E13/100) -> 12.4 | I13: 12.4 | J13: =H13-I13 -> 0 | L13: 2014 | M13: June | N13: 99.1 | O13: =AVERAGE(N11:N13) -> 98.8
C14: Q3 | D14: 12.8 | H14: =IF(D14>0,D14,D$164*E14/100) -> 12.8 | I14: 12.8 | J14: =H14-I14 -> 0 | L14: 2014 | M14: July | N14: 99.4 | O14: =AVERAGE(N12:N14) -> 99
C15: Q4 | D15: 12.7 | H15: =IF(D15>0,D15,D$164*E15/100) -> 12.7 | I15: 12.7 | J15: =H15-I15 -> 0 | L15: 2014 | M15: August | N15: 98.8 | O15: =AVERAGE(N13:N15) -> 99.1
B16: 1977 | C16: Q1 | D16: 12.3 | H16: =IF(D16>0,D16,D$164*E16/100) -> 12.3 | I16: 12.3 | J16: =H16-I16 -> 0 | L16: 2014 | M16: September | N16: 99.1 | O16: =AVERAGE(N14:N16) -> 99.1
C17: Q2 | D17: 13.5 | H17: =IF(D17>0,D17,D$164*E17/100) -> 13.5 | I17: 13.5 | J17: =H17-I17 -> 0 | L17: 2014 | M17: October | N17: 99 | O17: =AVERAGE(N15:N17) -> 98.966667
C18: Q3 | D18: 14.1 | H18: =IF(D18>0,D18,D$164*E18/100) -> 14.1 | I18: 14.1 | J18: =H18-I18 -> 0 | L18: 2014 | M18: November | N18: 99.3 | O18: =AVERAGE(N16:N18) -> 99.133333
C19: Q4 | D19: 14.1 | H19: =IF(D19>0,D19,D$164*E19/100) -> 14.1 | I19: 14.1 | J19: =H19-I19 -> 0 | L19: 2014 | M19: December | N19: 99 | O19: =AVERAGE(N17:N19) -> 99.1
B20: 1978 | C20: Q1 | D20: 13.6 | H20: =IF(D20>0,D20,D$164*E20/100) -> 13.6 | I20: 13.6 | J20: =H20-I20 -> 0 | L20: 2015 | M20: January | N20: 99 | O20: =AVERAGE(N18:N20) -> 99.1
C21: Q2 | D21: 15.2 | H21: =IF(D21>0,D21,D$164*E21/100) -> 15.2 | I21: 15.2 | J21: =H21-I21 -> 0 | L21: 2015 | M21: February | N21: 99.6 | O21: =AVERAGE(N19:N21) -> 99.2
C22: Q3 | D22: 16.3 | H22: =IF(D22>0,D22,D$164*E22/100) -> 16.3 | I22: 16.3 | J22: =H22-I22 -> 0 | L22: 2015 | M22: March | N22: 101 | O22: =AVERAGE(N20:N22) -> 99.866667
C23: Q4 | D23: 16.6 | H23: =IF(D23>0,D23,D$164*E23/100) -> 16.6 | I23: 16.6 | J23: =H23-I23 -> 0 | L23: 2015 | M23: April | N23: 100 | O23: =AVERAGE(N21:N23) -> 100.2
B24: 1979 | C24: Q1 | D24: 16.2 | H24: =IF(D24>0,D24,D$164*E24/100) -> 16.2 | I24: 16.2 | J24: =H24-I24 -> 0 | L24: 2015 | M24: May | N24: 99.9 | O24: =AVERAGE(N22:N24) -> 100.3
C25: Q2 | D25: 18.2 | H25: =IF(D25>0,D25,D$164*E25/100) -> 18.2 | I25: 18.2 | J25: =H25-I25 -> 0 | L25: 2015 | M25: June | N25: 100.3 | O25: =AVERAGE(N23:N25) -> 100.06667
C26: Q3 | D26: 20.1 | H26: =IF(D26>0,D26,D$164*E26/100) -> 20.1 | I26: 20.1 | J26: =H26-I26 -> 0 | L26: 2015 | M26: July | N26: 100.4 | O26: =AVERAGE(N24:N26) -> 100.2
C27: Q4 | D27: 20.6 | H27: =IF(D27>0,D27,D$164*E27/100) -> 20.6 | I27: 20.6 | J27: =H27-I27 -> 0 | L27: 2015 | M27: August | N27: 99.7 | O27: =AVERAGE(N25:N27) -> 100.13333
B28: 1980 | C28: Q1 | D28: 20.1 | H28: =IF(D28>0,D28,D$164*E28/100) -> 20.1 | I28: 20.1 | J28: =H28-I28 -> 0 | L28: 2015 | M28: September | N28: 99.6 | O28: =AVERAGE(N26:N28) -> 99.9
C29: Q2 | D29: 23 | H29: =IF(D29>0,D29,D$164*E29/100) -> 23 | I29: 23 | J29: =H29-I29 -> 0 | L29: 2015 | M29: October | N29: 100.1 | O29: =AVERAGE(N27:N29) -> 99.8
C30: Q3 | D30: 24.5 | H30: =IF(D30>0,D30,D$164*E30/100) -> 24.5 | I30: 24.5 | J30: =H30-I30 -> 0 | L30: 2015 | M30: November | N30: 100.7 | O30: =AVERAGE(N28:N30) -> 100.13333
C31: Q4 | D31: 24.5 | H31: =IF(D31>0,D31,D$164*E31/100) -> 24.5 | I31: 24.5 | J31: =H31-I31 -> 0 | L31: 2015 | M31: December | N31: 99.8 | O31: =AVERAGE(N29:N31) -> 100.2
B32: 1981 | C32: Q1 | D32: 23.1 | H32: =IF(D32>0,D32,D$164*E32/100) -> 23.1 | I32: 23.1 | J32: =H32-I32 -> 0 | L32: 2016 | M32: January | N32: 101.4 | O32: =AVERAGE(N30:N32) -> 100.63333
C33: Q2 | D33: 25.3 | H33: =IF(D33>0,D33,D$164*E33/100) -> 25.3 | I33: 25.3 | J33: =H33-I33 -> 0 | L33: 2016 | M33: February | N33: 101.6 | O33: =AVERAGE(N31:N33) -> 100.93333
C34: Q3 | D34: 25.5 | H34: =IF(D34>0,D34,D$164*E34/100) -> 25.5 | I34: 25.5 | J34: =H34-I34 -> 0 | L34: 2016 | M34: March | N34: 102.2 | O34: =AVERAGE(N32:N34) -> 101.73333
C35: Q4 | D35: 24.5 | H35: =IF(D35>0,D35,D$164*E35/100) -> 24.5 | I35: 24.5 | J35: =H35-I35 -> 0 | L35: 2016 | M35: April | N35: 102.5 | O35: =AVERAGE(N33:N35) -> 102.1
B36: 1982 | C36: Q1 | D36: 23.2 | H36: =IF(D36>0,D36,D$164*E36/100) -> 23.2 | I36: 23.2 | J36: =H36-I36 -> 0 | L36: 2016 | M36: May | N36: 102.3 | O36: =AVERAGE(N34:N36) -> 102.33333
C37: Q2 | D37: 25.2 | H37: =IF(D37>0,D37,D$164*E37/100) -> 25.2 | I37: 25.2 | J37: =H37-I37 -> 0 | L37: 2016 | M37: June | N37: 102.4 | O37: =AVERAGE(N35:N37) -> 102.4
C38: Q3 | D38: 25.3 | H38: =IF(D38>0,D38,D$164*E38/100) -> 25.3 | I38: 25.3 | J38: =H38-I38 -> 0 | L38: 2016 | M38: July | N38: 103.2 | O38: =AVERAGE(N36:N38) -> 102.63333
C39: Q4 | D39: 24.8 | H39: =IF(D39>0,D39,D$164*E39/100) -> 24.8 | I39: 24.8 | J39: =H39-I39 -> 0 | L39: 2016 | M39: August | N39: 103.2 | O39: =AVERAGE(N37:N39) -> 102.93333
B40: 1983 | C40: Q1 | D40: 25.6 | H40: =IF(D40>0,D40,D$164*E40/100) -> 25.6 | I40: 25.6 | J40: =H40-I40 -> 0 | L40: 2016 | M40: September | N40: 103.5 | O40: =AVERAGE(N38:N40) -> 103.3
C41: Q2 | D41: 26.2 | H41: =IF(D41>0,D41,D$164*E41/100) -> 26.2 | I41: 26.2 | J41: =H41-I41 -> 0 | L41: 2016 | M41: October | N41: 104.1 | O41: =AVERAGE(N39:N41) -> 103.6
C42: Q3 | D42: 26.9 | H42: =IF(D42>0,D42,D$164*E42/100) -> 26.9 | I42: 26.9 | J42: =H42-I42 -> 0 | L42: 2016 | M42: November | N42: 104.8 | O42: =AVERAGE(N40:N42) -> 104.13333
C43: Q4 | D43: 27.3 | H43: =IF(D43>0,D43,D$164*E43/100) -> 27.3 | I43: 27.3 | J43: =H43-I43 -> 0 | L43: 2016 | M43: December | N43: 104.8 | O43: =AVERAGE(N41:N43) -> 104.56667
B44: 1984 | C44: Q1 | D44: 27.8 | H44: =IF(D44>0,D44,D$164*E44/100) -> 27.8 | I44: 27.8 | J44: =H44-I44 -> 0 | L44: 2017 | M44: January | N44: 105.6 | O44: =AVERAGE(N42:N44) -> 105.06667
C45: Q2 | D45: 28.3 | H45: =IF(D45>0,D45,D$164*E45/100) -> 28.3 | I45: 28.3 | J45: =H45-I45 -> 0 | L45: 2017 | M45: February | N45: 105.8 | O45: =AVERAGE(N43:N45) -> 105.4
C46: Q3 | D46: 28.8 | H46: =IF(D46>0,D46,D$164*E46/100) -> 28.8 | I46: 28.8 | J46: =H46-I46 -> 0 | L46: 2017 | M46: March | N46: 106.1 | O46: =AVERAGE(N44:N46) -> 105.83333
C47: Q4 | D47: 29.1 | H47: =IF(D47>0,D47,D$164*E47/100) -> 29.1 | I47: 29.1 | J47: =H47-I47 -> 0 | L47: 2017 | M47: April | N47: 106.1 | O47: =AVERAGE(N45:N47) -> 106
B48: 1985 | C48: Q1 | D48: 29.5 | H48: =IF(D48>0,D48,D$164*E48/100) -> 29.5 | I48: 29.5 | J48: =H48-I48 -> 0 | L48: 2017 | M48: May | N48: 106.2 | O48: =AVERAGE(N46:N48) -> 106.13333
C49: Q2 | D49: 29.9 | H49: =IF(D49>0,D49,D$164*E49/100) -> 29.9 | I49: 29.9 | J49: =H49-I49 -> 0 | L49: 2017 | M49: June | N49: 106.7 | O49: =AVERAGE(N47:N49) -> 106.33333
C50: Q3 | D50: 30.4 | H50: =IF(D50>0,D50,D$164*E50/100) -> 30.4 | I50: 30.4 | J50: =H50-I50 -> 0 | L50: 2017 | M50: July | N50: 107.3 | O50: =AVERAGE(N48:N50) -> 106.73333
C51: Q4 | D51: 31 | H51: =IF(D51>0,D51,D$164*E51/100) -> 31 | I51: 31 | J51: =H51-I51 -> 0 | L51: 2017 | M51: August | N51: 107.6 | O51: =AVERAGE(N49:N51) -> 107.2
B52: 1986 | C52: Q1 | D52: 31.9 | H52: =IF(D52>0,D52,D$164*E52/100) -> 31.9 | I52: 31.9 | J52: =H52-I52 -> 0 | L52: 2017 | M52: September | N52: 108.6 | O52: =AVERAGE(N50:N52) -> 107.83333
C53: Q2 | D53: 32.4 | H53: =IF(D53>0,D53,D$164*E53/100) -> 32.4 | I53: 32.4 | J53: =H53-I53 -> 0 | L53: 2017 | M53: October | N53: 108.4 | O53: =AVERAGE(N51:N53) -> 108.2
C54: Q3 | D54: 33.2 | H54: =IF(D54>0,D54,D$164*E54/100) -> 33.2 | I54: 33.2 | J54: =H54-I54 -> 0 | L54: 2017 | M54: November | N54: 108.9 | O54: =AVERAGE(N52:N54) -> 108.63333
C55: Q4 | D55: 33.7 | H55: =IF(D55>0,D55,D$164*E55/100) -> 33.7 | I55: 33.7 | J55: =H55-I55 -> 0 | L55: 2017 | M55: December | N55: 109 | O55: =AVERAGE(N53:N55) -> 108.76667
B56: 1987 | C56: Q1 | D56: 34.6 | H56: =IF(D56>0,D56,D$164*E56/100) -> 34.6 | I56: 34.6 | J56: =H56-I56 -> 0 | L56: 2018 | M56: January | N56: 110.1 | O56: =AVERAGE(N54:N56) -> 109.33333
C57: Q2 | D57: 35.4 | H57: =IF(D57>0,D57,D$164*E57/100) -> 35.4 | I57: 35.4 | J57: =H57-I57 -> 0 | L57: 2018 | M57: February | N57: 109.8 | O57: =AVERAGE(N55:N57) -> 109.63333
C58: Q3 | D58: 36.4 | H58: =IF(D58>0,D58,D$164*E58/100) -> 36.4 | I58: 36.4 | J58: =H58-I58 -> 0 | L58: 2018 | M58: March | N58: 110.6 | O58: =AVERAGE(N56:N58) -> 110.16667
C59: Q4 | D59: 37.5 | H59: =IF(D59>0,D59,D$164*E59/100) -> 37.5 | I59: 37.5 | J59: =H59-I59 -> 0 | L59: 2018 | M59: April | N59: 110.9 | O59: =AVERAGE(N57:N59) -> 110.43333
B60: 1988 | C60: Q1 | D60: 38.6 | H60: =IF(D60>0,D60,D$164*E60/100) -> 38.6 | I60: 38.6 | J60: =H60-I60 -> 0 | L60: 2018 | M60: May | N60: 111.2 | O60: =AVERAGE(N58:N60) -> 110.9
C61: Q2 | D61: 40.1 | H61: =IF(D61>0,D61,D$164*E61/100) -> 40.1 | I61: 40.1 | J61: =H61-I61 -> 0 | L61: 2018 | M61: June | N61: 111.6 | O61: =AVERAGE(N59:N61) -> 111.23333
C62: Q3 | D62: 42.1 | H62: =IF(D62>0,D62,D$164*E62/100) -> 42.1 | I62: 42.1 | J62: =H62-I62 -> 0 | L62: 2018 | M62: July | N62: 111.4 | O62: =AVERAGE(N60:N62) -> 111.4
C63: Q4 | D63: 43.8 | H63: =IF(D63>0,D63,D$164*E63/100) -> 43.8 | I63: 43.8 | J63: =H63-I63 -> 0 | L63: 2018 | M63: August | N63: 111.2 | O63: =AVERAGE(N61:N63) -> 111.4
B64: 1989 | C64: Q1 | D64: 45.5 | H64: =IF(D64>0,D64,D$164*E64/100) -> 45.5 | I64: 45.5 | J64: =H64-I64 -> 0 | L64: 2018 | M64: September | N64: 111.2 | O64: =AVERAGE(N62:N64) -> 111.26667
C65: Q2 | D65: 47.1 | H65: =IF(D65>0,D65,D$164*E65/100) -> 47.1 | I65: 47.1 | J65: =H65-I65 -> 0 | L65: 2018 | M65: October | N65: 111.4 | O65: =AVERAGE(N63:N65) -> 111.26667
C66: Q3 | D66: 48.4 | H66: =IF(D66>0,D66,D$164*E66/100) -> 48.4 | I66: 48.4 | J66: =H66-I66 -> 0 | L66: 2018 | M66: November | N66: 112.5 | O66: =AVERAGE(N64:N66) -> 111.7
C67: Q4 | D67: 49.7 | H67: =IF(D67>0,D67,D$164*E67/100) -> 49.7 | I67: 49.7 | J67: =H67-I67 -> 0 | L67: 2018 | M67: December | N67: 112.5 | O67: =AVERAGE(N65:N67) -> 112.13333
B68: 1990 | C68: Q1 | D68: 50.9 | H68: =IF(D68>0,D68,D$164*E68/100) -> 50.9 | I68: 50.9 | J68: =H68-I68 -> 0 | L68: 2019 | M68: January | N68: 112.8 | O68: =AVERAGE(N66:N68) -> 112.6
C69: Q2 | D69: 51.8 | H69: =IF(D69>0,D69,D$164*E69/100) -> 51.8 | I69: 51.8 | J69: =H69-I69 -> 0 | L69: 2019 | M69: February | N69: 113.4 | O69: =AVERAGE(N67:N69) -> 112.9
C70: Q3 | D70: 52.5 | H70: =IF(D70>0,D70,D$164*E70/100) -> 52.5 | I70: 52.5 | J70: =H70-I70 -> 0 | L70: 2019 | M70: March | N70: 113.6 | O70: =AVERAGE(N68:N70) -> 113.26667
C71: Q4 | D71: 52.9 | H71: =IF(D71>0,D71,D$164*E71/100) -> 52.9 | I71: 52.9 | J71: =H71-I71 -> 0 | L71: 2019 | M71: April | N71: 114.3 | O71: =AVERAGE(N69:N71) -> 113.76667
B72: 1991 | C72: Q1 | D72: 53 | H72: =IF(D72>0,D72,D$164*E72/100) -> 53 | I72: 53 | J72: =H72-I72 -> 0 | L72: 2019 | M72: May | N72: 115 | O72: =AVERAGE(N70:N72) -> 114.3
C73: Q2 | D73: 52.5 | H73: =IF(D73>0,D73,D$164*E73/100) -> 52.5 | I73: 52.5 | J73: =H73-I73 -> 0 | L73: 2019 | M73: June | N73: 115.3 | O73: =AVERAGE(N71:N73) -> 114.86667
C74: Q3 | D74: 52.4 | H74: =IF(D74>0,D74,D$164*E74/100) -> 52.4 | I74: 52.4 | J74: =H74-I74 -> 0 | L74: 2019 | M74: July | N74: 115.5 | O74: =AVERAGE(N72:N74) -> 115.26667
C75: Q4 | D75: 52.1 | H75: =IF(D75>0,D75,D$164*E75/100) -> 52.1 | I75: 52.1 | J75: =H75-I75 -> 0 | L75: 2019 | M75: August | N75: 115.3 | O75: =AVERAGE(N73:N75) -> 115.36667
B76: 1992 | C76: Q1 | D76: 51.6 | H76: =IF(D76>0,D76,D$164*E76/100) -> 51.6 | I76: 51.6 | J76: =H76-I76 -> 0 | L76: 2019 | M76: September | N76: 115.3 | O76: =AVERAGE(N74:N76) -> 115.36667
C77: Q2 | D77: 51.1 | H77: =IF(D77>0,D77,D$164*E77/100) -> 51.1 | I77: 51.1 | J77: =H77-I77 -> 0 | L77: 2019 | M77: October | N77: 114.7 | O77: =AVERAGE(N75:N77) -> 115.1
C78: Q3 | D78: 50.7 | H78: =IF(D78>0,D78,D$164*E78/100) -> 50.7 | I78: 50.7 | J78: =H78-I78 -> 0 | L78: 2019 | M78: November | N78: 114.8 | O78: =AVERAGE(N76:N78) -> 114.93333
C79: Q4 | D79: 50.2 | H79: =IF(D79>0,D79,D$164*E79/100) -> 50.2 | I79: 50.2 | J79: =H79-I79 -> 0 | L79: 2019 | M79: December | N79: 114.2 | O79: =AVERAGE(N77:N79) -> 114.56667
B80: 1993 | C80: Q1 | D80: 48.7 | H80: =IF(D80>0,D80,D$164*E80/100) -> 48.7 | I80: 48.7 | J80: =H80-I80 -> 0 | L80: 2020 | M80: January | N80: 114.7 | O80: =AVERAGE(N78:N80) -> 114.56667
C81: Q2 | D81: 50.1 | H81: =IF(D81>0,D81,D$164*E81/100) -> 50.1 | I81: 50.1 | J81: =H81-I81 -> 0 | L81: 2020 | M81: February | N81: 114.8 | O81: =AVERAGE(N79:N81) -> 114.56667
C82: Q3 | D82: 50.2 | H82: =IF(D82>0,D82,D$164*E82/100) -> 50.2 | I82: 50.2 | J82: =H82-I82 -> 0 | L82: 2020 | M82: March | N82: 114.6 | O82: =AVERAGE(N80:N82) -> 114.7
C83: Q4 | D83: 51.5 | H83: =IF(D83>0,D83,D$164*E83/100) -> 51.5 | I83: 51.5 | J83: =H83-I83 -> 0 | L83: 2020 | M83: April | N83: 114.8 | O83: =AVERAGE(N81:N83) -> 114.73333
B84: 1994 | C84: Q1 | D84: 52.3 | H84: =IF(D84>0,D84,D$164*E84/100) -> 52.3 | I84: 52.3 | J84: =H84-I84 -> 0 | L84: 2020 | M84: May | N84: 114.8 | O84: =AVERAGE(N82:N84) -> 114.73333
C85: Q2 | D85: 53.7 | H85: =IF(D85>0,D85,D$164*E85/100) -> 53.7 | I85: 53.7 | J85: =H85-I85 -> 0 | L85: 2020 | M85: June | N85: 115 | O85: =AVERAGE(N83:N85) -> 114.86667
C86: Q3 | D86: 54.5 | H86: =IF(D86>0,D86,D$164*E86/100) -> 54.5 | I86: 54.5 | J86: =H86-I86 -> 0 | L86: 2020 | M86: July | N86: 115.4 | O86: =AVERAGE(N84:N86) -> 115.06667
C87: Q4 | D87: 54.6 | H87: =IF(D87>0,D87,D$164*E87/100) -> 54.6 | I87: 54.6 | J87: =H87-I87 -> 0 | L87: 2020 | M87: August | N87: 115.4 | O87: =AVERAGE(N85:N87) -> 115.26667
B88: 1995 | C88: Q1 | D88: 53.9 | H88: =IF(D88>0,D88,D$164*E88/100) -> 53.9 | I88: 53.9 | J88: =H88-I88 -> 0 | L88: 2020 | M88: September | N88: 115.8 | O88: =AVERAGE(N86:N88) -> 115.53333
C89: Q2 | D89: 54 | H89: =IF(D89>0,D89,D$164*E89/100) -> 54 | I89: 54 | J89: =H89-I89 -> 0 | L89: 2020 | M89: October | N89: 115.9 | O89: =AVERAGE(N87:N89) -> 115.7
C90: Q3 | D90: 53.9 | H90: =IF(D90>0,D90,D$164*E90/100) -> 53.9 | I90: 53.9 | J90: =H90-I90 -> 0 | L90: 2020 | M90: November | N90: 116.1 | O90: =AVERAGE(N88:N90) -> 115.93333
C91: Q4 | D91: 54 | H91: =IF(D91>0,D91,D$164*E91/100) -> 54 | I91: 54 | J91: =H91-I91 -> 0 | L91: 2020 | M91: December | N91: 116.2 | O91: =AVERAGE(N89:N91) -> 116.06667
B92: 1996 | C92: Q1 | D92: 54 | H92: =IF(D92>0,D92,D$164*E92/100) -> 54 | I92: 54 | J92: =H92-I92 -> 0 | L92: 2021 | M92: January | N92: 116.9 | O92: =AVERAGE(N90:N92) -> 116.4
C93: Q2 | D93: 55.2 | H93: =IF(D93>0,D93,D$164*E93/100) -> 55.2 | I93: 55.2 | J93: =H93-I93 -> 0 | L93: 2021 | M93: February | N93: 117.2 | O93: =AVERAGE(N91:N93) -> 116.76667
C94: Q3 | D94: 56.1 | H94: =IF(D94>0,D94,D$164*E94/100) -> 56.1 | I94: 56.1 | J94: =H94-I94 -> 0 | L94: 2021 | M94: March | N94: 118 | O94: =AVERAGE(N92:N94) -> 117.36667
C95: Q4 | D95: 57.2 | H95: =IF(D95>0,D95,D$164*E95/100) -> 57.2 | I95: 57.2 | J95: =H95-I95 -> 0 | L95: 2021 | M95: April | N95: 118.7 | O95: =AVERAGE(N93:N95) -> 117.96667
B96: 1997 | C96: Q1 | D96: 57.1 | H96: =IF(D96>0,D96,D$164*E96/100) -> 57.1 | I96: 57.1 | J96: =H96-I96 -> 0 | L96: 2021 | M96: May | N96: 119.9 | O96: =AVERAGE(N94:N96) -> 118.86667
C97: Q2 | D97: 58.4 | H97: =IF(D97>0,D97,D$164*E97/100) -> 58.4 | I97: 58.4 | J97: =H97-I97 -> 0 | L97: 2021 | M97: June | N97: 120.9 | O97: =AVERAGE(N95:N97) -> 119.83333
C98: Q3 | D98: 59.4 | H98: =IF(D98>0,D98,D$164*E98/100) -> 59.4 | I98: 59.4 | J98: =H98-I98 -> 0 | L98: 2021 | M98: July | N98: 122.4 | O98: =AVERAGE(N96:N98) -> 121.06667
C99: Q4 | D99: 60.2 | H99: =IF(D99>0,D99,D$164*E99/100) -> 60.2 | I99: 60.2 | J99: =H99-I99 -> 0 | L99: 2021 | M99: August | N99: 124 | O99: =AVERAGE(N97:N99) -> 122.43333
B100: 1998 | C100: Q1 | D100: 61.7 | H100: =IF(D100>0,D100,D$164*E100/100) -> 61.7 | I100: 61.7 | J100: =H100-I100 -> 0 | L100: 2021 | M100: September | N100: 124 | O100: =AVERAGE(N98:N100) -> 123.46667
C101: Q2 | D101: 62.1 | H101: =IF(D101>0,D101,D$164*E101/100) -> 62.1 | I101: 62.1 | J101: =H101-I101 -> 0 | L101: 2021 | M101: October | N101: 125.7 | O101: =AVERAGE(N99:N101) -> 124.56667
C102: Q3 | D102: 62.7 | H102: =IF(D102>0,D102,D$164*E102/100) -> 62.7 | I102: 62.7 | J102: =H102-I102 -> 0 | L102: 2021 | M102: November | N102: 127.1 | O102: =AVERAGE(N100:N102) -> 125.6
...

Sheet Transactions
D3: Cat 1 | E3: Cat 2 | F3: Cat 3 | G3: Cat4 | H3: Updated | I3: Previous | J3: Difference
B4: Notes 1 | D4: [Geoff Meen] | E4: Live tables on housing market and house price [DLUHC] | F4: House Price Index [ONS, Land Registry] | H4: Sum cats 1-3
B5: Notes 2 | E5: Property sales based on Land Registry data, by district, from 1996 (quarterly), England & Wales | F5: Property sales based on Land Registry data, England & Wales
B6: Link | D6: N/A | E6: Live tables on housing market and house prices - GOV.UK (www.gov.uk) | F6: UK House Price Index: data downloads September 2022 - GOV.UK (www.gov.uk)
B7: Table | D7: N/A | E7: Table 584, England & Wales total | F7: Sales, extract England & Wales data
B8: 1975 | C8: Q1 | D8: 193500 | H8: =SUM(D8:G8) -> 193500 | I8: 193500 | J8: =H8-I8 -> 0
C9: Q2 | D9: 226500 | H9: =SUM(D9:G9) -> 226500 | I9: 226500 | J9: =H9-I9 -> 0
C10: Q3 | D10: 236250 | H10: =SUM(D10:G10) -> 236250 | I10: 236250 | J10: =H10-I10 -> 0
C11: Q4 | D11: 224250 | H11: =SUM(D11:G11) -> 224250 | I11: 224250 | J11: =H11-I11 -> 0
B12: 1976 | C12: Q1 | D12: 201750 | H12: =SUM(D12:G12) -> 201750 | I12: 201750 | J12: =H12-I12 -> 0
C13: Q2 | D13: 222750 | H13: =SUM(D13:G13) -> 222750 | I13: 222750 | J13: =H13-I13 -> 0
C14: Q3 | D14: 237000 | H14: =SUM(D14:G14) -> 237000 | I14: 237000 | J14: =H14-I14 -> 0
C15: Q4 | D15: 231000 | H15: =SUM(D15:G15) -> 231000 | I15: 231000 | J15: =H15-I15 -> 0
B16: 1977 | C16: Q1 | D16: 196500 | H16: =SUM(D16:G16) -> 196500 | I16: 196500 | J16: =H16-I16 -> 0
C17: Q2 | D17: 225750 | H17: =SUM(D17:G17) -> 225750 | I17: 225750 | J17: =H17-I17 -> 0
C18: Q3 | D18: 249750 | H18: =SUM(D18:G18) -> 249750 | I18: 249750 | J18: =H18-I18 -> 0
C19: Q4 | D19: 257250 | H19: =SUM(D19:G19) -> 257250 | I19: 257250 | J19: =H19-I19 -> 0
B20: 1978 | C20: Q1 | D20: 248250 | H20: =SUM(D20:G20) -> 248250 | I20: 248250 | J20: =H20-I20 -> 0
C21: Q2 | D21: 263250 | H21: =SUM(D21:G21) -> 263250 | I21: 263250 | J21: =H21-I21 -> 0
C22: Q3 | D22: 261750 | H22: =SUM(D22:G22) -> 261750 | I22: 261750 | J22: =H22-I22 -> 0
C23: Q4 | D23: 250500 | H23: =SUM(D23:G23) -> 250500 | I23: 250500 | J23: =H23-I23 -> 0
B24: 1979 | C24: Q1 | D24: 229500 | H24: =SUM(D24:G24) -> 229500 | I24: 229500 | J24: =H24-I24 -> 0
C25: Q2 | D25: 235500 | H25: =SUM(D25:G25) -> 235500 | I25: 235500 | J25: =H25-I25 -> 0
C26: Q3 | D26: 258750 | H26: =SUM(D26:G26) -> 258750 | I26: 258750 | J26: =H26-I26 -> 0
C27: Q4 | D27: 255750 | H27: =SUM(D27:G27) -> 255750 | I27: 255750 | J27: =H27-I27 -> 0
B28: 1980 | C28: Q1 | D28: 234000 | H28: =SUM(D28:G28) -> 234000 | I28: 234000 | J28: =H28-I28 -> 0
C29: Q2 | D29: 246000 | H29: =SUM(D29:G29) -> 246000 | I29: 246000 | J29: =H29-I29 -> 0
C30: Q3 | D30: 231000 | H30: =SUM(D30:G30) -> 231000 | I30: 231000 | J30: =H30-I30 -> 0
C31: Q4 | D31: 239250 | H31: =SUM(D31:G31) -> 239250 | I31: 239250 | J31: =H31-I31 -> 0
B32: 1981 | C32: Q1 | D32: 216000 | H32: =SUM(D32:G32) -> 216000 | I32: 216000 | J32: =H32-I32 -> 0
C33: Q2 | D33: 246000 | H33: =SUM(D33:G33) -> 246000 | I33: 246000 | J33: =H33-I33 -> 0
C34: Q3 | D34: 263250 | H34: =SUM(D34:G34) -> 263250 | I34: 263250 | J34: =H34-I34 -> 0
C35: Q4 | D35: 288000 | H35: =SUM(D35:G35) -> 288000 | I35: 288000 | J35: =H35-I35 -> 0
B36: 1982 | C36: Q1 | D36: 240000 | H36: =SUM(D36:G36) -> 240000 | I36: 240000 | J36: =H36-I36 -> 0
C37: Q2 | D37: 276000 | H37: =SUM(D37:G37) -> 276000 | I37: 276000 | J37: =H37-I37 -> 0
C38: Q3 | D38: 318000 | H38: =SUM(D38:G38) -> 318000 | I38: 318000 | J38: =H38-I38 -> 0
C39: Q4 | D39: 321750 | H39: =SUM(D39:G39) -> 321750 | I39: 321750 | J39: =H39-I39 -> 0
B40: 1983 | C40: Q1 | D40: 302250 | H40: =SUM(D40:G40) -> 302250 | I40: 302250 | J40: =H40-I40 -> 0
C41: Q2 | D41: 308250 | H41: =SUM(D41:G41) -> 308250 | I41: 308250 | J41: =H41-I41 -> 0
C42: Q3 | D42: 323250 | H42: =SUM(D42:G42) -> 323250 | I42: 323250 | J42: =H42-I42 -> 0
C43: Q4 | D43: 318000 | H43: =SUM(D43:G43) -> 318000 | I43: 318000 | J43: =H43-I43 -> 0
B44: 1984 | C44: Q1 | D44: 318000 | H44: =SUM(D44:G44) -> 318000 | I44: 318000 | J44: =H44-I44 -> 0
C45: Q2 | D45: 320250 | H45: =SUM(D45:G45) -> 320250 | I45: 320250 | J45: =H45-I45 -> 0
C46: Q3 | D46: 342000 | H46: =SUM(D46:G46) -> 342000 | I46: 342000 | J46: =H46-I46 -> 0
C47: Q4 | D47: 339000 | H47: =SUM(D47:G47) -> 339000 | I47: 339000 | J47: =H47-I47 -> 0
B48: 1985 | C48: Q1 | D48: 303000 | H48: =SUM(D48:G48) -> 303000 | I48: 303000 | J48: =H48-I48 -> 0
C49: Q2 | D49: 325500 | H49: =SUM(D49:G49) -> 325500 | I49: 325500 | J49: =H49-I49 -> 0
C50: Q3 | D50: 346500 | H50: =SUM(D50:G50) -> 346500 | I50: 346500 | J50: =H50-I50 -> 0
C51: Q4 | D51: 331500 | H51: =SUM(D51:G51) -> 331500 | I51: 331500 | J51: =H51-I51 -> 0
B52: 1986 | C52: Q1 | D52: 292500 | H52: =SUM(D52:G52) -> 292500 | I52: 292500 | J52: =H52-I52 -> 0
C53: Q2 | D53: 313500 | H53: =SUM(D53:G53) -> 313500 | I53: 313500 | J53: =H53-I53 -> 0
C54: Q3 | D54: 374250 | H54: =SUM(D54:G54) -> 374250 | I54: 374250 | J54: =H54-I54 -> 0
C55: Q4 | D55: 370500 | H55: =SUM(D55:G55) -> 370500 | I55: 370500 | J55: =H55-I55 -> 0
B56: 1987 | C56: Q1 | D56: 321750 | H56: =SUM(D56:G56) -> 321750 | I56: 321750 | J56: =H56-I56 -> 0
C57: Q2 | D57: 329250 | H57: =SUM(D57:G57) -> 329250 | I57: 329250 | J57: =H57-I57 -> 0
C58: Q3 | D58: 400500 | H58: =SUM(D58:G58) -> 400500 | I58: 400500 | J58: =H58-I58 -> 0
C59: Q4 | D59: 401250 | H59: =SUM(D59:G59) -> 401250 | I59: 401250 | J59: =H59-I59 -> 0
B60: 1988 | C60: Q1 | D60: 365250 | H60: =SUM(D60:G60) -> 365250 | I60: 365250 | J60: =H60-I60 -> 0
C61: Q2 | D61: 388500 | H61: =SUM(D61:G61) -> 388500 | I61: 388500 | J61: =H61-I61 -> 0
C62: Q3 | D62: 462000 | H62: =SUM(D62:G62) -> 462000 | I62: 462000 | J62: =H62-I62 -> 0
C63: Q4 | D63: 395250 | H63: =SUM(D63:G63) -> 395250 | I63: 395250 | J63: =H63-I63 -> 0
B64: 1989 | C64: Q1 | D64: 305250 | H64: =SUM(D64:G64) -> 305250 | I64: 305250 | J64: =H64-I64 -> 0
C65: Q2 | D65: 303750 | H65: =SUM(D65:G65) -> 303750 | I65: 303750 | J65: =H65-I65 -> 0
C66: Q3 | D66: 292500 | H66: =SUM(D66:G66) -> 292500 | I66: 292500 | J66: =H66-I66 -> 0
C67: Q4 | D67: 283500 | H67: =SUM(D67:G67) -> 283500 | I67: 283500 | J67: =H67-I67 -> 0
B68: 1990 | C68: Q1 | D68: 258000 | H68: =SUM(D68:G68) -> 258000 | I68: 258000 | J68: =H68-I68 -> 0
C69: Q2 | D69: 270000 | H69: =SUM(D69:G69) -> 270000 | I69: 270000 | J69: =H69-I69 -> 0
C70: Q3 | D70: 261750 | H70: =SUM(D70:G70) -> 261750 | I70: 261750 | J70: =H70-I70 -> 0
C71: Q4 | D71: 258750 | H71: =SUM(D71:G71) -> 258750 | I71: 258750 | J71: =H71-I71 -> 0
B72: 1991 | C72: Q1 | D72: 235500 | H72: =SUM(D72:G72) -> 235500 | I72: 235500 | J72: =H72-I72 -> 0
C73: Q2 | D73: 243000 | H73: =SUM(D73:G73) -> 243000 | I73: 243000 | J73: =H73-I73 -> 0
C74: Q3 | D74: 264750 | H74: =SUM(D74:G74) -> 264750 | I74: 264750 | J74: =H74-I74 -> 0
C75: Q4 | D75: 236250 | H75: =SUM(D75:G75) -> 236250 | I75: 236250 | J75: =H75-I75 -> 0
B76: 1992 | C76: Q1 | D76: 177000 | H76: =SUM(D76:G76) -> 177000 | I76: 177000 | J76: =H76-I76 -> 0
C77: Q2 | D77: 198750 | H77: =SUM(D77:G77) -> 198750 | I77: 198750 | J77: =H77-I77 -> 0
C78: Q3 | D78: 275250 | H78: =SUM(D78:G78) -> 275250 | I78: 275250 | J78: =H78-I78 -> 0
C79: Q4 | D79: 201000 | H79: =SUM(D79:G79) -> 201000 | I79: 201000 | J79: =H79-I79 -> 0
B80: 1993 | C80: Q1 | D80: 179250 | H80: =SUM(D80:G80) -> 179250 | I80: 179250 | J80: =H80-I80 -> 0
C81: Q2 | D81: 209250 | H81: =SUM(D81:G81) -> 209250 | I81: 209250 | J81: =H81-I81 -> 0
C82: Q3 | D82: 260250 | H82: =SUM(D82:G82) -> 260250 | I82: 260250 | J82: =H82-I82 -> 0
C83: Q4 | D83: 248250 | H83: =SUM(D83:G83) -> 248250 | I83: 248250 | J83: =H83-I83 -> 0
B84: 1994 | C84: Q1 | D84: 224250 | H84: =SUM(D84:G84) -> 224250 | I84: 224250 | J84: =H84-I84 -> 0
C85: Q2 | D85: 234000 | H85: =SUM(D85:G85) -> 234000 | I85: 234000 | J85: =H85-I85 -> 0
C86: Q3 | D86: 258750 | H86: =SUM(D86:G86) -> 258750 | I86: 258750 | J86: =H86-I86 -> 0
C87: Q4 | D87: 239250 | H87: =SUM(D87:G87) -> 239250 | I87: 239250 | J87: =H87-I87 -> 0
B88: 1995 | C88: Q1 | D88: 213000 | H88: =SUM(D88:G88) -> 213000 | I88: 213000 | J88: =H88-I88 -> 0
C89: Q2 | D89: 210000 | H89: =SUM(D89:G89) -> 210000 | I89: 210000 | J89: =H89-I89 -> 0
C90: Q3 | D90: 223500 | H90: =SUM(D90:G90) -> 223500 | I90: 223500 | J90: =H90-I90 -> 0
C91: Q4 | D91: 204000 | H91: =SUM(D91:G91) -> 204000 | I91: 204000 | J91: =H91-I91 -> 0
B92: 1996 | C92: Q1 | E92: 185027 | H92: =SUM(D92:G92) -> 185027 | I92: 185027 | J92: =H92-I92 -> 0
C93: Q2 | E93: 238478 | H93: =SUM(D93:G93) -> 238478 | I93: 238478 | J93: =H93-I93 -> 0
C94: Q3 | E94: 279743 | H94: =SUM(D94:G94) -> 279743 | I94: 279743 | J94: =H94-I94 -> 0
C95: Q4 | E95: 290748 | H95: =SUM(D95:G95) -> 290748 | I95: 290748 | J95: =H95-I95 -> 0
B96: 1997 | C96: Q1 | E96: 228736 | H96: =SUM(D96:G96) -> 228736 | I96: 228736 | J96: =H96-I96 -> 0
C97: Q2 | E97: 289049 | H97: =SUM(D97:G97) -> 289049 | I97: 289049 | J97: =H97-I97 -> 0
C98: Q3 | E98: 316937 | H98: =SUM(D98:G98) -> 316937 | I98: 316937 | J98: =H98-I98 -> 0
C99: Q4 | E99: 289365 | H99: =SUM(D99:G99) -> 289365 | I99: 289365 | J99: =H99-I99 -> 0
B100: 1998 | C100: Q1 | E100: 218153 | H100: =SUM(D100:G100) -> 218153 | I100: 218153 | J100: =H100-I100 -> 0
C101: Q2 | E101: 279969 | H101: =SUM(D101:G101) -> 279969 | I101: 279969 | J101: =H101-I101 -> 0
C102: Q3 | E102: 302169 | H102: =SUM(D102:G102) -> 302169 | I102: 302169 | J102: =H102-I102 -> 0
...

Sheet Private housing stock
D3: Cat 1 | E3: Cat 2 | F3: Cat 3 | G3: Cat4 | H3: Cat 5 | I3: Cat 6 | J3: GB:ENG | K3: Updated | L3: Previous | M3: Difference | O3: Raw data download processing..
B4: Notes 1 | D4: Live tables on dwelling stock (including vacants) [DLUHC] | E4: Live tables on dwelling stock (including vacants) [DLUHC] | F4: Dwelling stock by tenure, UK [ONS] | G4: Dwelling stock by tenure, UK [ONS] | H4: Dwelling stock by tenure, UK [ONS] | I4: Dwelling stock by tenure, UK [ONS]
B5: Notes 2 | D5: Dwelling stock by tenure, GB | E5: Dwelling stock by tenure, GB | Q5: GB OO stock | R5: GB PR stock | S5: GBOOPR stock | W5: Starts | Y5: OOPR stock
B6: Link | D6: Live tables on dwelling stock (including vacants) - GOV.UK (www.gov.uk) | E6: Live tables on dwelling stock (including vacants) - GOV.UK (www.gov.uk) | F6: Dwelling stock by tenure, UK - Office for National Statistics (ons.gov.uk) | G6: Dwelling stock by tenure, UK - Office for National Statistics (ons.gov.uk)
B7: Table | D7: Table 102 - owner occupied | E7: Table 102 - rented privately | F7: Table 2 - owner occupied | G7: Table 2 - rented privately | H7: Table 3 - owner occupied | I7: Table 3 - rented privately
B8: 1975 | C8: Q1 | D8: 10340 | E8: 3233 | K8: =SUM(D8:G8) -> 13573 | L8: 10499.456 | O8: 1975 | P8: December | Q8: 10529 | R8: 3118 | S8: =Q8+R8 -> 13647 | U8: 1975 | V8: Q1 | W8: 28800 | X8: =W8/SUM(W8:W11) -> 0.19302949 | Y8: 13573
C9: Q2 | L9: 10529 | O9: 1976 | P9: December | Q9: 10724 | R9: 3027 | S9: =Q9+R9 -> 13751 | V9: Q2 | W9: 41600 | X9: =W9/SUM(W8:W11) -> 0.27882038 | Y9: =Y8+X8*(Y12-Y8) -> 13587.284
C10: Q3 | L10: 10583.229 | O10: 1977 | P10: December | Q10: 11026 | R10: 2597 | S10: =Q10+R10 -> 13623 | V10: Q3 | W10: 41400 | X10: =W10/SUM(W8:W11) -> 0.27747989 | Y10: =Y8+(X8+X9)*(Y12-Y8) -> 13607.917
C11: Q4 | L11: 10629.286 | O11: 1978 | P11: December | Q11: 11273 | R11: 2492 | S11: =Q11+R11 -> 13765 | V11: Q4 | W11: 37400 | X11: =W11/SUM(W8:W11) -> 0.25067024 | Y11: =Y8+(X8+X9+X10)*(Y12-Y8) -> 13628.45
B12: 1976 | C12: Q1 | D12: 10529 | E12: 3118 | K12: =SUM(D12:G12) -> 13647 | L12: 10670.514 | O12: 1979 | P12: December | Q12: 11520 | R12: 2385 | S12: =Q12+R12 -> 13905 | U12: 1976 | V12: Q1 | W12: 37200 | X12: =W12/SUM(W12:W15) -> 0.24062096 | Y12: 13647
C13: Q2 | L13: 10724 | O13: 1980 | P13: December | Q13: 11618 | R13: 2410 | S13: =Q13+R13 -> 14028 | V13: Q2 | W13: 46500 | X13: =W13/SUM(W12:W15) -> 0.3007762 | Y13: =Y12+X12*(Y16-Y12) -> 13672.025
C14: Q3 | L14: 10803.716 | O14: 1981 | P14: December | Q14: 11936 | R14: 2288 | S14: =Q14+R14 -> 14224 | V14: Q3 | W14: 42800 | X14: =W14/SUM(W12:W15) -> 0.27684347 | Y14: =Y12+(X12+X13)*(Y16-Y12) -> 13703.305
C15: Q4 | L15: 10883.048 | O15: 1982 | P15: December | Q15: 12357 | R15: 2201 | S15: =Q15+R15 -> 14558 | V15: Q4 | W15: 28100 | X15: =W15/SUM(W12:W15) -> 0.18175938 | Y15: =Y12+(X12+X13+X14)*(Y16-Y12) -> 13732.097
B16: 1977 | C16: Q1 | D16: 10724 | E16: 3027 | K16: =SUM(D16:G16) -> 13751 | L16: 10954.716 | O16: 1983 | P16: December | Q16: 12740 | R16: 2121 | S16: =Q16+R16 -> 14861 | U16: 1977 | V16: Q1 | W16: 26200 | X16: =W16/SUM(W16:W19) -> 0.19436202 | Y16: 13751
C17: Q2 | L17: 11026 | O17: 1984 | P17: December | Q17: 13099 | R17: 2040 | S17: =Q17+R17 -> 15139 | V17: Q2 | W17: 38100 | X17: =W17/SUM(W16:W19) -> 0.28264095 | Y17: =Y16+X16*(Y20-Y16) -> 13726.122
C18: Q3 | L18: 11105.983 | O18: 1985 | P18: December | Q18: 13440 | R18: 1963 | S18: =Q18+R18 -> 15403 | V18: Q3 | W18: 39100 | X18: =W18/SUM(W16:W19) -> 0.29005935 | Y18: =Y16+(X16+X17)*(Y20-Y16) -> 13689.944
C19: Q4 | L19: 11179.601 | O19: 1986 | P19: December | Q19: 13790 | R19: 1885 | S19: =Q19+R19 -> 15675 | V19: Q4 | W19: 31400 | X19: =W19/SUM(W16:W19) -> 0.23293769 | Y19: =Y16+(X16+X17+X18)*(Y20-Y16) -> 13652.816
B20: 1978 | C20: Q1 | D20: 11026 | E20: 2597 | K20: =SUM(D20:G20) -> 13623 | L20: 11227.935 | O20: 1987 | P20: December | Q20: 13968 | R20: 2139 | S20: =Q20+R20 -> 16107 | U20: 1978 | V20: Q1 | W20: 30390 | X20: =W20/SUM(W20:W23) -> 0.19318543 | Y20: 13623
C21: Q2 | L21: 11273 | O21: 1988 | P21: December | Q21: 14424 | R21: 2077 | S21: =Q21+R21 -> 16501 | V21: Q2 | W21: 46510 | X21: =W21/SUM(W20:W23) -> 0.29565825 | Y21: =Y20+X20*(Y24-Y20) -> 13650.432
C22: Q3 | L22: 11340.708 | O22: 1989 | P22: December | Q22: 14832 | R22: 2069 | S22: =Q22+R22 -> 16901 | V22: Q3 | W22: 41310 | X22: =W22/SUM(W20:W23) -> 0.2626025 | Y22: =Y20+(X20+X21)*(Y24-Y20) -> 13692.416
C23: Q4 | L23: 11410.193 | O23: 1990 | P23: December | Q23: 15099 | R23: 2123 | S23: =Q23+R23 -> 17222 | V23: Q4 | W23: 39100 | X23: =W23/SUM(W20:W23) -> 0.24855381 | Y23: =Y20+(X20+X21+X22)*(Y24-Y20) -> 13729.705
B24: 1979 | C24: Q1 | D24: 11273 | E24: 2492 | K24: =SUM(D24:G24) -> 13765 | L24: 11465.994 | O24: 1991 | P24: March | Q24: 15155 | R24: 1990 | S24: =Q24+R24 -> 17145 | U24: 1979 | V24: Q1 | W24: 23320 | X24: =W24/SUM(W24:W27) -> 0.1619332 | Y24: 13765
C25: Q2 | L25: 11520 | O25: 1992 | P25: March | Q25: 15367 | R25: 2058 | S25: =Q25+R25 -> 17425 | V25: Q2 | W25: 40050 | X25: =W25/SUM(W24:W27) -> 0.27810569 | Y25: =Y24+X24*(Y28-Y24) -> 13787.671
C26: Q3 | L26: 11550.338 | O26: 1993 | P26: March | Q26: 15523 | R26: 2120 | S26: =Q26+R26 -> 17643 | V26: Q3 | W26: 41250 | X26: =W26/SUM(W24:W27) -> 0.28643844 | Y26: =Y24+(X24+X25)*(Y28-Y24) -> 13826.605
C27: Q4 | L27: 11577.278 | O27: 1994 | P27: March | Q27: 15695 | R27: 2184 | S27: =Q27+R27 -> 17879 | V27: Q4 | W27: 39390 | X27: =W27/SUM(W24:W27) -> 0.27352267 | Y27: =Y24+(X24+X25+X26)*(Y28-Y24) -> 13866.707
B28: 1980 | C28: Q1 | D28: 11520 | E28: 2385 | K28: =SUM(D28:G28) -> 13905 | L28: 11602.789 | O28: 1995 | P28: March | Q28: 15869 | R28: 2255 | S28: =Q28+R28 -> 18124 | U28: 1980 | V28: Q1 | W28: 24530 | X28: =W28/SUM(W28:W31) -> 0.25028058 | Y28: 13905
C29: Q2 | L29: 11618 | O29: 1996 | P29: March | Q29: 16013 | R29: 2332 | S29: =Q29+R29 -> 18345 | V29: Q2 | W29: 29440 | X29: =W29/SUM(W28:W31) -> 0.30037751 | Y29: =Y28+X28*(Y32-Y28) -> 13935.785
C30: Q3 | L30: 11705.717 | O30: 1997 | P30: March | Q30: 16215 | R30: 2361 | S30: =Q30+R30 -> 18576 | V30: Q3 | W30: 23370 | X30: =W30/SUM(W28:W31) -> 0.23844506 | Y30: =Y28+(X28+X29)*(Y32-Y28) -> 13972.731
C31: Q4 | L31: 11796.039 | O31: 1998 | P31: March | Q31: 16461 | R31: 2367 | S31: =Q31+R31 -> 18828 | V31: Q4 | W31: 20670 | X31: =W31/SUM(W28:W31) -> 0.21089685 | Y31: =Y28+(X28+X29+X30)*(Y32-Y28) -> 14002.06
B32: 1981 | C32: Q1 | D32: 11618 | E32: 2410 | K32: =SUM(D32:G32) -> 14028 | L32: 11882.288 | O32: 1999 | P32: March | Q32: 16734 | R32: 2324 | S32: =Q32+R32 -> 19058 | U32: 1981 | V32: Q1 | W32: 26290 | X32: =W32/SUM(W32:W35) -> 0.22835056 | Y32: 14028
C33: Q2 | L33: 11936 | O33: 2000 | P33: March | Q33: 16949 | R33: 2350 | S33: =Q33+R33 -> 19299 | V33: Q2 | W33: 32240 | X33: =W33/SUM(W32:W35) -> 0.28003127 | Y33: =Y32+X32*(Y36-Y32) -> 14072.757
C34: Q3 | L34: 12060.27 | O34: 2001 | P34: March | Q34: 17115 | R34: 2404 | S34: =Q34+R34 -> 19519 | V34: Q3 | W34: 32080 | X34: =W34/SUM(W32:W35) -> 0.27864154 | Y34: =Y32+(X32+X33)*(Y36-Y32) -> 14127.643
C35: Q4 | L35: 12158.969 | O35: 2002 | P35: March | Q35: 17280 | R35: 2465 | S35: =Q35+R35 -> 19745 | V35: Q4 | W35: 24520 | X35: =W35/SUM(W32:W35) -> 0.21297664 | Y35: =Y32+(X32+X33+X34)*(Y36-Y32) -> 14182.257
B36: 1982 | C36: Q1 | D36: 11936 | E36: 2288 | K36: =SUM(D36:G36) -> 14224 | L36: 12246.022 | O36: 2003 5 | P36: March | Q36: 17223 | R36: 2834 | S36: =Q36+R36 -> 20057 | U36: 1982 | V36: Q1 | W36: 31770 | X36: =W36/SUM(W36:W39) -> 0.22687995 | Y36: 14224
C37: Q2 | L37: 12357 | O37: 2004 5 | P37: March | Q37: 17478 | R37: 2895 | S37: =Q37+R37 -> 20373 | V37: Q2 | W37: 38120 | X37: =W37/SUM(W36:W39) -> 0.27222738 | Y37: =Y36+X36*(Y40-Y36) -> 14299.778
C38: Q3 | L38: 12459.517 | O38: 2005 5 | P38: March | Q38: 17625 | R38: 3054 | S38: =Q38+R38 -> 20679 | V38: Q3 | W38: 38000 | X38: =W38/SUM(W36:W39) -> 0.27137042 | Y38: =Y36+(X36+X37)*(Y40-Y36) -> 14390.702
C39: Q4 | L39: 12561.303 | O39: 2006 5 | P39: March | Q39: 17608 | R39: 3334 | S39: =Q39+R39 -> 20942 | V39: Q4 | W39: 32140 | X39: =W39/SUM(W36:W39) -> 0.22952225 | Y39: =Y36+(X36+X37+X38)*(Y40-Y36) -> 14481.34
B40: 1983 | C40: Q1 | D40: 12357 | E40: 2201 | K40: =SUM(D40:G40) -> 14558 | L40: 12639.167 | O40: 2007 5 | P40: March | Q40: 17657 | R40: 3563 | S40: =Q40+R40 -> 21220 | U40: 1983 | V40: Q1 | W40: 39890 | X40: =W40/SUM(W40:W43) -> 0.23568685 | Y40: 14558
C41: Q2 | L41: 12740 | O41: 2008 5 | P41: March | Q41: 17660 | R41: 3837 | S41: =Q41+R41 -> 21497 | V41: Q2 | W41: 47850 | X41: =W41/SUM(W40:W43) -> 0.28271787 | Y41: =Y40+X40*(Y44-Y40) -> 14629.413
C42: Q3 | L42: 12832.166 | O42: 2009 5 | P42: March | Q42: 17547 | R42: 4147 | S42: =Q42+R42 -> 21694 | V42: Q3 | W42: 43730 | X42: =W42/SUM(W40:W43) -> 0.25837518 | Y42: =Y40+(X40+X41)*(Y44-Y40) -> 14715.077
C43: Q4 | L43: 12924.21 | O43: 2010 5 | P43: March | Q43: 17463 | R43: 4385 | S43: =Q43+R43 -> 21848 | V43: Q4 | W43: 37780 | X43: =W43/SUM(W40:W43) -> 0.22322009 | Y43: =Y40+(X40+X41+X42)*(Y44-Y40) -> 14793.364
B44: 1984 | C44: Q1 | D44: 12740 | E44: 2121 | K44: =SUM(D44:G44) -> 14861 | L44: 13002.33 | O44: 2011 5 | P44: March | Q44: 17388 | R44: 4605 | S44: =Q44+R44 -> 21993 | U44: 1984 | V44: Q1 | W44: 37090 | X44: =W44/SUM(W44:W47) -> 0.24140849 | Y44: 14861
C45: Q2 | L45: 13099 | O45: 2012 5 | P45: March | Q45: 17276 | R45: 4841 | S45: =Q45+R45 -> 22117 | V45: Q2 | W45: 43670 | X45: =W45/SUM(W44:W47) -> 0.28423588 | Y45: =Y44+X44*(Y48-Y44) -> 14928.112
C46: Q3 | L46: 13196.896 | O46: 2013 5 | P46: March | Q46: 17201 | R46: 5046 | S46: =Q46+R46 -> 22247 | V46: Q3 | W46: 40180 | X46: =W46/SUM(W44:W47) -> 0.26152044 | Y46: =Y44+(X44+X45)*(Y48-Y44) -> 15007.129
C47: Q4 | L47: 13286.625 | O47: 2014 5 | P47: March | Q47: 17201 | R47: 5212 | S47: =Q47+R47 -> 22413 | V47: Q4 | W47: 32700 | X47: =W47/SUM(W44:W47) -> 0.2128352 | Y47: =Y44+(X44+X45+X46)*(Y48-Y44) -> 15079.832
B48: 1985 | C48: Q1 | D48: 13099 | E48: 2040 | K48: =SUM(D48:G48) -> 15139 | L48: 13364.049 | O48: 2015 5 | P48: March | Q48: 17217 | R48: 5376 | S48: =Q48+R48 -> 22593 | U48: 1985 | V48: Q1 | W48: 33640 | X48: =W48/SUM(W48:W51) -> 0.20709185 | Y48: 15139
C49: Q2 | L49: 13440 | O49: 2016 5 | P49: March | Q49: 17341 | R49: 5452 | S49: =Q49+R49 -> 22793 | V49: Q2 | W49: 45460 | X49: =W49/SUM(W48:W51) -> 0.27985718 | Y49: =Y48+X48*(Y52-Y48) -> 15193.672
C50: Q3 | L50: 13541.804 | O50: 2017 5 | P50: March | Q50: 17617 | R50: 5416 | S50: =Q50+R50 -> 23033 | V50: Q3 | W50: 44650 | X50: =W50/SUM(W48:W51) -> 0.27487072 | Y50: =Y48+(X48+X49)*(Y52-Y48) -> 15267.555
C51: Q4 | L51: 13635.617 | O51: 2018 | P51: March | Q51: 17925 | R51: 5367 | S51: =Q51+R51 -> 23292 | V51: Q4 | W51: 38690 | X51: =W51/SUM(W48:W51) -> 0.23818025 | Y51: =Y48+(X48+X49+X50)*(Y52-Y48) -> 15340.12
B52: 1986 | C52: Q1 | D52: 13440 | E52: 1963 | K52: =SUM(D52:G52) -> 15403 | L52: 13711.655 | O52: 2019 | P52: March | Q52: 18171.367 | R52: 5364.2664 | S52: =Q52+R52 -> 23535.634 | U52: 1986 | V52: Q1 | W52: 35890 | X52: =W52/SUM(W52:W55) -> 0.20429189 | Y52: 15403
C53: Q2 | L53: 13790 | O53: 2020 | P53: March | Q53: 18347 | R53: 5434 | S53: =Q53+R53 -> 23781 | V53: Q2 | W53: 50150 | X53: =W53/SUM(W52:W55) -> 0.2854622 | Y53: =Y52+X52*(Y56-Y52) -> 15458.567
C54: Q3 | L54: 13839.094 | V54: Q3 | W54: 49990 | X54: =W54/SUM(W52:W55) -> 0.28455146 | Y54: =Y52+(X52+X53)*(Y56-Y52) -> 15536.213
C55: Q4 | L55: 13887.325 | V55: Q4 | W55: 39650 | X55: =W55/SUM(W52:W55) -> 0.22569444 | Y55: =Y52+(X52+X53+X54)*(Y56-Y52) -> 15613.611
B56: 1987 | C56: Q1 | D56: 13790 | E56: 1885 | K56: =SUM(D56:G56) -> 15675 | L56: 13929.152 | U56: 1987 | V56: Q1 | W56: 44270 | X56: =W56/SUM(W56:W59) -> 0.22929507 | Y56: 15675
C57: Q2 | L57: 13968 | V57: Q2 | W57: 51080 | X57: =W57/SUM(W56:W59) -> 0.26456726 | Y57: =Y56+X56*(Y60-Y56) -> 15774.055
C58: Q3 | L58: 14092.224 | V58: Q3 | W58: 53200 | X58: =W58/SUM(W56:W59) -> 0.27554773 | Y58: =Y56+(X56+X57)*(Y60-Y56) -> 15888.349
C59: Q4 | L59: 14216.176 | V59: Q4 | W59: 44520 | X59: =W59/SUM(W56:W59) -> 0.23058994 | Y59: =Y56+(X56+X57+X58)*(Y60-Y56) -> 16007.385
B60: 1988 | C60: Q1 | D60: 13968 | E60: 2139 | K60: =SUM(D60:G60) -> 16107 | L60: 14314.258 | U60: 1988 | V60: Q1 | W60: 51200 | X60: =W60/SUM(W60:W63) -> 0.23356599 | Y60: 16107
C61: Q2 | L61: 14424 | V61: Q2 | W61: 61290 | X61: =W61/SUM(W60:W63) -> 0.27959491 | Y61: =Y60+X60*(Y64-Y60) -> 16199.025
C62: Q3 | L62: 14528.218 | V62: Q3 | W62: 55970 | X62: =W62/SUM(W60:W63) -> 0.25532594 | Y62: =Y60+(X60+X61)*(Y64-Y60) -> 16309.185
C63: Q4 | L63: 14636.637 | V63: Q4 | W63: 50750 | X63: =W63/SUM(W60:W63) -> 0.23151316 | Y63: =Y60+(X60+X61+X62)*(Y64-Y60) -> 16409.784
B64: 1989 | C64: Q1 | D64: 14424 | E64: 2077 | K64: =SUM(D64:G64) -> 16501 | L64: 14727.456 | U64: 1989 | V64: Q1 | W64: 46690 | X64: =W64/SUM(W64:W67) -> 0.27557103 | Y64: 16501
C65: Q2 | L65: 14832 | V65: Q2 | W65: 50010 | X65: =W65/SUM(W64:W67) -> 0.29516615 | Y65: =Y64+X64*(Y68-Y64) -> 16611.228
C66: Q3 | L66: 14908.206 | V66: Q3 | W66: 40280 | X66: =W66/SUM(W64:W67) -> 0.2377383 | Y66: =Y64+(X64+X65)*(Y68-Y64) -> 16729.295
C67: Q4 | L67: 14977.824 | V67: Q4 | W67: 32450 | X67: =W67/SUM(W64:W67) -> 0.19152452 | Y67: =Y64+(X64+X65+X66)*(Y68-Y64) -> 16824.39
B68: 1990 | C68: Q1 | D68: 14832 | E68: 2069 | K68: =SUM(D68:G68) -> 16901 | L68: 15040.966 | U68: 1990 | V68: Q1 | W68: 35980 | X68: =W68/SUM(W68:W71) -> 0.26253192 | Y68: 16901
C69: Q2 | L69: 15099 | V69: Q2 | W69: 37390 | X69: =W69/SUM(W68:W71) -> 0.27282014 | Y69: =Y68+X68*(Y72-Y68) -> 16985.273
C70: Q3 | L70: 15116.628 | V70: Q3 | W70: 34350 | X70: =W70/SUM(W68:W71) -> 0.25063845 | Y70: =Y68+(X68+X69)*(Y72-Y68) -> 17072.848
C71: Q4 | L71: 15130.815 | V71: Q4 | W71: 29330 | X71: =W71/SUM(W68:W71) -> 0.21400949 | Y71: =Y68+(X68+X69+X70)*(Y72-Y68) -> 17153.303
B72: 1991 | C72: Q1 | D72: 15099 | E72: 2123 | K72: =SUM(D72:G72) -> 17222 | L72: 15142.337 | U72: 1991 | V72: Q1 | W72: 32010 | X72: =W72/SUM(W72:W75) -> 0.23431667 | Y72: 17222
C73: Q2 | D73: 15155 | E73: 1990 | K73: =SUM(D73:G73) -> 17145 | L73: 15155 | V73: Q2 | W73: 38350 | X73: =W73/SUM(W72:W75) -> 0.28072615 | Y73: 17145
C74: Q3 | L74: 15214.552 | V74: Q3 | W74: 36510 | X74: =W74/SUM(W72:W75) -> 0.26725716 | Y74: =Y73+X73*(Y77-Y73) -> 17223.603
C75: Q4 | L75: 15269.276 | V75: Q4 | W75: 29740 | X75: =W75/SUM(W72:W75) -> 0.21770002 | Y75: =Y73+(X73+X74)*(Y77-Y73) -> 17298.435
B76: 1992 | C76: Q1 | L76: 15316.003 | U76: 1992 | V76: Q1 | W76: 32040 | X76: =W76/SUM(W76:W79) -> 0.26664447 | Y76: =Y73+(X73+X74+X75)*(Y77-Y73) -> 17359.391
C77: Q2 | D77: 15367 | E77: 2058 | K77: =SUM(D77:G77) -> 17425 | L77: 15367 | V77: Q2 | W77: 34800 | X77: =W77/SUM(W76:W79) -> 0.28961385 | Y77: 17425
C78: Q3 | L78: 15410.78 | V78: Q3 | W78: 29770 | X78: =W78/SUM(W76:W79) -> 0.247753 | Y78: =Y77+X77*(Y81-Y77) -> 17488.136
C79: Q4 | L79: 15452.46 | V79: Q4 | W79: 23550 | X79: =W79/SUM(W76:W79) -> 0.19598868 | Y79: =Y77+(X77+X78)*(Y81-Y77) -> 17542.146
B80: 1993 | C80: Q1 | L80: 15486.412 | U80: 1993 | V80: Q1 | W80: 34910 | X80: =W80/SUM(W80:W83) -> 0.24774679 | Y80: =Y77+(X77+X78+X79)*(Y81-Y77) -> 17584.872
C81: Q2 | D81: 15523 | E81: 2120 | K81: =SUM(D81:G81) -> 17643 | L81: 15523 | V81: Q2 | W81: 38690 | X81: =W81/SUM(W80:W83) -> 0.27457242 | Y81: 17643
C82: Q3 | L82: 15571.642 | V82: Q3 | W82: 36000 | X82: =W82/SUM(W80:W83) -> 0.25548222 | Y82: =Y81+X81*(Y85-Y81) -> 17707.799
C83: Q4 | L83: 15613.264 | V83: Q4 | W83: 31310 | X83: =W83/SUM(W80:W83) -> 0.22219857 | Y83: =Y81+(X81+X82)*(Y85-Y81) -> 17768.093
B84: 1994 | C84: Q1 | L84: 15646.191 | U84: 1994 | V84: Q1 | W84: 39280 | X84: =W84/SUM(W84:W87) -> 0.24712174 | Y84: =Y81+(X81+X82+X83)*(Y85-Y81) -> 17820.532
C85: Q2 | D85: 15695 | E85: 2184 | K85: =SUM(D85:G85) -> 17879 | L85: 15695 | V85: Q2 | W85: 44380 | X85: =W85/SUM(W84:W87) -> 0.2792073 | Y85: 17879
C86: Q3 | L86: 15741.333 | V86: Q3 | W86: 41020 | X86: =W86/SUM(W84:W87) -> 0.25806858 | Y86: =Y85+X85*(Y89-Y85) -> 17947.406
C87: Q4 | L87: 15784.456 | V87: Q4 | W87: 34270 | X87: =W87/SUM(W84:W87) -> 0.21560239 | Y87: =Y85+(X85+X86)*(Y89-Y85) -> 18010.633
B88: 1995 | C88: Q1 | L88: 15821.96 | U88: 1995 | V88: Q1 | W88: 35470 | X88: =W88/SUM(W88:W91) -> 0.26328682 | Y88: =Y85+(X85+X86+X87)*(Y89-Y85) -> 18063.455
C89: Q2 | D89: 15869 | E89: 2255 | K89: =SUM(D89:G89) -> 18124 | L89: 15869 | V89: Q2 | W89: 39370 | X89: =W89/SUM(W88:W91) -> 0.29223575 | Y89: 18124
C90: Q3 | L90: 15910.196 | V90: Q3 | W90: 33890 | X90: =W90/SUM(W88:W91) -> 0.25155879 | Y90: =Y89+X89*(Y93-Y89) -> 18188.584
C91: Q4 | L91: 15948.273 | V91: Q4 | W91: 25990 | X91: =W91/SUM(W88:W91) -> 0.19291865 | Y91: =Y89+(X89+X90)*(Y93-Y89) -> 18244.179
B92: 1996 | C92: Q1 | L92: 15980.075 | U92: 1996 | V92: Q1 | W92: 33280 | X92: =W92/SUM(W92:W95) -> 0.22841455 | Y92: =Y89+(X89+X90+X91)*(Y93-Y89) -> 18286.814
C93: Q2 | D93: 16013 | E93: 2332 | K93: =SUM(D93:G93) -> 18345 | L93: 16013 | V93: Q2 | W93: 37720 | X93: =W93/SUM(W92:W95) -> 0.25888813 | Y93: 18345
C94: Q3 | L94: 16072.996 | V94: Q3 | W94: 39160 | X94: =W94/SUM(W92:W95) -> 0.26877145 | Y94: =Y93+X93*(Y97-Y93) -> 18404.803
C95: Q4 | L95: 16124.655 | V95: Q4 | W95: 35540 | X95: =W95/SUM(W92:W95) -> 0.24392588 | Y95: =Y93+(X93+X94)*(Y97-Y93) -> 18466.889
B96: 1997 | C96: Q1 | L96: 16164.271 | U96: 1997 | V96: Q1 | W96: 42510 | X96: =W96/SUM(W96:W99) -> 0.26074956 | Y96: =Y93+(X93+X94+X95)*(Y97-Y93) -> 18523.236
C97: Q2 | D97: 16215 | E97: 2361 | K97: =SUM(D97:G97) -> 18576 | L97: 16215 | V97: Q2 | W97: 42510 | X97: =W97/SUM(W96:W99) -> 0.26074956 | Y97: 18576
C98: Q3 | L98: 16281.888 | V98: Q3 | W98: 41520 | X98: =W98/SUM(W96:W99) -> 0.25467705 | Y98: =Y97+X97*(Y101-Y97) -> 18641.709
C99: Q4 | L99: 16351.33 | V99: Q4 | W99: 36490 | X99: =W99/SUM(W96:W99) -> 0.22382384 | Y99: =Y97+(X97+X98)*(Y101-Y97) -> 18705.888
B100: 1998 | C100: Q1 | L100: 16414.335 | U100: 1998 | V100: Q1 | W100: 41870 | X100: =W100/SUM(W100:W103) -> 0.26993746 | Y100: =Y97+(X97+X98+X99)*(Y101-Y97) -> 18762.291
C101: Q2 | D101: 16461 | E101: 2367 | K101: =SUM(D101:G101) -> 18828 | L101: 16489.7 | V101: Q2 | W101: 40580 | X101: =W101/SUM(W100:W103) -> 0.26162079 | Y101: 18828
C102: Q3 | L102: 16566.994 | V102: Q3 | W102: 40620 | X102: =W102/SUM(W100:W103) -> 0.26187867 | Y102: =Y101+X101*(Y105-Y101) -> 18888.173
...

Sheet Interest rate
D3: Cat 1 | E3: Cat 2 | F3: Cat 3 | G3: Cat4 | H3: Updated | I3: Previous | J3: Difference | L3: Raw data download processing..
B4: Notes 1 | D4: Official Bank Rate History [BoE] | H4: Cat 1
B5: Notes 2
B6: Link | D6: Bank Rate history and data | Bank of England Database
B7: Table
B8: 1975 | C8: Q1 | D8: 10.783333 | H8: =SUM(D8:G8) -> 10.783333 | I8: 10.783333 | J8: =H8-I8 -> 0 | L8: 1975 | M8: Q1 | N8: 10.783333 | P8: 20 Jan 75 | Q8: 11.25 | S8: 27395 | T8: 11.5
C9: Q2 | D9: 9.9615385 | H9: =SUM(D9:G9) -> 9.9615385 | I9: 9.9615385 | J9: =H9-I9 -> 0 | M9: Q2 | N9: 9.9615385 | P9: 27 Jan 75 | Q9: 11 | S9: 27396 | T9: 11.5
C10: Q3 | D10: 10.706522 | H10: =SUM(D10:G10) -> 10.706522 | I10: 10.706522 | J10: =H10-I10 -> 0 | M10: Q3 | N10: 10.706522 | P10: 10 Feb 75 | Q10: 10.75 | S10: 27397 | T10: 11.5
C11: Q4 | D11: 11.730978 | H11: =SUM(D11:G11) -> 11.730978 | I11: 11.730978 | J11: =H11-I11 -> 0 | M11: Q4 | N11: 11.730978 | P11: 17 Feb 75 | Q11: 10.5 | S11: 27398 | T11: 11.5
B12: 1976 | C12: Q1 | D12: 9.8681319 | H12: =SUM(D12:G12) -> 9.8681319 | I12: 9.8681319 | J12: =H12-I12 -> 0 | L12: 1976 | M12: Q1 | N12: 9.8681319 | P12: 10 Mar 75 | Q12: 10.25 | S12: 27399 | T12: 11.5
C13: Q2 | D13: 10.505495 | H13: =SUM(D13:G13) -> 10.505495 | I13: 10.505495 | J13: =H13-I13 -> 0 | M13: Q2 | N13: 10.505495 | P13: 24 Mar 75 | Q13: 10 | S13: 27400 | T13: 11.5
C14: Q3 | D14: 11.793478 | H14: =SUM(D14:G14) -> 11.793478 | I14: 11.793478 | J14: =H14-I14 -> 0 | M14: Q3 | N14: 11.793478 | P14: 21 Apr 75 | Q14: 9.75 | S14: 27401 | T14: 11.5
C15: Q4 | D15: 14.720109 | H15: =SUM(D15:G15) -> 14.720109 | I15: 14.720109 | J15: =H15-I15 -> 0 | M15: Q4 | N15: 14.720109 | P15: 05 May 75 | Q15: 10 | S15: 27402 | T15: 11.5
B16: 1977 | C16: Q1 | D16: 12.325 | H16: =SUM(D16:G16) -> 12.325 | I16: 12.325 | J16: =H16-I16 -> 0 | L16: 1977 | M16: Q1 | N16: 12.325 | P16: 28 Jul 75 | Q16: 11 | S16: 27403 | T16: 11.5
C17: Q2 | D17: 8.4368132 | H17: =SUM(D17:G17) -> 8.4368132 | I17: 8.4368132 | J17: =H17-I17 -> 0 | M17: Q2 | N17: 8.4368132 | P17: 06 Oct 75 | Q17: 12 | S17: 27404 | T17: 11.5
C18: Q3 | D18: 7.2826087 | H18: =SUM(D18:G18) -> 7.2826087 | I18: 7.2826087 | J18: =H18-I18 -> 0 | M18: Q3 | N18: 7.2826087 | P18: 17 Nov 75 | Q18: 11.75 | S18: 27405 | T18: 11.5
C19: Q4 | D19: 5.875 | H19: =SUM(D19:G19) -> 5.875 | I19: 5.875 | J19: =H19-I19 -> 0 | M19: Q4 | N19: 5.875 | P19: 01 Dec 75 | Q19: 11.5 | S19: 27406 | T19: 11.5
B20: 1978 | C20: Q1 | D20: 6.5444444 | H20: =SUM(D20:G20) -> 6.5444444 | I20: 6.5444444 | J20: =H20-I20 -> 0 | L20: 1978 | M20: Q1 | N20: 6.5444444 | P20: 29 Dec 75 | Q20: 11.25 | S20: 27407 | T20: 11.5
C21: Q2 | D21: 8.5027473 | H21: =SUM(D21:G21) -> 8.5027473 | I21: 8.5027473 | J21: =H21-I21 -> 0 | M21: Q2 | N21: 8.5027473 | P21: 05 Jan 76 | Q21: 11 | S21: 27408 | T21: 11.5
C22: Q3 | D22: 10 | H22: =SUM(D22:G22) -> 10 | I22: 10 | J22: =H22-I22 -> 0 | M22: Q3 | N22: 10 | P22: 19 Jan 76 | Q22: 10.75 | S22: 27409 | T22: 11.5
C23: Q4 | D23: 11.440217 | H23: =SUM(D23:G23) -> 11.440217 | I23: 11.440217 | J23: =H23-I23 -> 0 | M23: Q4 | N23: 11.440217 | P23: 26 Jan 76 | Q23: 10.5 | S23: 27410 | T23: 11.5
B24: 1979 | C24: Q1 | D24: 13.022222 | H24: =SUM(D24:G24) -> 13.022222 | I24: 13.022222 | J24: =H24-I24 -> 0 | L24: 1979 | M24: Q1 | N24: 13.022222 | P24: 02 Feb 76 | Q24: 10 | S24: 27411 | T24: 11.5
C25: Q2 | D25: 12.43956 | H25: =SUM(D25:G25) -> 12.43956 | I25: 12.43956 | J25: =H25-I25 -> 0 | M25: Q2 | N25: 12.43956 | P25: 09 Feb 76 | Q25: 9.5 | S25: 27412 | T25: 11.5
C26: Q3 | D26: 14 | H26: =SUM(D26:G26) -> 14 | I26: 14 | J26: =H26-I26 -> 0 | M26: Q3 | N26: 14 | P26: 01 Mar 76 | Q26: 9.25 | S26: 27413 | T26: 11.5
C27: Q4 | D27: 15.532609 | H27: =SUM(D27:G27) -> 15.532609 | I27: 15.532609 | J27: =H27-I27 -> 0 | M27: Q4 | N27: 15.532609 | P27: 08 Mar 76 | Q27: 9 | S27: 27414 | T27: 11.25
B28: 1980 | C28: Q1 | D28: 17 | H28: =SUM(D28:G28) -> 17 | I28: 17 | J28: =H28-I28 -> 0 | L28: 1980 | M28: Q1 | N28: 17 | P28: 26 Apr 76 | Q28: 10.5 | S28: 27415 | T28: 11.25
C29: Q2 | D29: 17 | H29: =SUM(D29:G29) -> 17 | I29: 17 | J29: =H29-I29 -> 0 | M29: Q2 | N29: 17 | P29: 24 May 76 | Q29: 11.5 | S29: 27416 | T29: 11.25
C30: Q3 | D30: 16.021739 | H30: =SUM(D30:G30) -> 16.021739 | I30: 16.021739 | J30: =H30-I30 -> 0 | M30: Q3 | N30: 16.021739 | P30: 13 Sep 76 | Q30: 13 | S30: 27417 | T30: 11.25
C31: Q4 | D31: 15.195652 | H31: =SUM(D31:G31) -> 15.195652 | I31: 15.195652 | J31: =H31-I31 -> 0 | M31: Q4 | N31: 15.195652 | P31: 07 Oct 76 | Q31: 15 | S31: 27418 | T31: 11.25
B32: 1981 | C32: Q1 | D32: 13.533333 | H32: =SUM(D32:G32) -> 13.533333 | I32: 13.533333 | J32: =H32-I32 -> 0 | L32: 1981 | M32: Q1 | N32: 13.533333 | P32: 22 Nov 76 | Q32: 14.75 | S32: 27419 | T32: 11.25
C33: Q2 | D33: 12 | H33: =SUM(D33:G33) -> 12 | I33: 12 | J33: =H33-I33 -> 0 | M33: Q2 | N33: 12 | P33: 20 Dec 76 | Q33: 14.5 | S33: 27420 | T33: 11.25
C34: Q3 | D34: 12.505326 | H34: =SUM(D34:G34) -> 12.505326 | I34: 12.505326 | J34: =H34-I34 -> 0 | M34: Q3 | N34: 12.505326 | P34: 29 Dec 76 | Q34: 14.25 | S34: 27421 | T34: 11
C35: Q4 | D35: 14.599022 | H35: =SUM(D35:G35) -> 14.599022 | I35: 14.599022 | J35: =H35-I35 -> 0 | M35: Q4 | N35: 14.599022 | P35: 10 Jan 77 | Q35: 14 | S35: 27422 | T35: 11
B36: 1982 | C36: Q1 | D36: 13.795 | H36: =SUM(D36:G36) -> 13.795 | I36: 13.795 | J36: =H36-I36 -> 0 | L36: 1982 | M36: Q1 | N36: 13.795 | P36: 24 Jan 77 | Q36: 13.25 | S36: 27423 | T36: 11
C37: Q2 | D37: 13.021978 | H37: =SUM(D37:G37) -> 13.021978 | I37: 13.021978 | J37: =H37-I37 -> 0 | M37: Q2 | N37: 13.021978 | P37: 31 Jan 77 | Q37: 12.25 | S37: 27424 | T37: 11
C38: Q3 | D38: 11.364239 | H38: =SUM(D38:G38) -> 11.364239 | I38: 11.364239 | J38: =H38-I38 -> 0 | M38: Q3 | N38: 11.364239 | P38: 03 Feb 77 | Q38: 12 | S38: 27425 | T38: 11
C39: Q4 | D39: 9.701413 | H39: =SUM(D39:G39) -> 9.701413 | I39: 9.701413 | J39: =H39-I39 -> 0 | M39: Q4 | N39: 9.701413 | P39: 10 Mar 77 | Q39: 11 | S39: 27426 | T39: 11
B40: 1983 | C40: Q1 | D40: 10.794667 | H40: =SUM(D40:G40) -> 10.794667 | I40: 10.794667 | J40: =H40-I40 -> 0 | L40: 1983 | M40: Q1 | N40: 10.794667 | P40: 21 Mar 77 | Q40: 10.5 | S40: 27427 | T40: 11
C41: Q2 | D41: 10.032527 | H41: =SUM(D41:G41) -> 10.032527 | I41: 10.032527 | J41: =H41-I41 -> 0 | M41: Q2 | N41: 10.032527 | P41: 31 Mar 77 | Q41: 9.5 | S41: 27428 | T41: 11
C42: Q3 | D42: 9.5586957 | H42: =SUM(D42:G42) -> 9.5586957 | I42: 9.5586957 | J42: =H42-I42 -> 0 | M42: Q3 | N42: 9.5586957 | P42: 12 Apr 77 | Q42: 9.25 | S42: 27429 | T42: 11
C43: Q4 | D43: 9.0708696 | H43: =SUM(D43:G43) -> 9.0708696 | I43: 9.0708696 | J43: =H43-I43 -> 0 | M43: Q4 | N43: 9.0708696 | P43: 18 Apr 77 | Q43: 9 | S43: 27430 | T43: 11
B44: 1984 | C44: Q1 | D44: 8.9418681 | H44: =SUM(D44:G44) -> 8.9418681 | I44: 8.9418681 | J44: =H44-I44 -> 0 | L44: 1984 | M44: Q1 | N44: 8.9418681 | P44: 25 Apr 77 | Q44: 8.75 | S44: 27431 | T44: 11
C45: Q2 | D45: 8.8417582 | H45: =SUM(D45:G45) -> 8.8417582 | I45: 8.8417582 | J45: =H45-I45 -> 0 | M45: Q2 | N45: 8.8417582 | P45: 02 May 77 | Q45: 8.25 | S45: 27432 | T45: 11
C46: Q3 | D46: 10.892935 | H46: =SUM(D46:G46) -> 10.892935 | I46: 10.892935 | J46: =H46-I46 -> 0 | M46: Q3 | N46: 10.892935 | P46: 16 May 77 | Q46: 8 | S46: 27433 | T46: 11
C47: Q4 | D47: 9.9673913 | H47: =SUM(D47:G47) -> 9.9673913 | I47: 9.9673913 | J47: =H47-I47 -> 0 | M47: Q4 | N47: 9.9673913 | P47: 08 Aug 77 | Q47: 7.5 | S47: 27434 | T47: 11
B48: 1985 | C48: Q1 | D48: 12.847333 | H48: =SUM(D48:G48) -> 12.847333 | I48: 12.847333 | J48: =H48-I48 -> 0 | L48: 1985 | M48: Q1 | N48: 12.847333 | P48: 15 Aug 77 | Q48: 7 | S48: 27435 | T48: 10.75
C49: Q2 | D49: 12.478901 | H49: =SUM(D49:G49) -> 12.478901 | I49: 12.478901 | J49: =H49-I49 -> 0 | M49: Q2 | N49: 12.478901 | P49: 12 Sep 77 | Q49: 6.5 | S49: 27436 | T49: 10.75
C50: Q3 | D50: 11.570217 | H50: =SUM(D50:G50) -> 11.570217 | I50: 11.570217 | J50: =H50-I50 -> 0 | M50: Q3 | N50: 11.570217 | P50: 19 Sep 77 | Q50: 6 | S50: 27437 | T50: 10.75
C51: Q4 | D51: 11.38 | H51: =SUM(D51:G51) -> 11.38 | I51: 11.38 | J51: =H51-I51 -> 0 | M51: Q4 | N51: 11.38 | P51: 10 Oct 77 | Q51: 5.5 | S51: 27438 | T51: 10.75
B52: 1986 | C52: Q1 | D52: 12.08 | H52: =SUM(D52:G52) -> 12.08 | I52: 12.08 | J52: =H52-I52 -> 0 | L52: 1986 | M52: Q1 | N52: 12.08 | P52: 17 Oct 77 | Q52: 5 | S52: 27439 | T52: 10.75
C53: Q2 | D53: 10.314066 | H53: =SUM(D53:G53) -> 10.314066 | I53: 10.314066 | J53: =H53-I53 -> 0 | M53: Q2 | N53: 10.314066 | P53: 28 Nov 77 | Q53: 7 | S53: 27440 | T53: 10.75
C54: Q3 | D54: 9.88 | H54: =SUM(D54:G54) -> 9.88 | I54: 9.88 | J54: =H54-I54 -> 0 | M54: Q3 | N54: 9.88 | P54: 09 Jan 78 | Q54: 6.5 | S54: 27441 | T54: 10.75
C55: Q4 | D55: 10.727826 | H55: =SUM(D55:G55) -> 10.727826 | I55: 10.727826 | J55: =H55-I55 -> 0 | M55: Q4 | N55: 10.727826 | P55: 12 Apr 78 | Q55: 7.5 | S55: 27442 | T55: 10.5
B56: 1987 | C56: Q1 | D56: 10.674444 | H56: =SUM(D56:G56) -> 10.674444 | I56: 10.674444 | J56: =H56-I56 -> 0 | L56: 1987 | M56: Q1 | N56: 10.674444 | P56: 08 May 78 | Q56: 8.75 | S56: 27443 | T56: 10.5
C57: Q2 | D57: 9.2316484 | H57: =SUM(D57:G57) -> 9.2316484 | I57: 9.2316484 | J57: =H57-I57 -> 0 | M57: Q2 | N57: 9.2316484 | P57: 15 May 78 | Q57: 9 | S57: 27444 | T57: 10.5
C58: Q3 | D58: 9.4886957 | H58: =SUM(D58:G58) -> 9.4886957 | I58: 9.4886957 | J58: =H58-I58 -> 0 | M58: Q3 | N58: 9.4886957 | P58: 08 Jun 78 | Q58: 10 | S58: 27445 | T58: 10.5
C59: Q4 | D59: 9.0267391 | H59: =SUM(D59:G59) -> 9.0267391 | I59: 9.0267391 | J59: =H59-I59 -> 0 | M59: Q4 | N59: 9.0267391 | P59: 09 Nov 78 | Q59: 12.5 | S59: 27446 | T59: 10.5
B60: 1988 | C60: Q1 | D60: 8.6272527 | H60: =SUM(D60:G60) -> 8.6272527 | I60: 8.6272527 | J60: =H60-I60 -> 0 | L60: 1988 | M60: Q1 | N60: 8.6272527 | P60: 08 Feb 79 | Q60: 14 | S60: 27447 | T60: 10.5
C61: Q2 | D61: 7.9789011 | H61: =SUM(D61:G61) -> 7.9789011 | I61: 7.9789011 | J61: =H61-I61 -> 0 | M61: Q2 | N61: 7.9789011 | P61: 01 Mar 79 | Q61: 13 | S61: 27448 | T61: 10.5
C62: Q3 | D62: 10.901739 | H62: =SUM(D62:G62) -> 10.901739 | I62: 10.901739 | J62: =H62-I62 -> 0 | M62: Q3 | N62: 10.901739 | P62: 05 Apr 79 | Q62: 12 | S62: 27449 | T62: 10.5
C63: Q4 | D63: 12.282174 | H63: =SUM(D63:G63) -> 12.282174 | I63: 12.282174 | J63: =H63-I63 -> 0 | M63: Q4 | N63: 12.282174 | P63: 13 Jun 79 | Q63: 14 | S63: 27450 | T63: 10.5
B64: 1989 | C64: Q1 | D64: 12.88 | H64: =SUM(D64:G64) -> 12.88 | I64: 12.88 | J64: =H64-I64 -> 0 | L64: 1989 | M64: Q1 | N64: 12.88 | P64: 15 Nov 79 | Q64: 17 | S64: 27451 | T64: 10.5
C65: Q2 | D65: 13.233736 | H65: =SUM(D65:G65) -> 13.233736 | I65: 13.233736 | J65: =H65-I65 -> 0 | M65: Q2 | N65: 13.233736 | P65: 03 Jul 80 | Q65: 16 | S65: 27452 | T65: 10.5
C66: Q3 | D66: 13.759565 | H66: =SUM(D66:G66) -> 13.759565 | I66: 13.759565 | J66: =H66-I66 -> 0 | M66: Q3 | N66: 13.759565 | P66: 25 Nov 80 | Q66: 14 | S66: 27453 | T66: 10.5
C67: Q4 | D67: 14.818587 | H67: =SUM(D67:G67) -> 14.818587 | I67: 14.818587 | J67: =H67-I67 -> 0 | M67: Q4 | N67: 14.818587 | P67: 11 Mar 81 | Q67: 12 | S67: 27454 | T67: 10.5
B68: 1990 | C68: Q1 | D68: 14.88 | H68: =SUM(D68:G68) -> 14.88 | I68: 14.88 | J68: =H68-I68 -> 0 | L68: 1990 | M68: Q1 | N68: 14.88 | P68: 25 Aug 81 | Q68: 12.69 | S68: 27455 | T68: 10.5
C69: Q2 | D69: 14.88 | H69: =SUM(D69:G69) -> 14.88 | I69: 14.88 | J69: =H69-I69 -> 0 | M69: Q2 | N69: 14.88 | P69: 15 Sep 81 | Q69: 14 | S69: 27456 | T69: 10.5
C70: Q3 | D70: 14.88 | H70: =SUM(D70:G70) -> 14.88 | I70: 14.88 | J70: =H70-I70 -> 0 | M70: Q3 | N70: 14.88 | P70: 12 Oct 81 | Q70: 15 | S70: 27457 | T70: 10.5
C71: Q4 | D71: 13.956087 | H71: =SUM(D71:G71) -> 13.956087 | I71: 13.956087 | J71: =H71-I71 -> 0 | M71: Q4 | N71: 13.956087 | P71: 28 Oct 81 | Q71: 15.13 | S71: 27458 | T71: 10.5
B72: 1991 | C72: Q1 | D72: 13.38 | H72: =SUM(D72:G72) -> 13.38 | I72: 13.38 | J72: =H72-I72 -> 0 | L72: 1991 | M72: Q1 | N72: 13.38 | P72: 06 Nov 81 | Q72: 15.06 | S72: 27459 | T72: 10.5
C73: Q2 | D73: 11.731648 | H73: =SUM(D73:G73) -> 11.731648 | I73: 11.731648 | J73: =H73-I73 -> 0 | M73: Q2 | N73: 11.731648 | P73: 09 Nov 81 | Q73: 14.63 | S73: 27460 | T73: 10.5
C74: Q3 | D74: 10.793043 | H74: =SUM(D74:G74) -> 10.793043 | I74: 10.793043 | J74: =H74-I74 -> 0 | M74: Q3 | N74: 10.793043 | P74: 25 Nov 81 | Q74: 14.56 | S74: 27461 | T74: 10.5
C75: Q4 | D75: 10.38 | H75: =SUM(D75:G75) -> 10.38 | I75: 10.38 | J75: =H75-I75 -> 0 | M75: Q4 | N75: 10.38 | P75: 04 Dec 81 | Q75: 14.38 | S75: 27462 | T75: 10.5
B76: 1992 | C76: Q1 | D76: 10.38 | H76: =SUM(D76:G76) -> 10.38 | I76: 10.38 | J76: =H76-I76 -> 0 | L76: 1992 | M76: Q1 | N76: 10.38 | P76: 18 Jan 82 | Q76: 14.31 | S76: 27463 | T76: 10.25
C77: Q2 | D77: 10.066813 | H77: =SUM(D77:G77) -> 10.066813 | I77: 10.066813 | J77: =H77-I77 -> 0 | M77: Q2 | N77: 10.066813 | P77: 19 Jan 82 | Q77: 14.25 | S77: 27464 | T77: 10.25
C78: Q3 | D78: 9.7821739 | H78: =SUM(D78:G78) -> 9.7821739 | I78: 9.7821739 | J78: =H78-I78 -> 0 | M78: Q3 | N78: 9.7821739 | P78: 20 Jan 82 | Q78: 14.13 | S78: 27465 | T78: 10.25
C79: Q4 | D79: 7.5104348 | H79: =SUM(D79:G79) -> 7.5104348 | I79: 7.5104348 | J79: =H79-I79 -> 0 | M79: Q4 | N79: 7.5104348 | P79: 21 Jan 82 | Q79: 14 | S79: 27466 | T79: 10.25
B80: 1993 | C80: Q1 | D80: 6.1577778 | H80: =SUM(D80:G80) -> 6.1577778 | I80: 6.1577778 | J80: =H80-I80 -> 0 | L80: 1993 | M80: Q1 | N80: 6.1577778 | P80: 22 Jan 82 | Q80: 13.88 | S80: 27467 | T80: 10.25
C81: Q2 | D81: 5.88 | H81: =SUM(D81:G81) -> 5.88 | I81: 5.88 | J81: =H81-I81 -> 0 | M81: Q2 | N81: 5.88 | P81: 22 Feb 82 | Q81: 13.81 | S81: 27468 | T81: 10.25
C82: Q3 | D82: 5.88 | H82: =SUM(D82:G82) -> 5.88 | I82: 5.88 | J82: =H82-I82 -> 0 | M82: Q3 | N82: 5.88 | P82: 25 Feb 82 | Q82: 13.63 | S82: 27469 | T82: 10.25
C83: Q4 | D83: 5.6680435 | H83: =SUM(D83:G83) -> 5.6680435 | I83: 5.6680435 | J83: =H83-I83 -> 0 | M83: Q4 | N83: 5.6680435 | P83: 10 Mar 82 | Q83: 13.25 | S83: 27470 | T83: 10.25
B84: 1994 | C84: Q1 | D84: 5.2355556 | H84: =SUM(D84:G84) -> 5.2355556 | I84: 5.2355556 | J84: =H84-I84 -> 0 | L84: 1994 | M84: Q1 | N84: 5.2355556 | P84: 16 Apr 82 | Q84: 13.13 | S84: 27471 | T84: 10.25
C85: Q2 | D85: 5.13 | H85: =SUM(D85:G85) -> 5.13 | I85: 5.13 | J85: =H85-I85 -> 0 | M85: Q2 | N85: 5.13 | P85: 19 Apr 82 | Q85: 13 | S85: 27472 | T85: 10.25
C86: Q3 | D86: 5.2332609 | H86: =SUM(D86:G86) -> 5.2332609 | I86: 5.2332609 | J86: =H86-I86 -> 0 | M86: Q3 | N86: 5.2332609 | P86: 20 Apr 82 | Q86: 13.13 | S86: 27473 | T86: 10.25
C87: Q4 | D87: 5.7658696 | H87: =SUM(D87:G87) -> 5.7658696 | I87: 5.7658696 | J87: =H87-I87 -> 0 | M87: Q4 | N87: 5.7658696 | P87: 08 Jun 82 | Q87: 12.63 | S87: 27474 | T87: 10.25
B88: 1995 | C88: Q1 | D88: 6.4522222 | H88: =SUM(D88:G88) -> 6.4522222 | I88: 6.4522222 | J88: =H88-I88 -> 0 | L88: 1995 | M88: Q1 | N88: 6.4522222 | P88: 09 Jul 82 | Q88: 12.5 | S88: 27475 | T88: 10.25
C89: Q2 | D89: 6.63 | H89: =SUM(D89:G89) -> 6.63 | I89: 6.63 | J89: =H89-I89 -> 0 | M89: Q2 | N89: 6.63 | P89: 12 Jul 82 | Q89: 12.25 | S89: 27476 | T89: 10.25
C90: Q3 | D90: 6.63 | H90: =SUM(D90:G90) -> 6.63 | I90: 6.63 | J90: =H90-I90 -> 0 | M90: Q3 | N90: 6.63 | P90: 13 Jul 82 | Q90: 12.13 | S90: 27477 | T90: 10
C91: Q4 | D91: 6.5783696 | H91: =SUM(D91:G91) -> 6.5783696 | I91: 6.5783696 | J91: =H91-I91 -> 0 | M91: Q4 | N91: 6.5783696 | P91: 21 Jul 82 | Q91: 12.06 | S91: 27478 | T91: 10
B92: 1996 | C92: Q1 | D92: 6.1265934 | H92: =SUM(D92:G92) -> 6.1265934 | I92: 6.1265934 | J92: =H92-I92 -> 0 | L92: 1996 | M92: Q1 | N92: 6.1265934 | P92: 26 Jul 82 | Q92: 11.94 | S92: 27479 | T92: 10
C93: Q2 | D93: 5.8713187 | H93: =SUM(D93:G93) -> 5.8713187 | I93: 5.8713187 | J93: =H93-I93 -> 0 | M93: Q2 | N93: 5.8713187 | P93: 28 Jul 82 | Q93: 11.81 | S93: 27480 | T93: 10
C94: Q3 | D94: 5.69 | H94: =SUM(D94:G94) -> 5.69 | I94: 5.69 | J94: =H94-I94 -> 0 | M94: Q3 | N94: 5.69 | P94: 29 Jul 82 | Q94: 11.75 | S94: 27481 | T94: 10
C95: Q4 | D95: 5.8611957 | H95: =SUM(D95:G95) -> 5.8611957 | I95: 5.8611957 | J95: =H95-I95 -> 0 | M95: Q4 | N95: 5.8611957 | P95: 30 Jul 82 | Q95: 11.63 | S95: 27482 | T95: 10
B96: 1997 | C96: Q1 | D96: 5.94 | H96: =SUM(D96:G96) -> 5.94 | I96: 5.94 | J96: =H96-I96 -> 0 | L96: 1997 | M96: Q1 | N96: 5.94 | P96: 02 Aug 82 | Q96: 11.56 | S96: 27483 | T96: 10
C97: Q2 | D97: 6.1994505 | H97: =SUM(D97:G97) -> 6.1994505 | I97: 6.1994505 | J97: =H97-I97 -> 0 | M97: Q2 | N97: 6.1994505 | P97: 04 Aug 82 | Q97: 11.5 | S97: 27484 | T97: 10 | U97: =AVERAGE(T8:T97) -> 10.783333
C98: Q3 | D98: 6.875 | H98: =SUM(D98:G98) -> 6.875 | I98: 6.875 | J98: =H98-I98 -> 0 | M98: Q3 | N98: 6.875 | P98: 16 Aug 82 | Q98: 11.38 | S98: 27485 | T98: 10
C99: Q4 | D99: 7.1521739 | H99: =SUM(D99:G99) -> 7.1521739 | I99: 7.1521739 | J99: =H99-I99 -> 0 | M99: Q4 | N99: 7.1521739 | P99: 17 Aug 82 | Q99: 11.25 | S99: 27486 | T99: 10
B100: 1998 | C100: Q1 | D100: 7.25 | H100: =SUM(D100:G100) -> 7.25 | I100: 7.25 | J100: =H100-I100 -> 0 | L100: 1998 | M100: Q1 | N100: 7.25 | P100: 24 Aug 82 | Q100: 11.13 | S100: 27487 | T100: 10
C101: Q2 | D101: 7.3241758 | H101: =SUM(D101:G101) -> 7.3241758 | I101: 7.3241758 | J101: =H101-I101 -> 0 | M101: Q2 | N101: 7.3241758 | P101: 25 Aug 82 | Q101: 11 | S101: 27488 | T101: 10
C102: Q3 | D102: 7.5 | H102: =SUM(D102:G102) -> 7.5 | I102: 7.5 | J102: =H102-I102 -> 0 | M102: Q3 | N102: 7.5 | P102: 26 Aug 82 | Q102: 10.88 | S102: 27489 | T102: 10
...

Sheet House price (income) deflator
D3: Cat 1 | E3: Cat 2 | F3: Cat 3 | G3: Cat4 | H3: Updated | I3: Previous | J3: Difference
B4: Notes 1 | D4: HH & NPISH: Disposable income at chained volume measures (ref 2019), constant price, SA [ONS] | E4: HH & NPISH: Disposable income, gross, current price, SA [ONS] | H4: Cat 1 / Cat 2
B5: Notes 2 | D5: NRJR 2019 base year | E5: RPHQ | H5: 2019 base year | I5: 2017? base year
B6: Link | D6: HH & NPISH (S.14 + S.15): Real Households' & NPISH disposable income at chained volume measures (reference year 2019)(1):CP:£m:SA - Office for National Statistics (ons.gov.uk)
B7: Table
B8: 1975 | C8: Q1 | D8: 137874 | E8: 18231 | H8: =E8/D8*100 -> 13.222943 | I8: 14.78484 | J8: =H8-I8 -> -1.5618973
C9: Q2 | D9: 133846 | E9: 18617 | H9: =E9/D9*100 -> 13.909269 | I9: 15.586287 | J9: =H9-I9 -> -1.6770185
C10: Q3 | D10: 135538 | E10: 19568 | H10: =E10/D10*100 -> 14.43728 | I10: 16.210535 | J10: =H10-I10 -> -1.7732554
C11: Q4 | D11: 133270 | E11: 20196 | H11: =E11/D11*100 -> 15.154198 | I11: 17.033271 | J11: =H11-I11 -> -1.879073
B12: 1976 | C12: Q1 | D12: 135164 | E12: 21297 | H12: =E12/D12*100 -> 15.756414 | I12: 17.714087 | J12: =H12-I12 -> -1.9576722
C13: Q2 | D13: 133533 | E13: 21572 | H13: =E13/D13*100 -> 16.154808 | I13: 18.14758 | J13: =H13-I13 -> -1.9927714
C14: Q3 | D14: 137523 | E14: 22880 | H14: =E14/D14*100 -> 16.637217 | I14: 18.640226 | J14: =H14-I14 -> -2.0030091
C15: Q4 | D15: 133454 | E15: 23452 | H15: =E15/D15*100 -> 17.573096 | I15: 19.612306 | J15: =H15-I15 -> -2.0392098
B16: 1977 | C16: Q1 | D16: 130916 | E16: 23884 | H16: =E16/D16*100 -> 18.243759 | I16: 20.504241 | J16: =H16-I16 -> -2.2604812
C17: Q2 | D17: 129464 | E17: 24513 | H17: =E17/D17*100 -> 18.934221 | I17: 21.202712 | J17: =H17-I17 -> -2.2684907
C18: Q3 | D18: 131751 | E18: 25443 | H18: =E18/D18*100 -> 19.311428 | I18: 21.58865 | J18: =H18-I18 -> -2.2772215
C19: Q4 | D19: 137135 | E19: 26944 | H19: =E19/D19*100 -> 19.647792 | I19: 21.958592 | J19: =H19-I19 -> -2.3107997
B20: 1978 | C20: Q1 | D20: 136777 | E20: 27799 | H20: =E20/D20*100 -> 20.324324 | I20: 22.662608 | J20: =H20-I20 -> -2.3382847
C21: Q2 | D21: 140847 | E21: 29146 | H21: =E21/D21*100 -> 20.693377 | I21: 23.085561 | J21: =H21-I21 -> -2.3921842
C22: Q3 | D22: 144584 | E22: 30469 | H22: =E22/D22*100 -> 21.073563 | I22: 23.530591 | J22: =H22-I22 -> -2.4570282
C23: Q4 | D23: 144501 | E23: 31467 | H23: =E23/D23*100 -> 21.77632 | I23: 24.31828 | J23: =H23-I23 -> -2.5419601
B24: 1979 | C24: Q1 | D24: 146093 | E24: 32865 | H24: =E24/D24*100 -> 22.495944 | I24: 25.058601 | J24: =H24-I24 -> -2.5626571
C25: Q2 | D25: 148612 | E25: 34145 | H25: =E25/D25*100 -> 22.975937 | I25: 25.577587 | J25: =H25-I25 -> -2.60165
C26: Q3 | D26: 148613 | E26: 36471 | H26: =E26/D26*100 -> 24.540922 | I26: 27.291466 | J26: =H26-I26 -> -2.7505442
C27: Q4 | D27: 155340 | E27: 39786 | H27: =E27/D27*100 -> 25.612205 | I27: 28.493609 | J27: =H27-I27 -> -2.8814035
B28: 1980 | C28: Q1 | D28: 150565 | E28: 40242 | H28: =E28/D28*100 -> 26.727327 | I28: 29.655314 | J28: =H28-I28 -> -2.9279874
C29: Q2 | D29: 150941 | E29: 41768 | H29: =E29/D29*100 -> 27.671739 | I29: 30.710868 | J29: =H29-I29 -> -3.0391292
C30: Q3 | D30: 153176 | E30: 43385 | H30: =E30/D30*100 -> 28.323628 | I30: 31.431691 | J30: =H30-I30 -> -3.1080628
C31: Q4 | D31: 151565 | E31: 44816 | H31: =E31/D31*100 -> 29.568832 | I31: 32.76755 | J31: =H31-I31 -> -3.1987179
B32: 1981 | C32: Q1 | D32: 152206 | E32: 46336 | H32: =E32/D32*100 -> 30.442952 | I32: 33.690542 | J32: =H32-I32 -> -3.2475895
C33: Q2 | D33: 149759 | E33: 46816 | H33: =E33/D33*100 -> 31.260893 | I33: 34.524125 | J33: =H33-I33 -> -3.2632324
C34: Q3 | D34: 149212 | E34: 47698 | H34: =E34/D34*100 -> 31.966598 | I34: 35.280398 | J34: =H34-I34 -> -3.3138001
C35: Q4 | D35: 150082 | E35: 49617 | H35: =E35/D35*100 -> 33.059927 | I35: 36.464947 | J35: =H35-I35 -> -3.4050199
B36: 1982 | C36: Q1 | D36: 148370 | E36: 50445 | H36: =E36/D36*100 -> 33.999461 | I36: 37.424589 | J36: =H36-I36 -> -3.4251282
C37: Q2 | D37: 150930 | E37: 51986 | H37: =E37/D37*100 -> 34.443782 | I37: 37.843827 | J37: =H37-I37 -> -3.4000449
C38: Q3 | D38: 149876 | E38: 52217 | H38: =E38/D38*100 -> 34.840135 | I38: 38.280421 | J38: =H38-I38 -> -3.4402866
C39: Q4 | D39: 150147 | E39: 53560 | H39: =E39/D39*100 -> 35.671708 | I39: 39.125174 | J39: =H39-I39 -> -3.4534656
B40: 1983 | C40: Q1 | D40: 149047 | E40: 54244 | H40: =E40/D40*100 -> 36.393889 | I40: 39.814306 | J40: =H40-I40 -> -3.4204171
C41: Q2 | D41: 156082 | E41: 56864 | H41: =E41/D41*100 -> 36.432132 | I41: 40.118129 | J41: =H41-I41 -> -3.6859973
C42: Q3 | D42: 152323 | E42: 56839 | H42: =E42/D42*100 -> 37.314785 | I42: 40.497789 | J42: =H42-I42 -> -3.183004
C43: Q4 | D43: 153973 | E43: 57922 | H43: =E43/D43*100 -> 37.618284 | I43: 41.091915 | J43: =H43-I43 -> -3.4736317
B44: 1984 | C44: Q1 | D44: 156311 | E44: 59641 | H44: =E44/D44*100 -> 38.155344 | I44: 41.582188 | J44: =H44-I44 -> -3.4268441
C45: Q2 | D45: 154770 | E45: 59936 | H45: =E45/D45*100 -> 38.725851 | I45: 42.305715 | J45: =H45-I45 -> -3.5798637
C46: Q3 | D46: 157723 | E46: 62344 | H46: =E46/D46*100 -> 39.527526 | I46: 42.783286 | J46: =H46-I46 -> -3.2557602
C47: Q4 | D47: 161367 | E47: 64545 | H47: =E47/D47*100 -> 39.998885 | I47: 43.33523 | J47: =H47-I47 -> -3.3363456
B48: 1985 | C48: Q1 | D48: 161907 | E48: 65225 | H48: =E48/D48*100 -> 40.285473 | I48: 43.268442 | J48: =H48-I48 -> -2.9829693
C49: Q2 | D49: 165521 | E49: 66396 | H49: =E49/D49*100 -> 40.113339 | I49: 43.934703 | J49: =H49-I49 -> -3.8213642
C50: Q3 | D50: 162436 | E50: 67479 | H50: =E50/D50*100 -> 41.5419 | I50: 44.560742 | J50: =H50-I50 -> -3.0188429
C51: Q4 | D51: 164361 | E51: 68969 | H51: =E51/D51*100 -> 41.961901 | I51: 45.229208 | J51: =H51-I51 -> -3.2673075
B52: 1986 | C52: Q1 | D52: 166220 | E52: 70315 | H52: =E52/D52*100 -> 42.30237 | I52: 45.445115 | J52: =H52-I52 -> -3.1427442
C53: Q2 | D53: 173839 | E53: 73709 | H53: =E53/D53*100 -> 42.400727 | I53: 45.865805 | J53: =H53-I53 -> -3.4650775
C54: Q3 | D54: 169356 | E54: 73119 | H54: =E54/D54*100 -> 43.174733 | I54: 46.364498 | J54: =H54-I54 -> -3.1897659
C55: Q4 | D55: 168232 | E55: 74157 | H55: =E55/D55*100 -> 44.080199 | I55: 46.938042 | J55: =H55-I55 -> -2.8578429
B56: 1987 | C56: Q1 | D56: 165809 | E56: 74135 | H56: =E56/D56*100 -> 44.711083 | I56: 47.592992 | J56: =H56-I56 -> -2.8819083
C57: Q2 | D57: 170664 | E57: 76557 | H57: =E57/D57*100 -> 44.858318 | I57: 48.059878 | J57: =H57-I57 -> -3.2015595
C58: Q3 | D58: 172318 | E58: 78288 | H58: =E58/D58*100 -> 45.432282 | I58: 48.486149 | J58: =H58-I58 -> -3.0538672
C59: Q4 | D59: 175407 | E59: 79789 | H59: =E59/D59*100 -> 45.487922 | I59: 49.063791 | J59: =H59-I59 -> -3.5758688
B60: 1988 | C60: Q1 | D60: 176973 | E60: 82268 | H60: =E60/D60*100 -> 46.486187 | I60: 49.811212 | J60: =H60-I60 -> -3.325025
C61: Q2 | D61: 178237 | E61: 84814 | H61: =E61/D61*100 -> 47.584957 | I61: 50.474048 | J61: =H61-I61 -> -2.889091
C62: Q3 | D62: 180765 | E62: 86563 | H62: =E62/D62*100 -> 47.887036 | I62: 50.948276 | J62: =H62-I62 -> -3.0612402
C63: Q4 | D63: 182942 | E63: 88239 | H63: =E63/D63*100 -> 48.23332 | I63: 51.523867 | J63: =H63-I63 -> -3.2905474
B64: 1989 | C64: Q1 | D64: 184742 | E64: 90551 | H64: =E64/D64*100 -> 49.014842 | I64: 52.152458 | J64: =H64-I64 -> -3.1376161
C65: Q2 | D65: 185769 | E65: 93362 | H65: =E65/D65*100 -> 50.25704 | I65: 53.019218 | J65: =H65-I65 -> -2.7621781
C66: Q3 | D66: 192369 | E66: 97497 | H66: =E66/D66*100 -> 50.682282 | I66: 53.875344 | J66: =H66-I66 -> -3.1930613
C67: Q4 | D67: 189995 | E67: 98363 | H67: =E67/D67*100 -> 51.771362 | I67: 54.855992 | J67: =H67-I67 -> -3.0846297
B68: 1990 | C68: Q1 | D68: 193719 | E68: 102904 | H68: =E68/D68*100 -> 53.120241 | I68: 55.73105 | J68: =H68-I68 -> -2.6108084
C69: Q2 | D69: 193944 | E69: 103913 | H69: =E69/D69*100 -> 53.578868 | I69: 56.942955 | J69: =H69-I69 -> -3.3640865
C70: Q3 | D70: 196373 | E70: 107142 | H70: =E70/D70*100 -> 54.560454 | I70: 58.15505 | J70: =H70-I70 -> -3.5945962
C71: Q4 | D71: 198794 | E71: 110528 | H71: =E71/D71*100 -> 55.599264 | I71: 59.061849 | J71: =H71-I71 -> -3.4625859
B72: 1991 | C72: Q1 | D72: 198792 | E72: 113138 | H72: =E72/D72*100 -> 56.912753 | I72: 60.054077 | J72: =H72-I72 -> -3.1413237
C73: Q2 | D73: 195858 | E73: 113715 | H73: =E73/D73*100 -> 58.059921 | I73: 61.457387 | J73: =H73-I73 -> -3.3974659
C74: Q3 | D74: 198891 | E74: 118516 | H74: =E74/D74*100 -> 59.588418 | I74: 62.197059 | J74: =H74-I74 -> -2.6086416
C75: Q4 | D75: 200640 | E75: 119682 | H75: =E75/D75*100 -> 59.65012 | I75: 62.949777 | J75: =H75-I75 -> -3.2996573
B76: 1992 | C76: Q1 | D76: 201312 | E76: 121804 | H76: =E76/D76*100 -> 60.505087 | I76: 63.595065 | J76: =H76-I76 -> -3.0899788
C77: Q2 | D77: 203773 | E77: 123653 | H77: =E77/D77*100 -> 60.681739 | I77: 63.908133 | J77: =H77-I77 -> -3.226394
C78: Q3 | D78: 203375 | E78: 125269 | H78: =E78/D78*100 -> 61.595083 | I78: 64.208358 | J78: =H78-I78 -> -2.6132755
C79: Q4 | D79: 204437 | E79: 126305 | H79: =E79/D79*100 -> 61.781869 | I79: 64.760171 | J79: =H79-I79 -> -2.9783018
B80: 1993 | C80: Q1 | D80: 205130 | E80: 127257 | H80: =E80/D80*100 -> 62.037245 | I80: 65.6621 | J80: =H80-I80 -> -3.6248558
C81: Q2 | D81: 193040 | E81: 131721 | H81: =E81/D81*100 -> 68.235081 | I81: 66.057111 | J81: =H81-I81 -> 2.1779697
C82: Q3 | D82: 223779 | E82: 133453 | H82: =E82/D82*100 -> 59.63607 | I82: 66.315748 | J82: =H82-I82 -> -6.6796786
C83: Q4 | D83: 210322 | E83: 134977 | H83: =E83/D83*100 -> 64.176358 | I83: 66.792667 | J83: =H83-I83 -> -2.616309
B84: 1994 | C84: Q1 | D84: 210768 | E84: 134646 | H84: =E84/D84*100 -> 63.883512 | I84: 66.75001 | J84: =H84-I84 -> -2.8664981
C85: Q2 | D85: 212600 | E85: 135245 | H85: =E85/D85*100 -> 63.61477 | I85: 67.145529 | J85: =H85-I85 -> -3.5307599
C86: Q3 | D86: 209908 | E86: 138259 | H86: =E86/D86*100 -> 65.866475 | I86: 67.278103 | J86: =H86-I86 -> -1.4116285
C87: Q4 | D87: 215906 | E87: 138453 | H87: =E87/D87*100 -> 64.126518 | I87: 67.788725 | J87: =H87-I87 -> -3.6622065
B88: 1995 | C88: Q1 | D88: 216820 | E88: 141934 | H88: =E88/D88*100 -> 65.461673 | I88: 68.285969 | J88: =H88-I88 -> -2.8242955
C89: Q2 | D89: 215918 | E89: 143377 | H89: =E89/D89*100 -> 66.403449 | I89: 68.923927 | J89: =H89-I89 -> -2.520478
C90: Q3 | D90: 220034 | E90: 146523 | H90: =E90/D90*100 -> 66.591072 | I90: 69.755695 | J90: =H90-I90 -> -3.1646227
C91: Q4 | D91: 218441 | E91: 147820 | H91: =E91/D91*100 -> 67.670446 | I91: 70.056571 | J91: =H91-I91 -> -2.386125
B92: 1996 | C92: Q1 | D92: 221835 | E92: 151668 | H92: =E92/D92*100 -> 68.369734 | I92: 70.485171 | J92: =H92-I92 -> -2.1154372
C93: Q2 | D93: 221601 | E93: 153604 | H93: =E93/D93*100 -> 69.315572 | I93: 71.512732 | J93: =H93-I93 -> -2.1971604
C94: Q3 | D94: 222885 | E94: 156436 | H94: =E94/D94*100 -> 70.186868 | I94: 72.070111 | J94: =H94-I94 -> -1.8832434
C95: Q4 | D95: 220844 | E95: 154216 | H95: =E95/D95*100 -> 69.830287 | I95: 72.368409 | J95: =H95-I95 -> -2.5381214
B96: 1997 | C96: Q1 | D96: 222945 | E96: 156559 | H96: =E96/D96*100 -> 70.223149 | I96: 72.372603 | J96: =H96-I96 -> -2.1494535
C97: Q2 | D97: 225087 | E97: 159663 | H97: =E97/D97*100 -> 70.933906 | I97: 72.606233 | J97: =H97-I97 -> -1.6723279
C98: Q3 | D98: 227563 | E98: 162211 | H98: =E98/D98*100 -> 71.281799 | I98: 73.185754 | J98: =H98-I98 -> -1.903955
C99: Q4 | D99: 226783 | E99: 160980 | H99: =E99/D99*100 -> 70.984157 | I99: 73.647269 | J99: =H99-I99 -> -2.6631123
B100: 1998 | C100: Q1 | D100: 226653 | E100: 161758 | H100: =E100/D100*100 -> 71.368127 | I100: 73.39668 | J100: =H100-I100 -> -2.0285532
C101: Q2 | D101: 227698 | E101: 163323 | H101: =E101/D101*100 -> 71.727903 | I101: 73.713693 | J101: =H101-I101 -> -1.9857906
C102: Q3 | D102: 226775 | E102: 163494 | H102: =E102/D102*100 -> 72.095249 | I102: 74.245555 | J102: =H102-I102 -> -2.1503063
...

Sheet Construction cost deflator
D3: Cat 1 | E3: Cat 2 | F3: Cat 3 | G3: Cat4 | H3: Updated | I3: Previous | J3: Difference
B4: Notes 1 | D4: Implied GDP deflator at market prices, SA [ONS] | H4: Cat 1
B5: Notes 2 | D5: L8GG | H5: 2021 base year | I5: 2016?? base year
B6: Link | D6: Implied GDP deflator at market prices: SA Index - Office for National Statistics (ons.gov.uk)
B7: Table
B8: 1975 | C8: Q1 | D8: 10.9778 | H8: =D8 -> 10.9778 | I8: 13.0061 | J8: =H8-I8 -> -2.0283
C9: Q2 | D9: 11.7071 | H9: =D9 -> 11.7071 | I9: 13.8638 | J9: =H9-I9 -> -2.1567
C10: Q3 | D10: 12.2219 | H10: =D10 -> 12.2219 | I10: 14.4732 | J10: =H10-I10 -> -2.2513
C11: Q4 | D11: 12.7565 | H11: =D11 -> 12.7565 | I11: 15.1123 | J11: =H11-I11 -> -2.3558
B12: 1976 | C12: Q1 | D12: 13.1829 | H12: =D12 -> 13.1829 | I12: 15.6137 | J12: =H12-I12 -> -2.4308
C13: Q2 | D13: 13.5525 | H13: =D13 -> 13.5525 | I13: 16.0516 | J13: =H13-I13 -> -2.4991
C14: Q3 | D14: 13.8741 | H14: =D14 -> 13.8741 | I14: 16.4327 | J14: =H14-I14 -> -2.5586
C15: Q4 | D15: 14.4219 | H15: =D15 -> 14.4219 | I15: 17.0917 | J15: =H15-I15 -> -2.6698
B16: 1977 | C16: Q1 | D16: 14.9647 | H16: =D16 -> 14.9647 | I16: 17.7103 | J16: =H16-I16 -> -2.7456
C17: Q2 | D17: 15.5529 | H17: =D17 -> 15.5529 | I17: 18.4114 | J17: =H17-I17 -> -2.8585
C18: Q3 | D18: 15.8767 | H18: =D18 -> 15.8767 | I18: 18.7956 | J18: =H18-I18 -> -2.9189
C19: Q4 | D19: 16.316 | H19: =D19 -> 16.316 | I19: 19.3069 | J19: =H19-I19 -> -2.9909
B20: 1978 | C20: Q1 | D20: 16.9545 | H20: =D20 -> 16.9545 | I20: 20.0352 | J20: =H20-I20 -> -3.0807
C21: Q2 | D21: 17.4266 | H21: =D21 -> 17.4266 | I21: 20.5777 | J21: =H21-I21 -> -3.1511
C22: Q3 | D22: 17.6786 | H22: =D22 -> 17.6786 | I22: 20.8782 | J22: =H22-I22 -> -3.1996
C23: Q4 | D23: 18.1534 | H23: =D23 -> 18.1534 | I23: 21.4444 | J23: =H23-I23 -> -3.291
B24: 1979 | C24: Q1 | D24: 18.8287 | H24: =D24 -> 18.8287 | I24: 22.2206 | J24: =H24-I24 -> -3.3919
C25: Q2 | D25: 19.2827 | H25: =D25 -> 19.2827 | I25: 22.75 | J25: =H25-I25 -> -3.4673
C26: Q3 | D26: 20.7477 | H26: =D26 -> 20.7477 | I26: 24.4643 | J26: =H26-I26 -> -3.7166
C27: Q4 | D27: 21.6294 | H27: =D27 -> 21.6294 | I27: 25.5042 | J27: =H27-I27 -> -3.8748
B28: 1980 | C28: Q1 | D28: 22.724 | H28: =D28 -> 22.724 | I28: 26.7695 | J28: =H28-I28 -> -4.0455
C29: Q2 | D29: 23.7775 | H29: =D29 -> 23.7775 | I29: 28.008 | J29: =H29-I29 -> -4.2305
C30: Q3 | D30: 24.6711 | H30: =D30 -> 24.6711 | I30: 29.0602 | J30: =H30-I30 -> -4.3891
C31: Q4 | D31: 25.7582 | H31: =D31 -> 25.7582 | I31: 30.3221 | J31: =H31-I31 -> -4.5639
B32: 1981 | C32: Q1 | D32: 26.4908 | H32: =D32 -> 26.4908 | I32: 31.1644 | J32: =H32-I32 -> -4.6736
C33: Q2 | D33: 26.9733 | H33: =D33 -> 26.9733 | I33: 31.6793 | J33: =H33-I33 -> -4.706
C34: Q3 | D34: 27.4242 | H34: =D34 -> 27.4242 | I34: 32.1961 | J34: =H34-I34 -> -4.7719
C35: Q4 | D35: 28.2612 | H35: =D35 -> 28.2612 | I35: 33.1743 | J35: =H35-I35 -> -4.9131
B36: 1982 | C36: Q1 | D36: 28.956 | H36: =D36 -> 28.956 | I36: 33.9604 | J36: =H36-I36 -> -5.0044
C37: Q2 | D37: 29.2297 | H37: =D37 -> 29.2297 | I37: 34.217 | J37: =H37-I37 -> -4.9873
C38: Q3 | D38: 29.6918 | H38: =D38 -> 29.6918 | I38: 34.7551 | J38: =H38-I38 -> -5.0633
C39: Q4 | D39: 30.3211 | H39: =D39 -> 30.3211 | I39: 35.4654 | J39: =H39-I39 -> -5.1443
B40: 1983 | C40: Q1 | D40: 30.8562 | H40: =D40 -> 30.8562 | I40: 36.1186 | J40: =H40-I40 -> -5.2624
C41: Q2 | D41: 30.9348 | H41: =D41 -> 30.9348 | I41: 36.1224 | J41: =H41-I41 -> -5.1876
C42: Q3 | D42: 31.3756 | H42: =D42 -> 31.3756 | I42: 36.6038 | J42: =H42-I42 -> -5.2282
C43: Q4 | D43: 31.945 | H43: =D43 -> 31.945 | I43: 37.2155 | J43: =H43-I43 -> -5.2705
B44: 1984 | C44: Q1 | D44: 32.0195 | H44: =D44 -> 32.0195 | I44: 37.296 | J44: =H44-I44 -> -5.2765
C45: Q2 | D45: 33.008 | H45: =D45 -> 33.008 | I45: 38.3846 | J45: =H45-I45 -> -5.3766
C46: Q3 | D46: 33.2646 | H46: =D46 -> 33.2646 | I46: 38.671 | J46: =H46-I46 -> -5.4064
C47: Q4 | D47: 33.7681 | H47: =D47 -> 33.7681 | I47: 39.2284 | J47: =H47-I47 -> -5.4603
B48: 1985 | C48: Q1 | D48: 33.8297 | H48: =D48 -> 33.8297 | I48: 39.2568 | J48: =H48-I48 -> -5.4271
C49: Q2 | D49: 34.7102 | H49: =D49 -> 34.7102 | I49: 40.1835 | J49: =H49-I49 -> -5.4733
C50: Q3 | D50: 35.2137 | H50: =D50 -> 35.2137 | I50: 40.7604 | J50: =H50-I50 -> -5.5467
C51: Q4 | D51: 35.9104 | H51: =D51 -> 35.9104 | I51: 41.5284 | J51: =H51-I51 -> -5.618
B52: 1986 | C52: Q1 | D52: 35.9949 | H52: =D52 -> 35.9949 | I52: 41.6108 | J52: =H52-I52 -> -5.6159
C53: Q2 | D53: 36.4128 | H53: =D53 -> 36.4128 | I53: 41.9413 | J53: =H53-I53 -> -5.5285
C54: Q3 | D54: 36.8573 | H54: =D54 -> 36.8573 | I54: 42.438 | J54: =H54-I54 -> -5.5807
C55: Q4 | D55: 37.4189 | H55: =D55 -> 37.4189 | I55: 42.9654 | J55: =H55-I55 -> -5.5465
B56: 1987 | C56: Q1 | D56: 37.8694 | H56: =D56 -> 37.8694 | I56: 43.5282 | J56: =H56-I56 -> -5.6588
C57: Q2 | D57: 38.5077 | H57: =D57 -> 38.5077 | I57: 44.2441 | J57: =H57-I57 -> -5.7364
C58: Q3 | D58: 39.1525 | H58: =D58 -> 39.1525 | I58: 44.9306 | J58: =H58-I58 -> -5.7781
C59: Q4 | D59: 39.5653 | H59: =D59 -> 39.5653 | I59: 45.3713 | J59: =H59-I59 -> -5.806
B60: 1988 | C60: Q1 | D60: 39.955 | H60: =D60 -> 39.955 | I60: 45.8827 | J60: =H60-I60 -> -5.9277
C61: Q2 | D61: 40.7764 | H61: =D61 -> 40.7764 | I61: 46.5793 | J61: =H61-I61 -> -5.8029
C62: Q3 | D62: 41.6271 | H62: =D62 -> 41.6271 | I62: 47.4568 | J62: =H62-I62 -> -5.8297
C63: Q4 | D63: 42.6328 | H63: =D63 -> 42.6328 | I63: 48.6395 | J63: =H63-I63 -> -6.0067
B64: 1989 | C64: Q1 | D64: 43.3473 | H64: =D64 -> 43.3473 | I64: 49.4464 | J64: =H64-I64 -> -6.0991
C65: Q2 | D65: 43.9994 | H65: =D65 -> 43.9994 | I65: 50.0036 | J65: =H65-I65 -> -6.0042
C66: Q3 | D66: 45.2101 | H66: =D66 -> 45.2101 | I66: 51.3511 | J66: =H66-I66 -> -6.141
C67: Q4 | D67: 46.1388 | H67: =D67 -> 46.1388 | I67: 52.4502 | J67: =H67-I67 -> -6.3114
B68: 1990 | C68: Q1 | D68: 46.9188 | H68: =D68 -> 46.9188 | I68: 53.117 | J68: =H68-I68 -> -6.1982
C69: Q2 | D69: 47.8913 | H69: =D69 -> 47.8913 | I69: 54.3022 | J69: =H69-I69 -> -6.4109
C70: Q3 | D70: 49.3666 | H70: =D70 -> 49.3666 | I70: 55.9026 | J70: =H70-I70 -> -6.536
C71: Q4 | D71: 49.6666 | H71: =D71 -> 49.6666 | I71: 56.2514 | J71: =H71-I71 -> -6.5848
B72: 1991 | C72: Q1 | D72: 50.8122 | H72: =D72 -> 50.8122 | I72: 57.423 | J72: =H72-I72 -> -6.6108
C73: Q2 | D73: 51.5787 | H73: =D73 -> 51.5787 | I73: 58.1788 | J73: =H73-I73 -> -6.6001
C74: Q3 | D74: 52.2071 | H74: =D74 -> 52.2071 | I74: 58.8416 | J74: =H74-I74 -> -6.6345
C75: Q4 | D75: 52.8926 | H75: =D75 -> 52.8926 | I75: 59.5973 | J75: =H75-I75 -> -6.7047
B76: 1992 | C76: Q1 | D76: 53.4255 | H76: =D76 -> 53.4255 | I76: 60.1207 | J76: =H76-I76 -> -6.6952
C77: Q2 | D77: 53.718 | H77: =D77 -> 53.718 | I77: 60.3233 | J77: =H77-I77 -> -6.6053
C78: Q3 | D78: 53.5477 | H78: =D78 -> 53.5477 | I78: 60.0962 | J78: =H78-I78 -> -6.5485
C79: Q4 | D79: 54.1034 | H79: =D79 -> 54.1034 | I79: 60.6598 | J79: =H79-I79 -> -6.5564
B80: 1993 | C80: Q1 | D80: 55.1164 | H80: =D80 -> 55.1164 | I80: 61.6492 | J80: =H80-I80 -> -6.5328
C81: Q2 | D81: 54.9872 | H81: =D81 -> 54.9872 | I81: 61.4903 | J81: =H81-I81 -> -6.5031
C82: Q3 | D82: 55.5651 | H82: =D82 -> 55.5651 | I82: 62.1011 | J82: =H82-I82 -> -6.536
C83: Q4 | D83: 55.9242 | H83: =D83 -> 55.9242 | I83: 62.4327 | J83: =H83-I83 -> -6.5085
B84: 1994 | C84: Q1 | D84: 56.2623 | H84: =D84 -> 56.2623 | I84: 62.6076 | J84: =H84-I84 -> -6.3453
C85: Q2 | D85: 56.1132 | H85: =D85 -> 56.1132 | I85: 62.4334 | J85: =H85-I85 -> -6.3202
C86: Q3 | D86: 56.1499 | H86: =D86 -> 56.1499 | I86: 62.4254 | J86: =H86-I86 -> -6.2755
C87: Q4 | D87: 57.0215 | H87: =D87 -> 57.0215 | I87: 63.3687 | J87: =H87-I87 -> -6.3472
B88: 1995 | C88: Q1 | D88: 57.205 | H88: =D88 -> 57.205 | I88: 63.4094 | J88: =H88-I88 -> -6.2044
C89: Q2 | D89: 57.764 | H89: =D89 -> 57.764 | I89: 63.9639 | J89: =H89-I89 -> -6.1999
C90: Q3 | D90: 58.2673 | H90: =D90 -> 58.2673 | I90: 64.5044 | J90: =H90-I90 -> -6.2371
C91: Q4 | D91: 58.8322 | H91: =D91 -> 58.8322 | I91: 65.1181 | J91: =H91-I91 -> -6.2859
B92: 1996 | C92: Q1 | D92: 59.609 | H92: =D92 -> 59.609 | I92: 65.7792 | J92: =H92-I92 -> -6.1702
C93: Q2 | D93: 60.7563 | H93: =D93 -> 60.7563 | I93: 66.9533 | J93: =H93-I93 -> -6.197
C94: Q3 | D94: 61.2501 | H94: =D94 -> 61.2501 | I94: 67.3717 | J94: =H94-I94 -> -6.1216
C95: Q4 | D95: 61.6322 | H95: =D95 -> 61.6322 | I95: 67.3848 | J95: =H95-I95 -> -5.7526
B96: 1997 | C96: Q1 | D96: 60.5473 | H96: =D96 -> 60.5473 | I96: 66.7897 | J96: =H96-I96 -> -6.2424
C97: Q2 | D97: 60.5804 | H97: =D97 -> 60.5804 | I97: 66.9235 | J97: =H97-I97 -> -6.3431
C98: Q3 | D98: 61.8046 | H98: =D98 -> 61.8046 | I98: 68.4764 | J98: =H98-I98 -> -6.6718
C99: Q4 | D99: 60.705 | H99: =D99 -> 60.705 | I99: 67.2188 | J99: =H99-I99 -> -6.5138
B100: 1998 | C100: Q1 | D100: 61.2826 | H100: =D100 -> 61.2826 | I100: 67.6576 | J100: =H100-I100 -> -6.375
C101: Q2 | D101: 61.5423 | H101: =D101 -> 61.5423 | I101: 67.7003 | J101: =H101-I101 -> -6.158
C102: Q3 | D102: 62.1222 | H102: =D102 -> 62.1222 | I102: 67.8501 | J102: =H102-I102 -> -5.7279
...
